Workbook

Sheet Summary
A1: PIPELINE OVERVIEW
A2: Metric | B2: Value
A3: Total Scraped Profiles | B3: =COUNTA(Profiles!A:A)-1 -> 609
A4: Total Classified | B4: =COUNTA('Classified Leads'!A:A)-1 -> 285
A5: Unclassified (Pending) | B5: =MAX(0,(COUNTA(Profiles!A:A)-1)-(COUNTA('Classified Leads'!A:A)-1)) -> 324
A6: Classification Progress % | B6: =IF(COUNTA(Profiles!A:A)-1>0,(COUNTA('Classified Leads'!A:A)-1)/(COUNTA(Profiles!A:A)-1),0) -> 0.4679803
A7: Total Relevant Leads | B7: =COUNTA('Relevant Leads'!A:A)-1 -> 92
A8: Relevance Rate % | B8: =IF(COUNTA('Classified Leads'!A:A)-1>0,(COUNTA('Relevant Leads'!A:A)-1)/(COUNTA('Classified Leads'!A:A)-1),0) -> 0.32280702
A10: CLASSIFICATION BREAKDOWN
A11: Classification | B11: Count | C11: % of Total
A12: Collector | B12: =COUNTIF('Classified Leads'!R:R,"collector") -> 46 | C12: =IF(B4>0,B12/B4,0) -> 0.16140351
A13: Dealer | B13: =COUNTIF('Classified Leads'!R:R,"dealer") -> 27 | C13: =IF(B4>0,B13/B4,0) -> 0.094736842
A14: Enthusiast | B14: =COUNTIF('Classified Leads'!R:R,"enthusiast") -> 19 | C14: =IF(B4>0,B14/B4,0) -> 0.066666667
A15: Media/Influencer | B15: =COUNTIF('Classified Leads'!R:R,"media")+COUNTIF('Classified Leads'!R:R,"influencer") -> 0 | C15: =IF(B4>0,B15/B4,0) -> 0
A16: Irrelevant | B16: =COUNTIF('Classified Leads'!R:R,"irrelevant") -> 82 | C16: =IF(B4>0,B16/B4,0) -> 0.2877193
A17: Error/Unknown | B17: =COUNTIF('Classified Leads'!R:R,"error")+COUNTIF('Classified Leads'!R:R,"unknown") -> 111 | C17: =IF(B4>0,B17/B4,0) -> 0.38947368
A19: PROFILE STATISTICS
A20: Metric | B20: Value
A21: Avg Follower Count | B21: =IF(COUNTA(Profiles!A:A)>1,ROUND(AVERAGE(Profiles!E2:E1000),0),0) -> 5710
A22: Median Follower Count | B22: =IF(COUNTA(Profiles!A:A)>1,ROUND(MEDIAN(Profiles!E2:E1000),0),0) -> 680
A23: Avg Post Count | B23: =IF(COUNTA(Profiles!A:A)>1,ROUND(AVERAGE(Profiles!G2:G1000),0),0) -> 415
A24: Verified Accounts | B24: =COUNTIF(Profiles!H:H,TRUE) -> 50
A25: Business Accounts | B25: =COUNTIF(Profiles!I:I,TRUE) -> 119
A26: Has Email in Bio | B26: =COUNTIFS(Profiles!M2:M1000,"<>") -> 11
A27: Has Phone in Bio | B27: =COUNTIFS(Profiles!N2:N1000,"<>") -> 16
A28: Has External URL | B28: =COUNTIFS(Profiles!K2:K1000,"<>") -> 184
A30: RELEVANT LEADS QUALITY
A31: Metric | B31: Value
A32: Avg Priority Score | B32: =IF(COUNTA('Relevant Leads'!A:A)>1,ROUND(AVERAGE('Relevant Leads'!D2:D1000),1),0) -> 6
A33: Max Priority Score | B33: =IF(COUNTA('Relevant Leads'!A:A)>1,MAX('Relevant Leads'!D2:D1000),0) -> 10
A34: High Priority (Score >= 7) | B34: =COUNTIFS('Relevant Leads'!D2:D1000,">="&7) -> 42
A35: Medium Priority (4-6.9) | B35: =COUNTIFS('Relevant Leads'!D2:D1000,">="&4,'Relevant Leads'!D2:D1000,"<"&7) -> 30
A36: Low Priority (< 4) | B36: =COUNTIFS('Relevant Leads'!D2:D1000,"<"&4,'Relevant Leads'!D2:D1000,">"&0) -> 20
A38: NET WORTH DISTRIBUTION
A39: Tier | B39: Count
A40: Ultra High Net Worth | B40: =COUNTIF('Classified Leads'!X:X,"*ultra*") -> 2
A41: High Net Worth | B41: =COUNTIF('Classified Leads'!X:X,"*high*")-COUNTIF('Classified Leads'!X:X,"*ultra*") -> 43
A42: Medium Net Worth | B42: =COUNTIF('Classified Leads'!X:X,"*medium*")+COUNTIF('Classified Leads'!X:X,"*moderate*") -> 0
A43: Unknown/Other | B43: =MAX(0,B4-B39-B40-B41) -> #VALUE!
A45: CONTACTABLE RELEVANT LEADS
A46: Metric | B46: Value
A47: With Email | B47: =COUNTIFS('Relevant Leads'!U2:U1000,"<>") -> 2
A48: With Phone | B48: =COUNTIFS('Relevant Leads'!V2:V1000,"<>") -> 4
A49: With External URL | B49: =COUNTIFS('Relevant Leads'!W2:W1000,"<>") -> 21
A50: With Any Contact Info | B50: =SUMPRODUCT((('Relevant Leads'!U2:U1000<>"")*1+('Relevant Leads'!V2:V1000<>"")*1+('Relevant Leads'!W2:W1000<>"")*1)>0) -> 0
A52: Seed Account | B52: Profiles Scraped | C52: Classified | D52: Relevant Leads
A53: loupethis | B53: {=IF(A53:A1000="","",COUNTIF(Profiles!AD:AD,A53:A1000))} -> 189 | C53: {=IF(A53:A1000="","",COUNTIF('Classified Leads'!P:P,A53:A1000))} -> 190 | D53: {=IF(A53:A1000="","",COUNTIF('Relevant Leads'!AA:AA,A53:A1000))} -> 86
A54: sin_takizawa | B54: 180 | C54: 5 | D54: 0
A55: sunnyboyyy | B55: 89 | C55: 5 | D55: 0
A56: watch_investor | B56: 151 | C56: 65 | D56: 3

Sheet Sheet1
A1: doc.txt | B1: Individual Collector | C1: Collector/Page | D1: Dealer | E1: Media | F1: Collector's Club | G1: Auction House | H1: Celebrities | I1: Other Luxury Goods | J1: Designer
A2: instagram.com/roni_m_29 | B2: https://www.instagram.com/jc_jil/ | C2: https://www.instagram.com/loupethis/ | D2: https://www.instagram.com/watch_investor/ | E2: https://www.instagram.com/hodinkee/ | F2: https://www.instagram.com/shanghaiwatchgang/ | G2: https://www.instagram.com/polyauctionhk/ | H2: https://www.instagram.com/sunnyboyyy/ | I2: https://www.instagram.com/supercarownerscircle/ | J2: https://www.instagram.com/sin_takizawa/
A3: instagram.com/bader_belselah | B3: https://www.instagram.com/a.dose.of.time/ | C3: https://www.instagram.com/amsterdamvintagewatches/ | D3: https://www.instagram.com/dauri.club/ | E3: https://www.instagram.com/monochromewatches/ | G3: https://www.instagram.com/bonhamswatches/ | H3: https://www.instagram.com/willpan23/ | I3: https://www.instagram.com/classicdriver/ | J3: https://www.instagram.com/nari_x_x_x_/
A4: instagram.com/markchodotcom | B4: https://www.instagram.com/jessicajjos/ | C4: https://www.instagram.com/watchanish/ | D4: https://www.instagram.com/1224_com/ | E4: https://www.instagram.com/watchonista/ | G4: https://www.instagram.com/christieswatches/ | I4: https://www.instagram.com/yachtcharterfleet/ | J4: https://www.instagram.com/rhuigi/
A5: instagram.com/indigo.8 | B5: https://www.instagram.com/paulabatinas/ | C5: https://www.instagram.com/santa_laura/ | D5: https://www.instagram.com/precious_time_now/ | E5: https://www.instagram.com/watchanalytics/ | G5: https://www.instagram.com/phillipswatches/ | I5: https://www.instagram.com/robbreport/
A6: instagram.com/watchdulum | B6: https://www.instagram.com/fedtan/ | C6: https://www.instagram.com/horology_ancienne/ | D6: https://www.instagram.com/yuriy_grekov74/ | E6: instagram.com/watch_the_f_out | G6: https://www.instagram.com/sothebyswatches/
A7: instagram.com/watchesa85 | B7: https://www.instagram.com/kpee/ | C7: https://www.instagram.com/patekgallery/ | D7: https://www.instagram.com/watchgirloffduty/ | E7: https://www.instagram.com/danblink
A8: instagram.com/bubbasteph | B8: https://www.instagram.com/lunglungthun/ | C8: https://www.instagram.com/horology_ancienne | D8: https://www.instagram.com/worldlywatches/
A9: instagram.com/luxecoffer | B9: https://www.instagram.com/timk1019/ | C9: https://www.instagram.com/matthiashaha | D9: https://www.instagram.com/watchand/
A10: instagram.com/champsg | B10: https://www.instagram.com/a_zhangerator/ | C10: https://www.instagram.com/watches_gmk | D10: https://www.instagram.com/dtimepieces.sg/
A11: instagram.com/fremstar | B11: https://www.instagram.com/johnson.collection/ | C11: https://www.instagram.com/watchfalcon | D11: https://www.instagram.com/mikenouveau/
A12: instagram.com/watchjabs | C12: https://www.instagram.com/cuuhu3888 | D12: https://www.instagram.com/eastcrown_japan/
A13: instagram.com/thewrongwrist | C13: https://www.instagram.com/wristspeaker/ | D13: https://www.instagram.com/woohoo_time/
A14: instagram.com/hairdude | C14: instagram.com/zachattack__25 | D14: https://www.instagram.com/watchnerdco/
A15: instagram.com/watch_the_f_out | D15: https://www.instagram.com/oliverandclarke/
A16: instagram.com/bangkokwrist | D16: https://www.instagram.com/kinsmen_ltd/
A17: instagram.com/journehutong | D17: https://www.instagram.com/shoyo_k/
A18: instagram.com/tom.chng
A19: instagram.com/battermaker
A20: instagram.com/faizul.ridzuan
A21: instagram.com/dens.watchvault
A22: instagram.com/watch.jelly
A23: instagram.com/luckymanzano
A24: instagram.com/zachattack__25
A25: instagram.com/johnson.collection
A26: instagram.com/danblink
A27: instagram.com/horology_ancienne
A28: instagram.com/masato.official
A29: instagram.com/matthiashaha
... A71: https://www.instagram.com/dr_audemars/

Sheet Profiles
A1: username | B1: platform | C1: full_name | D1: bio | E1: follower_count | F1: following_count | G1: post_count | H1: is_verified | I1: is_business | J1: business_category | K1: external_url | L1: profile_pic_url | M1: email_in_bio | N1: phone_in_bio | O1: engagement_rate | P1: recent_captions | Q1: hashtags | R1: mentions | S1: recent_post_urls | T1: recent_post_likes | U1: recent_post_comments | V1: recent_post_dates | W1: recent_post_locations | X1: recent_post_types | Y1: image_urls | Z1: video_urls | AA1: avg_likes | AB1: avg_comments | AC1: scrape_date | AD1: seed_account | AE1: seed_type | AF1: profile_url
A2: gunnertachejose | B2: instagram | C2: Jose R. Perez | E2: 571 | F2: 3536 | G2: 51 | H2: FALSE | I2: FALSE | L2: https://scontent-iad3-2.cdninstagram.com/v/t51.82787-19/568070790_18512543902068336_3998894716886781335_n.jpg?stp=dst-jpg_e0_s150x150_tt6&efg=eyJ2ZW5jb2RlX3RhZyI6InByb2ZpbGVfcGljLmRqYW5nby45NjAuYzIifQ&_nc_ht=scontent-iad3-2.cdninstagram.com&_nc_cat=100&_nc_oc=Q6cZ2QF4_ne5iN-IAFuxkpnTotn60cdpP-DocHD14HxlgKMganw4uoJ0AgT7c8CPZ9tZnEg&_nc_ohc=TnAiRTOqwpQQ7kNvwFk0gVe&_nc_gid=1Uz9GzkoOm5RERNhmxMMFQ&edm=AOQ1c0wBAAAA&ccb=7-5&oh=00_AfyKuub8ZKHvC1wlM6DXc3IKxJXkcvD2bTRwVRrDqglyoA&oe=69BD9C69&_nc_sid=8b3546 | O2: 0.035 | P2: 10 watches from Puerto Rico; Philippines; France;Switzerland; Rusia; China; England; Singapore; Australia; United States. 1 picture | S2: https://instagram.com/p/DUPQf9fEc-X, https://instagram.com/p/DUOGvx_kRu3, https://instagram.com/p/DUL0HjhERP-, https://instagram.com/p/DULmMPUEVcx, https://instagram.com/p/DULl0lokdBp, https://instagram.com/p/DULI1J6EY0B, https://instagram.com/p/DUI6b_ekYn7, https://instagram.com/p/DUIz6RDkaau, https://instagram.com/p/DUIzq0iEQFY, https://instagram.com/p/DUIyqNokdWs, https://instagram.com/p/DUIuhRlEUBI, https://instagram.com/p/DUGnElDEfGb | T2: 24, 20, 25, 20, 13, 22, 12, 25, 8, 7, 11, 43 | U2: 2, 2, 1, 0, 0, 0, 0, 0, 0, 0, 3, 2 | V2: 2026-02-02, 2026-02-01, 2026-01-31, 2026-01-31, 2026-01-31, 2026-01-31, 2026-01-30, 2026-01-30, 2026-01-30, 2026-01-30, 2026-01-30, 2026-01-29 | X2: Image, Video, Video, Image, Image, Image, Video, Image, Image, Video, Video, Image | Y2: https://scontent-iad3-2.cdninstagram.com/v/t51.82787-15/626473210_18530467810068336_2591620040173073744_n.heic?stp=dst-jpg_e15_fr_p1080x1080_tt6&_nc_ht=scontent-iad3-2.cdninstagram.com&_nc_cat=100&_nc_oc=Q6cZ2QF4_ne5iN-IAFuxkpnTotn60cdpP-DocHD14HxlgKMganw4uoJ0AgT7c8CPZ9tZnEg&_nc_ohc=BddgG_ocAXcQ7kNvwETAqdf&_nc_gid=1Uz9GzkoOm5RERNhmxMMFQ&edm=AOQ1c0wBAAAA&ccb=7-5&ig_cache_key=MzgyMzM0NzE3MzcyODMwOTE0Mw%3D%3D.3-ccb7-5&oh=00_AfwReCybVhbiZ7UHNNm9YDEMw34yFubhUfxs7mnybx60sA&oe=69BD9A3B&_nc_sid=8b3546, https://scontent-iad3-2.cdninstagram.com/v/t51.82787-15/624549240_18530129350068336_2101175656524860850_n.heic?stp=dst-jpg_e35_s1080x1080_sh0.08_tt6&_nc_ht=scontent-iad3-2.cdninstagram.com&_nc_cat=100&_nc_oc=Q6cZ2QF4_ne5iN-IAFuxkpnTotn60cdpP-DocHD14HxlgKMganw4uoJ0AgT7c8CPZ9tZnEg&_nc_ohc=uKpXynLFi9gQ7kNvwFJbYMp&_nc_gid=1Uz9GzkoOm5RERNhmxMMFQ&edm=AOQ1c0wBAAAA&ccb=7-5&ig_cache_key=MzgyMjMxNjY3NTU5Nzk0ODcyMQ%3D%3D.3-ccb7-5&oh=00_AfxeiM7AiKYhYDFZ4DnIMDGveWsSSqJdOt0V7HTd20t-DQ&oe=69BDB53B&_nc_sid=8b3546, https://scontent-iad3-2.cdninstagram.com/v/t51.82787-15/624823170_18530129083068336_4566934327069630923_n.heic?stp=dst-jpg_e35_s1080x1080_sh0.08_tt6&_nc_ht=scontent-iad3-2.cdninstagram.com&_nc_cat=100&_nc_oc=Q6cZ2QF4_ne5iN-IAFuxkpnTotn60cdpP-DocHD14HxlgKMganw4uoJ0AgT7c8CPZ9tZnEg&_nc_ohc=KY5p58zE7rwQ7kNvwFeO9OW&_nc_gid=1Uz9GzkoOm5RERNhmxMMFQ&edm=AOQ1c0wBAAAA&ccb=7-5&ig_cache_key=MzgyMjMxNTA1MDI5Njc5MTE0NQ%3D%3D.3-ccb7-5&oh=00_AfztBXuO53uJD7hIFo-J-A-g6QB0IA7TyGZkUvL04TC54A&oe=69BDA7EA&_nc_sid=8b3546, https://scontent-iad3-2.cdninstagram.com/v/t51.82787-15/625204535_18530061052068336_2254622707446308490_n.heic?stp=dst-jpg_e35_s1080x1080_sh0.08_tt6&_nc_ht=scontent-iad3-2.cdninstagram.com&_nc_cat=100&_nc_oc=Q6cZ2QF4_ne5iN-IAFuxkpnTotn60cdpP-DocHD14HxlgKMganw4uoJ0AgT7c8CPZ9tZnEg&_nc_ohc=T4nxl1eOMlIQ7kNvwEb8-8a&_nc_gid=1Uz9GzkoOm5RERNhmxMMFQ&edm=AOQ1c0wBAAAA&ccb=7-5&ig_cache_key=MzgyMjE4NzU0NTg5NjI1ODgxNw%3D%3D.3-ccb7-5&oh=00_AfzLUVXX7O8oWXXl08rMvixUSBa7L0b5zpeGb0-AqPiU7Q&oe=69BDB6C3&_nc_sid=8b3546, https://scontent-iad3-2.cdninstagram.com/v/t51.82787-15/624944082_18529865083068336_5749358781468525952_n.heic?stp=dst-jpg_e35_s1080x1080_sh0.08_tt6&_nc_ht=scontent-iad3-2.cdninstagram.com&_nc_cat=100&_nc_oc=Q6cZ2QF4_ne5iN-IAFuxkpnTotn60cdpP-DocHD14HxlgKMganw4uoJ0AgT7c8CPZ9tZnEg&_nc_ohc=mi9DGRUKFsMQ7kNvwGgodAr&_nc_gid=1Uz9GzkoOm5RERNhmxMMFQ&edm=AOQ1c0wBAAAA&ccb=7-5&ig_cache_key=MzgyMTUzMjU4ODIzOTA3MDg5NA%3D%3D.3-ccb7-5&oh=00_AfzUDluSTpUiENgMfNy3qo99GCmhBC3jOC4RRU1TzvgxrQ&oe=69BD9C7F&_nc_sid=8b3546, https://scontent-iad3-2.cdninstagram.com/v/t51.82787-15/625204648_18529864651068336_2195409626985506752_n.heic?stp=dst-jpg_e35_s1080x1080_sh0.08_tt6&_nc_ht=scontent-iad3-2.cdninstagram.com&_nc_cat=100&_nc_oc=Q6cZ2QF4_ne5iN-IAFuxkpnTotn60cdpP-DocHD14HxlgKMganw4uoJ0AgT7c8CPZ9tZnEg&_nc_ohc=Nl3K9gxwm4UQ7kNvwEXrJiJ&_nc_gid=1Uz9GzkoOm5RERNhmxMMFQ&edm=AOQ1c0wBAAAA&ccb=7-5&ig_cache_key=MzgyMTUzMTUyNjgyMDA2OTcyMA%3D%3D.3-ccb7-5&oh=00_AfwMdD6Mikkt_FURzHTnlpYoqwqFDFBRTweVgIpsQLIwxg&oe=69BD9EA1&_nc_sid=8b3546, https://scontent-iad3-2.cdninstagram.com/v/t51.82787-15/625140264_18529624555068336_4333841618875518379_n.heic?stp=dst-jpg_e35_s1080x1080_sh0.08_tt6&_nc_ht=scontent-iad3-2.cdninstagram.com&_nc_cat=100&_nc_oc=Q6cZ2QF4_ne5iN-IAFuxkpnTotn60cdpP-DocHD14HxlgKMganw4uoJ0AgT7c8CPZ9tZnEg&_nc_ohc=kYAx7ebVmt4Q7kNvwEFPWoc&_nc_gid=1Uz9GzkoOm5RERNhmxMMFQ&edm=AOQ1c0wBAAAA&ccb=7-5&ig_cache_key=MzgyMDkxMzE3MjM0MjIzOTY0Mw%3D%3D.3-ccb7-5&oh=00_AfyAAPkIbx-0k4IhPqmnb0ztmZhq3N_y9oK83GxThAUyEg&oe=69BDB8B6&_nc_sid=8b3546 | Z2: https://scontent-iad3-1.cdninstagram.com/o1/v/t2/f2/m86/AQN9IAvzBlJ00KdxXojw7J9DffaLxigQTn-MUUVjBniN6qHyxjUqF_HXGE2Q1LgYhRQuMJUK1nOPlW-nZlbroUyR9LBP6qqqIq1jUqo.mp4?_nc_cat=110&_nc_sid=5e9851&_nc_ht=scontent-iad3-1.cdninstagram.com&_nc_ohc=D2jNu6hoL20Q7kNvwHnqaXa&efg=eyJ2ZW5jb2RlX3RhZyI6Inhwdl9wcm9ncmVzc2l2ZS5JTlNUQUdSQU0uQ0xJUFMuQzMuNzIwLmRhc2hfYmFzZWxpbmVfMV92MSIsInhwdl9hc3NldF9pZCI6MTc5MzU2NDEyNTgxNDk4NTYsImFzc2V0X2FnZV9kYXlzIjo0MiwidmlfdXNlY2FzZV9pZCI6MTAwOTksImR1cmF0aW9uX3MiOjUsInVybGdlbl9zb3VyY2UiOiJ3d3cifQ%3D%3D&ccb=17-1&vs=4fdf8fb7bcba5249&_nc_vs=HBksFQIYUmlnX3hwdl9yZWVsc19wZXJtYW5lbnRfc3JfcHJvZC9FQjRFQTM4M0NGNTM2RjVCOUI1MTFGRUZDRTI3MEY4OF92aWRlb19kYXNoaW5pdC5tcDQVAALIARIAFQIYUWlnX3hwdl9wbGFjZW1lbnRfcGVybWFuZW50X3YyLzY4NDU4QkYyODI1RDcxNzU2RTk4NEE2NDNDMkVFRDg3X2F1ZGlvX2Rhc2hpbml0Lm1wNBUCAsgBEgAoABgAGwKIB3VzZV9vaWwBMRJwcm9ncmVzc2l2ZV9yZWNpcGUBMRUAACbAn5bg3JfcPxUCKAJDMywXQBQhysCDEm8YEmRhc2hfYmFzZWxpbmVfMV92MREAdf4HZeadAQA&_nc_gid=1Uz9GzkoOm5RERNhmxMMFQ&_nc_ss=1a&_nc_zt=28&oh=00_AfwJ38cXm8NC6y-Zjxj_Y1wqDgI4Lfz_nxqCxTqch-LZMA&oe=69B9B297, https://scontent-iad3-2.cdninstagram.com/o1/v/t2/f2/m86/AQOzejS7p7R9jDh9lvYoTR48LB5k03lYcc72-Llkv2PmyvBd0Gt7w7PgcvS5jG_B3Pn0-htLFVODPx-oNL0IoxcSFR_231Y20aUrUko.mp4?_nc_cat=100&_nc_sid=5e9851&_nc_ht=scontent-iad3-2.cdninstagram.com&_nc_ohc=ckUV_u-4BjcQ7kNvwEYdQgz&efg=eyJ2ZW5jb2RlX3RhZyI6Inhwdl9wcm9ncmVzc2l2ZS5JTlNUQUdSQU0uQ0xJUFMuQzMuNzIwLmRhc2hfYmFzZWxpbmVfMV92MSIsInhwdl9hc3NldF9pZCI6MTc5MzU1MzgwNjQxNDk4NTYsImFzc2V0X2FnZV9kYXlzIjo0MywidmlfdXNlY2FzZV9pZCI6MTAwOTksImR1cmF0aW9uX3MiOjUsInVybGdlbl9zb3VyY2UiOiJ3d3cifQ%3D%3D&ccb=17-1&vs=32fad8171ddab06c&_nc_vs=HBksFQIYUmlnX3hwdl9yZWVsc19wZXJtYW5lbnRfc3JfcHJvZC9BMjQ2NzE3RUVDOTYzOTY3RTM0OTg0NDczQTQ2OUY5Q192aWRlb19kYXNoaW5pdC5tcDQVAALIARIAFQIYUWlnX3hwdl9wbGFjZW1lbnRfcGVybWFuZW50X3YyL0NENDdBMzIwRkY5MEFCRThFNDA2MkMzQUIxNkY4RDlFX2F1ZGlvX2Rhc2hpbml0Lm1wNBUCAsgBEgAoABgAGwKIB3VzZV9vaWwBMRJwcm9ncmVzc2l2ZV9yZWNpcGUBMRUAACbAtdry25HcPxUCKAJDMywXQBQhysCDEm8YEmRhc2hfYmFzZWxpbmVfMV92MREAdf4HZeadAQA&_nc_gid=1Uz9GzkoOm5RERNhmxMMFQ&_nc_ss=1a&_nc_zt=28&oh=00_AfwRMEIaB2WeGojlaZ_gdUfZntVde56mlGeE4xF-Y5jwuw&oe=69B9B579, https://scontent-iad3-2.cdninstagram.com/o1/v/t2/f2/m86/AQNv2Sy6sVGLCXFhyV7NpeiTnARHHqIxzBFE52DPbXEy-wHwhb4q8M9O99kM_9XxkyUU54ewWf8dmAv7CaA-q4iIV-ujqxupSjOtcnM.mp4?_nc_cat=105&_nc_sid=5e9851&_nc_ht=scontent-iad3-2.cdninstagram.com&_nc_ohc=JmC6xinXKNkQ7kNvwEaPFqh&efg=eyJ2ZW5jb2RlX3RhZyI6Inhwdl9wcm9ncmVzc2l2ZS5JTlNUQUdSQU0uQ0xJUFMuQzMuNzIwLmRhc2hfYmFzZWxpbmVfMV92MSIsInhwdl9hc3NldF9pZCI6MTc5MzU0MDI3MTkxNDk4NTYsImFzc2V0X2FnZV9kYXlzIjo0NCwidmlfdXNlY2FzZV9pZCI6MTAwOTksImR1cmF0aW9uX3MiOjUsInVybGdlbl9zb3VyY2UiOiJ3d3cifQ%3D%3D&ccb=17-1&vs=f97412d6216c3869&_nc_vs=HBksFQIYUmlnX3hwdl9yZWVsc19wZXJtYW5lbnRfc3JfcHJvZC8xMDQ3NzgyNTVGMUQ0RkJERDEyQTE4QkI4MTYzM0VCQV92aWRlb19kYXNoaW5pdC5tcDQVAALIARIAFQIYUWlnX3hwdl9wbGFjZW1lbnRfcGVybWFuZW50X3YyLzJDNEZDNzdEMjM2OEIzQ0VENkE2MERGRUJFN0YzNTg0X2F1ZGlvX2Rhc2hpbml0Lm1wNBUCAsgBEgAoABgAGwKIB3VzZV9vaWwBMRJwcm9ncmVzc2l2ZV9yZWNpcGUBMRUAACbA_NO_64ncPxUCKAJDMywXQBQhysCDEm8YEmRhc2hfYmFzZWxpbmVfMV92MREAdf4HZeadAQA&_nc_gid=1Uz9GzkoOm5RERNhmxMMFQ&_nc_ss=1a&_nc_zt=28&oh=00_Afxg7UGZYyO8kExaFs8kxx6SZzdWivy_bixUp0hoA241Fg&oe=69B9B902, https://scontent-iad3-1.cdninstagram.com/o1/v/t2/f2/m86/AQOGbnnAISke8z1AlZ27XyiDDix35QH1yuzlsqw4X2Km90Q9A8ziKaDefffwdLIUJtgcjv65Jp_vXd3pxn2p9_z0Q-_nd5Kl1GRJkrg.mp4?_nc_cat=109&_nc_sid=5e9851&_nc_ht=scontent-iad3-1.cdninstagram.com&_nc_ohc=UFYt_Rh4bkEQ7kNvwHCfN3h&efg=eyJ2ZW5jb2RlX3RhZyI6Inhwdl9wcm9ncmVzc2l2ZS5JTlNUQUdSQU0uQ0xJUFMuQzMuMTI4MC5kYXNoX2Jhc2VsaW5lXzFfdjEiLCJ4cHZfYXNzZXRfaWQiOjE3OTM1Mzk1NDA4MTQ5ODU2LCJhc3NldF9hZ2VfZGF5cyI6NDQsInZpX3VzZWNhc2VfaWQiOjEwMDk5LCJkdXJhdGlvbl9zIjo1LCJ1cmxnZW5fc291cmNlIjoid3d3In0%3D&ccb=17-1&vs=64479dbc4e999247&_nc_vs=HBksFQIYUmlnX3hwdl9yZWVsc19wZXJtYW5lbnRfc3JfcHJvZC85MDQzNDdBQTI1QTVEMUY0REZEM0VFMkY2RkY4ODE4OV92aWRlb19kYXNoaW5pdC5tcDQVAALIARIAFQIYUWlnX3hwdl9wbGFjZW1lbnRfcGVybWFuZW50X3YyLzhCNEE0N0Y1MkRGNzI2Qzc1QTE2QkEyNzA3NkYxQzkxX2F1ZGlvX2Rhc2hpbml0Lm1wNBUCAsgBEgAoABgAGwKIB3VzZV9vaWwBMRJwcm9ncmVzc2l2ZV9yZWNpcGUBMRUAACbA9auDtYncPxUCKAJDMywXQBQhysCDEm8YEmRhc2hfYmFzZWxpbmVfMV92MREAdf4HZeadAQA&_nc_gid=1Uz9GzkoOm5RERNhmxMMFQ&_nc_ss=1a&_nc_zt=28&oh=00_Afw3l40keS_5djY_VfHUOzEGmwfa0sjNb2SVrhZcnPjKrQ&oe=69B9C0CE, https://scontent-iad3-1.cdninstagram.com/o1/v/t2/f2/m86/AQOPK3vvcKJoOroBHEUhx9qxRxEhtIIjs04d1iysRAA3hNDqdrfWB0zZNMiU2TRhVez-uQ5m2eT8z0DWLbFhFYJhpOaJgy4laNiirlY.mp4?_nc_cat=110&_nc_sid=5e9851&_nc_ht=scontent-iad3-1.cdninstagram.com&_nc_ohc=EMY9XvmIW4kQ7kNvwFjxwb6&efg=eyJ2ZW5jb2RlX3RhZyI6Inhwdl9wcm9ncmVzc2l2ZS5JTlNUQUdSQU0uQ0xJUFMuQzMuNzIwLmRhc2hfYmFzZWxpbmVfMV92MSIsInhwdl9hc3NldF9pZCI6MTc5MzUzOTA3NDkxNDk4NTYsImFzc2V0X2FnZV9kYXlzIjo0NCwidmlfdXNlY2FzZV9pZCI6MTAwOTksImR1cmF0aW9uX3MiOjEwLCJ1cmxnZW5fc291cmNlIjoid3d3In0%3D&ccb=17-1&vs=91c4305ff100753f&_nc_vs=HBksFQIYUmlnX3hwdl9yZWVsc19wZXJtYW5lbnRfc3JfcHJvZC82NTQ4RUM0MjQ3MDdGQkE1Qjc5MjZDNUIxRkE1OENBQl92aWRlb19kYXNoaW5pdC5tcDQVAALIARIAFQIYUWlnX3hwdl9wbGFjZW1lbnRfcGVybWFuZW50X3YyLzhGNDk3RkY0ODM0MTg2MjY4Q0VDRkVENUYyNTU4QTk0 | AA2: 19 | AB2: 1 | AC2: 46097 | AD2: loupethis | AE2: collector_page | AF2: https://www.instagram.com/gunnertachejose
A3: abogado_casas | B3: instagram | C3: Alejandro Casas | D3: Personal Injury Attorney-Owner of Casas Law P.A.; Watches, Whiskey and, Cigars. | E3: 869 | F3: 2807 | G3: 175 | H3: FALSE | I3: FALSE | L3: https://instagram.fyto1-2.fna.fbcdn.net/v/t51.2885-19/431698407_929956895117509_3137349195214736088_n.jpg?stp=dst-jpg_e0_s150x150_tt6&efg=eyJ2ZW5jb2RlX3RhZyI6InByb2ZpbGVfcGljLmRqYW5nby4xMDgwLmMyIn0&_nc_ht=instagram.fyto1-2.fna.fbcdn.net&_nc_cat=101&_nc_oc=Q6cZ2QGN2q_9e63hviuPUfLgrrXn-vgVmnrF0H5SjWXWXU23NIQhl6ygTJWoFrxhgjJipCg&_nc_ohc=dpMRisC0vkQQ7kNvwFWJADr&_nc_gid=fhJwiM6umqPJBRfXbBA-Gw&edm=AOQ1c0wBAAAA&ccb=7-5&oh=00_Afwc2Sa9Qo1oPCXD1TkwnogtU7pMM8MHx9lmKmhNYRCOaA&oe=69BDA5E2&_nc_sid=8b3546 | O3: 0.0533 | P3: HAPPY BIRTHDAY, SUSIE! You are the love of my life, my wife, best friend and partner in all things. I wish for you a lifetime filled with love, happiness and adventure. Love you! | Thankful for good friends. Goodbye 2025! Palm Beach Watch Club. | Wishing all of our friends and family the very best of the season. Looking forward to a new year filled with health, happiness and prosperity. | Christmas Markets Stop #8. Dresden This beautiful city was completely destroyed in World War II. It has now been rebuilt with much of the original materials. You can look at the old buildings and easily recognize the original stones because they were left blackened as they looked after the bombings. | The Casas Law Family Christmas dinner. We are truly blessed to be in the company of such a fantastic group of people. There was too much food, too many drinks and an evening filled with laughs. Thank you to Ernesto from Paella Uno Catering for making the amazing dinner and to Megan Burr of Bite Hau | Stop #7 Frankfurt & Weisbaden. I mistakenly labeled the prior stop as Weisbaden but, this is it. Frankfurt is a big city with several Christmas markets and much to see. It’s a modern city that still retains some old world charm. The market in Weisbaden is known as the shooting star Christmas market. | Stop #6 Wertheim Another well preserved medieval town. This town sits between two rivers and has flooded many times over the centuries. There are numerous flood marks that are unsettlingly high on the walls. There is a beautiful old Lutheran Church that started out as a Catholic Church. There are | Stop #5. The Franconian village of Aschfeld. This tiny village was untouched by the Second World War. Well over 1,000 years old. It was too small to surround itself with a wall and most grew around a fortified church which was the center of activity. We saw many restored rooms depicting life over th | Stop #4 Wurzburg: We visited the Christmas Market and the Residenz which is a baroque 18th century palace built for the prince-bishops. | Stop #3. Rothenberg. This is an almost completely preserved medieval city. Walt Disney visited this town in the 1930’s and modeled Pinocchio’s village after it. We had warm apple strudel and hot chocolate in a hotel that was built in 1300. Another great day. | Stop #2. Bamberg A fairly small market but such a cool town. | Q3: #8, #7, #6, #5, #4, #3, #2 | S3: https://instagram.com/p/DUDYt2vjK2O, https://instagram.com/p/DS_VpuuFZNJ, https://instagram.com/p/DSyVsGeAXP2, https://instagram.com/p/DSr6STJFZZI, https://instagram.com/p/DSf2zv2gVbN, https://instagram.com/p/DSQZVs-gYex, https://instagram.com/p/DSFqdLnFdEJ, https://instagram.com/p/DSE_H_ukSOa, https://instagram.com/p/DR-lWuwlBJX, https://instagram.com/p/DR8CSgxgZaD, https://instagram.com/p/DR48lkKgHBn, https://instagram.com/p/DR2z6gtEewQ | T3: 51, 42, 70, 58, 60, 56, 39, 20, 28, 40, 35, 24 | U3: 15, 2, 7, 2, 0, 1, 1, 2, 0, 1, 2, 0 | V3: 2026-01-28, 2026-01-02, 2025-12-28, 2025-12-25, 2025-12-20, 2025-12-14, 2025-12-10, 2025-12-10, 2025-12-07, 2025-12-06, 2025-12-05, 2025-12-04 | W3: Antigua, Carribbean, Würzburg, Germany | X3: Image, Image, Sidecar, Image, Sidecar, Sidecar, Sidecar, Sidecar, Sidecar, Sidecar, Sidecar, Sidecar | Y3: https://instagram.fyto1-1.fna.fbcdn.net/v/t39.30808-6/624539548_4338479249813019_5618141011669941887_n.jpg?stp=dst-jpg_e35_p1080x1080_sh0.08_tt6&_nc_ht=instagram.fyto1-1.fna.fbcdn.net&_nc_cat=103&_nc_oc=Q6cZ2QGN2q_9e63hviuPUfLgrrXn-vgVmnrF0H5SjWXWXU23NIQhl6ygTJWoFrxhgjJipCg&_nc_ohc=Ot1X7YQyH0IQ7kNvwGFKKAk&_nc_gid=fhJwiM6umqPJBRfXbBA-Gw&edm=AOQ1c0wAAAAA&ccb=7-5&ig_cache_key=MzgyMDAwNTYxMzIxMjgzOTMxMA%3D%3D.3-ccb7-5&oh=00_AfyemXgMB5AEXIHg3fGSty1ey4rgBlt-CTIJkb-vl5HWoA&oe=69BD9226&_nc_sid=8b3546, https://instagram.fyto1-2.fna.fbcdn.net/v/t51.82787-15/609533529_18007216970821806_8806535578618323406_n.jpg?stp=dst-jpg_e35_p1080x1080_sh0.08_tt6&_nc_ht=instagram.fyto1-2.fna.fbcdn.net&_nc_cat=106&_nc_oc=Q6cZ2QGN2q_9e63hviuPUfLgrrXn-vgVmnrF0H5SjWXWXU23NIQhl6ygTJWoFrxhgjJipCg&_nc_ohc=VfhpOCYYx0EQ7kNvwFapH7H&_nc_gid=fhJwiM6umqPJBRfXbBA-Gw&edm=AOQ1c0wBAAAA&ccb=7-5&ig_cache_key=MzgwMDg1MTgzNzE2NDU1NzEyOQ%3D%3D.3-ccb7-5&oh=00_Afzyw8PRk12o2WdwbXb9WyFPuc3GABFCQm-KtfIyDq3Nww&oe=69BD9D64&_nc_sid=8b3546, https://instagram.fyto1-2.fna.fbcdn.net/v/t51.82787-15/602716518_18006621941821806_9034530550002112950_n.jpg?stp=dst-jpg_e35_s1080x1080_sh0.08_tt6&_nc_ht=instagram.fyto1-2.fna.fbcdn.net&_nc_cat=106&_nc_oc=Q6cZ2QGN2q_9e63hviuPUfLgrrXn-vgVmnrF0H5SjWXWXU23NIQhl6ygTJWoFrxhgjJipCg&_nc_ohc=et59naadZHAQ7kNvwHUj_Cb&_nc_gid=fhJwiM6umqPJBRfXbBA-Gw&edm=AOQ1c0wBAAAA&ccb=7-5&ig_cache_key=Mzc5NzE5MjgxMTg0MTk2NjQ5Mw%3D%3D.3-ccb7-5&oh=00_Afz5aiR_R3HMRCN8pnrwTrxUlmAonjzXR0HKfzUYU1Im7A&oe=69BDB46E&_nc_sid=8b3546, https://instagram.fyto1-2.fna.fbcdn.net/v/t51.82787-15/602716518_18006621941821806_9034530550002112950_n.jpg?stp=dst-jpg_e35_s1080x1080_sh0.08_tt6&_nc_ht=instagram.fyto1-2.fna.fbcdn.net&_nc_cat=106&_nc_oc=Q6cZ2QGN2q_9e63hviuPUfLgrrXn-vgVmnrF0H5SjWXWXU23NIQhl6ygTJWoFrxhgjJipCg&_nc_ohc=et59naadZHAQ7kNvwHUj_Cb&_nc_gid=fhJwiM6umqPJBRfXbBA-Gw&edm=AOQ1c0wBAAAA&ccb=7-5&ig_cache_key=Mzc5NzE5MjgxMTg0MTk2NjQ5Mw%3D%3D.3-ccb7-5&oh=00_Afz5aiR_R3HMRCN8pnrwTrxUlmAonjzXR0HKfzUYU1Im7A&oe=69BDB46E&_nc_sid=8b3546, https://instagram.fyto1-2.fna.fbcdn.net/v/t51.82787-15/590367460_18006621953821806_2721736594605781782_n.jpg?stp=dst-jpg_e35_s1080x1080_sh0.08_tt6&_nc_ht=instagram.fyto1-2.fna.fbcdn.net&_nc_cat=106&_nc_oc=Q6cZ2QGN2q_9e63hviuPUfLgrrXn-vgVmnrF0H5SjWXWXU23NIQhl6ygTJWoFrxhgjJipCg&_nc_ohc=PjNzPObTnvQQ7kNvwGa4mGM&_nc_gid=fhJwiM6umqPJBRfXbBA-Gw&edm=AOQ1c0wBAAAA&ccb=7-5&ig_cache_key=Mzc5NzE5MjgxMjE2OTA3MTkzMw%3D%3D.3-ccb7-5&oh=00_AfylAqMB2ICa14dfxxQJHs6dDCd2Ayq1GYP-vV4RtaxL1Q&oe=69BDB43E&_nc_sid=8b3546, https://instagram.fyto1-2.fna.fbcdn.net/v/t51.82787-15/603069925_18006621962821806_7938595125366558076_n.jpg?stp=dst-jpg_e35_s1080x1080_sh0.08_tt6&_nc_ht=instagram.fyto1-2.fna.fbcdn.net&_nc_cat=106&_nc_oc=Q6cZ2QGN2q_9e63hviuPUfLgrrXn-vgVmnrF0H5SjWXWXU23NIQhl6ygTJWoFrxhgjJipCg&_nc_ohc=kMLWGDV7oq4Q7kNvwFUBGwI&_nc_gid=fhJwiM6umqPJBRfXbBA-Gw&edm=AOQ1c0wBAAAA&ccb=7-5&ig_cache_key=Mzc5NzE5MjgxMTgyNTE4NDg5MA%3D%3D.3-ccb7-5&oh=00_AfyQm38w6Eh5rK70Mm0fHik0bsyw6Y20w8ZTJ3GM5sdvWA&oe=69BDB2A9&_nc_sid=8b3546, https://instagram.fyto1-2.fna.fbcdn.net/v/t51.82787-15/587791479_18006351173821806_4339232795343398157_n.jpg?stp=dst-jpg_e35_p1080x1080_sh0.08_tt6&_nc_ht=instagram.fyto1-2.fna.fbcdn.net&_nc_cat=106&_nc_oc=Q6cZ2QGN2q_9e63hviuPUfLgrrXn-vgVmnrF0H5SjWXWXU23NIQhl6ygTJWoFrxhgjJipCg&_nc_ohc=fxqOYOTu-qYQ7kNvwE8vcar&_nc_gid=fhJwiM6umqPJBRfXbBA-Gw&edm=AOQ1c0wBAAAA&ccb=7-5&ig_cache_key=Mzc5NTM4MzQ1NTE5MTUwNDQ1Ng%3D%3D.3-ccb7-5&oh=00_AfwAu4KyI5yPHBvWy061FN2V-zoZdZ54Pp1xpUevyEPGzQ&oe=69BDA5FC&_nc_sid=8b3546, https://instagram.fyto1-2.fna.fbcdn.net/v/t51.82787-15/589942231_18005836514821806_1060000011034679358_n.jpg?stp=dst-jpg_e35_p1080x1080_sh0.08_tt6&_nc_ht=instagram.fyto1-2.fna.fbcdn.net&_nc_cat=106&_nc_oc=Q6cZ2QGN2q_9e63hviuPUfLgrrXn-vgVmnrF0H5SjWXWXU23NIQhl6ygTJWoFrxhgjJipCg&_nc_ohc=jsoQeLdc3UQQ7kNvwEbfjnO&_nc_gid=fhJwiM6umqPJBRfXbBA-Gw&edm=AOQ1c0wBAAAA&ccb=7-5&ig_cache_key=Mzc5MTk5MDQzNDQwNjk3MzgyNg%3D%3D.3-ccb7-5&oh=00_AfzTtocM0MfcZq_tPcfAyHrNlHAbzXOBS9aS00Ag5QD1LA&oe=69BD935E&_nc_sid=8b3546, https://instagram.fyto1-2.fna.fbcdn.net/v/t51.82787-15/589942231_18005836514821806_1060000011034679358_n.jpg?stp=dst-jpg_e35_p1080x1080_sh0.08_tt6&_nc_ht=instagram.fyto1-2.fna.fbcdn.net&_nc_cat=106&_nc_oc=Q6cZ2QGN2q_9e63hviuPUfLgrrXn-vgVmnrF0H5SjWXWXU23NIQhl6ygTJWoFrxhgjJipCg&_nc_ohc=jsoQeLdc3UQQ7kNvwEbfjnO&_nc_gid=fhJwiM6umqPJBRfXbBA-Gw&edm=AOQ1c0wBAAAA&ccb=7-5&ig_cache_key=Mzc5MTk5MDQzNDQwNjk3MzgyNg%3D%3D.3-ccb7-5&oh=00_AfzTtocM0MfcZq_tPcfAyHrNlHAbzXOBS9aS00Ag5QD1LA&oe=69BD935E&_nc_sid=8b3546, https://instagram.fyto1-2.fna.fbcdn.net/v/t51.82787-15/603080092_18005836544821806_1601593861678180600_n.jpg?stp=dst-jpg_e35_p1080x1080_sh0.08_tt6&_nc_ht=instagram.fyto1-2.fna.fbcdn.net&_nc_cat=106&_nc_oc=Q6cZ2QGN2q_9e63hviuPUfLgrrXn-vgVmnrF0H5SjWXWXU23NIQhl6ygTJWoFrxhgjJipCg&_nc_ohc=UNeZA0DIfiEQ7kNvwExrLx7&_nc_gid=fhJwiM6umqPJBRfXbBA-Gw&edm=AOQ1c0wBAAAA&ccb=7-5&ig_cache_key=Mzc5MTk5MDQzNDQwNjk4Njg3OA%3D%3D.3-ccb7-5&oh=00_AfyYbSwa1zkL_wmzRVC8964rBtMDSX8TkSwP1TacbmbHLw&oe=69BDA89E&_nc_sid= | AA3: 44 | AB3: 3 | AC3: 46097 | AD3: loupethis | AE3: collector_page | AF3: https://www.instagram.com/abogado_casas
A4: noritera24 | B4: instagram | C4: 寺田 憲永 | E4: 263 | F4: 751 | G4: 69 | H4: FALSE | I4: FALSE | L4: https://scontent-sjc6-1.cdninstagram.com/v/t51.2885-19/476847396_651892737516527_1167557373126833247_n.jpg?stp=dst-jpg_e0_s150x150_tt6&efg=eyJ2ZW5jb2RlX3RhZyI6InByb2ZpbGVfcGljLmRqYW5nby41MDAuYzIifQ&_nc_ht=scontent-sjc6-1.cdninstagram.com&_nc_cat=111&_nc_oc=Q6cZ2QF1yPgdmWQ8bSJjpCokyM5dER8QBycS2wh5DAQ7_p1aKTR_oUAMmRTJ8LgSztCvKUA&_nc_ohc=ZCv-OkJe1tAQ7kNvwFHSAUO&_nc_gid=c0a-TjvY6fR91GXlq02zlg&edm=AOQ1c0wBAAAA&ccb=7-5&oh=00_AfzxUtpIQ8t0bawHCSt8wzIxSvU2s3Qnb3RjZD0mo7rLuQ&oe=69BD8E74&_nc_sid=8b3546 | O4: 0.0691 | P4: 近江八幡市ラコリーナの飛び出し坊やがかわいい。⁡ ⁡ #ラコリーナ #バームクーヘン | 天理市にある町中華の大和軒。ここのもやし炒めは最高に美味い。 #天理市 #町中華 #大和軒 #もやし炒め | 助けてください。帯状疱疹になってしまいました。剣山で刺されているような激痛です。 | 奈良県と京都府の境にあるその名も国境食堂。 腹が減ったらここのカツ丼をオススメ！ #国境食堂 #カツ丼 #大盛り | 先日の若草山の山焼き前の花火です。 #奈良市 #若草山 #山焼き | 今日は山焼きでした🔥 #若草山 #山焼き | いつまでも元気でいてね | ニンテンドーミュージアムだ‼️ | まさに別腹❗ | 我が生涯に一片の悔い無し❗ #北斗の拳大原画展 #ラオウ #巨星墜つ | はっ、これは！北斗天帰掌!! #北斗の拳大原画展 #トキ #兵庫県立美術館 | ひでぶっ！ #北斗の拳大原画展 #ハート様 #北斗柔破斬 | S4: https://instagram.com/p/DVKfvgxkpeJ, https://instagram.com/p/DLABHMWyqQA, https://instagram.com/p/DJiF92_TNtF, https://instagram.com/p/DI8fDNhSZQR, https://instagram.com/p/DFUHpr6yeAt, https://instagram.com/p/DFPs7NrSLRI, https://instagram.com/p/DE7S1M4SuAc, https://instagram.com/p/DE6oNM1y8qJ, https://instagram.com/p/DCEPOW7S8xC, https://instagram.com/p/C9sFnCry7aO, https://instagram.com/p/C9jyB7GS7XL, https://instagram.com/p/C9hZMY4ygR8 | T4: 9, 18, 6, 24, 27, 24, 16, 18, 20, 27, 17, 11 | U4: 0, 0, 1, 0, 0, 0, 0, 0, 0, 0, 0, 0 | V4: 2026-02-25, 2025-06-17, 2025-05-12, 2025-04-27, 2025-01-27, 2025-01-25, 2025-01-17, 2025-01-17, 2024-11-07, 2024-07-21, 2024-07-18, 2024-07-17 | X4: Video, Image, Image, Image, Video, Image, Image, Image, Image, Image, Image, Image | Y4: https://scontent-sjc3-1.cdninstagram.com/v/t51.82787-15/623390926_18039801947725596_8171532934446088184_n.jpg?stp=dst-jpg_e35_s1080x1080_sh0.08_tt6&_nc_ht=scontent-sjc3-1.cdninstagram.com&_nc_cat=100&_nc_oc=Q6cZ2QF1yPgdmWQ8bSJjpCokyM5dER8QBycS2wh5DAQ7_p1aKTR_oUAMmRTJ8LgSztCvKUA&_nc_ohc=KVrCwzLO5a8Q7kNvwE80TAP&_nc_gid=c0a-TjvY6fR91GXlq02zlg&edm=AOQ1c0wBAAAA&ccb=7-5&ig_cache_key=MzY1NjkyNzc4OTc3NDk3MTkwNA%3D%3D.3-ccb7-5&oh=00_Afyio9iE_OJY6zm9V5-UR8IKeuRdpEeaIA5avwMzebFaSA&oe=69BDB079&_nc_sid=8b3546, https://scontent-sjc6-1.cdninstagram.com/v/t51.82787-15/620897612_17887274766427585_5168461228460557261_n.jpg?stp=dst-jpg_e35_s1080x1080_sh0.08_tt6&_nc_ht=scontent-sjc6-1.cdninstagram.com&_nc_cat=101&_nc_oc=Q6cZ2QF1yPgdmWQ8bSJjpCokyM5dER8QBycS2wh5DAQ7_p1aKTR_oUAMmRTJ8LgSztCvKUA&_nc_ohc=wrQ-X7rzhjkQ7kNvwFxwiPf&_nc_gid=c0a-TjvY6fR91GXlq02zlg&edm=AOQ1c0wBAAAA&ccb=7-5&ig_cache_key=MzYzMDQ5MDQ5MDc3ODczNzQ3Nw%3D%3D.3-ccb7-5&oh=00_AfxmCkya5zucLN0w_ZfvY30Edo2Z5HO_oGR36nWLfieljQ&oe=69BD99DE&_nc_sid=8b3546, https://scontent-sjc6-1.cdninstagram.com/v/t51.82787-15/623515472_18063560801644149_3446559460627410548_n.jpg?stp=dst-jpg_e35_s1080x1080_sh0.08_tt6&_nc_ht=scontent-sjc6-1.cdninstagram.com&_nc_cat=109&_nc_oc=Q6cZ2QF1yPgdmWQ8bSJjpCokyM5dER8QBycS2wh5DAQ7_p1aKTR_oUAMmRTJ8LgSztCvKUA&_nc_ohc=dOF3UbSmsK0Q7kNvwG_vL7k&_nc_gid=c0a-TjvY6fR91GXlq02zlg&edm=AOQ1c0wBAAAA&ccb=7-5&ig_cache_key=MzYxOTkwNDc2MDYxNjQyNDQ2NQ%3D%3D.3-ccb7-5&oh=00_AfwzhPB2AdE8SSPhSsJhDBXryExNt6NSfO0c73PMfXOAmg&oe=69BDB2F4&_nc_sid=8b3546, https://scontent-sjc3-1.cdninstagram.com/v/t51.82787-15/622356808_17946552131962134_7831933523479587071_n.jpg?stp=dst-jpg_e35_s1080x1080_sh0.08_tt6&_nc_ht=scontent-sjc3-1.cdninstagram.com&_nc_cat=106&_nc_oc=Q6cZ2QF1yPgdmWQ8bSJjpCokyM5dER8QBycS2wh5DAQ7_p1aKTR_oUAMmRTJ8LgSztCvKUA&_nc_ohc=_bkZrFKmQ2EQ7kNvwHvDoiX&_nc_gid=c0a-TjvY6fR91GXlq02zlg&edm=AOQ1c0wBAAAA&ccb=7-5&ig_cache_key=MzU1MzI1NjIxNDE5OTA1NTQzMg%3D%3D.3-ccb7-5&oh=00_Afwz55L2e0Zyaky9kto5_XGgK51WoidZUlJpjtz9uryg3Q&oe=69BDB932&_nc_sid=8b3546, https://scontent-sjc3-1.cdninstagram.com/v/t51.82787-15/626538272_18050463545695625_7909197216043427244_n.jpg?stp=dst-jpg_e35_s1080x1080_sh0.08_tt6&_nc_ht=scontent-sjc3-1.cdninstagram.com&_nc_cat=105&_nc_oc=Q6cZ2QF1yPgdmWQ8bSJjpCokyM5dER8QBycS2wh5DAQ7_p1aKTR_oUAMmRTJ8LgSztCvKUA&_nc_ohc=2sOILFQDRXMQ7kNvwHIEh7c&_nc_gid=c0a-TjvY6fR91GXlq02zlg&edm=AOQ1c0wBAAAA&ccb=7-5&ig_cache_key=MzU0NzUxMTk1MjI4MzE5NzQ2OA%3D%3D.3-ccb7-5&oh=00_Afwcj9ORhihTfmdxYKO3DVW1Z9yC06vo8HgkHjTbwvbF5w&oe=69BD9134&_nc_sid=8b3546, https://scontent-sjc6-1.cdninstagram.com/v/t51.82787-15/629422017_18338209159240372_1702916677156418156_n.jpg?stp=dst-jpg_e35_s1080x1080_sh0.08_tt6&_nc_ht=scontent-sjc6-1.cdninstagram.com&_nc_cat=104&_nc_oc=Q6cZ2QF1yPgdmWQ8bSJjpCokyM5dER8QBycS2wh5DAQ7_p1aKTR_oUAMmRTJ8LgSztCvKUA&_nc_ohc=YTCBoGTmYo4Q7kNvwGHWTSl&_nc_gid=c0a-TjvY6fR91GXlq02zlg&edm=AOQ1c0wBAAAA&ccb=7-5&ig_cache_key=MzU0NzMyNDQ4NTUwODc3ODYzMw%3D%3D.3-ccb7-5&oh=00_Afzw0RASfraeCW1k6ktLmsnmDdw5ihaDgUJIWT1Wy6onTA&oe=69BD8C80&_nc_sid=8b3546, https://scontent-sjc6-1.cdninstagram.com/v/t51.82787-15/630630791_18403701019131093_4145509035250462642_n.jpg?stp=dst-jpg_e35_s1080x1080_sh0.08_tt6&_nc_ht=scontent-sjc6-1.cdninstagram.com&_nc_cat=109&_nc_oc=Q6cZ2QF1yPgdmWQ8bSJjpCokyM5dER8QBycS2wh5DAQ7_p1aKTR_oUAMmRTJ8LgSztCvKUA&_nc_ohc=H3QyYgCPzCQQ7kNvwGif1GP&_nc_gid=c0a-TjvY6fR91GXlq02zlg&edm=AOQ1c0wBAAAA&ccb=7-5&ig_cache_key=MzQ5NTk4NjE2ODEzMzgzMTc0Ng%3D%3D.3-ccb7-5&oh=00_AfzyWwyBNHw_npQ4fxb3QsAGemIeeTuVn_2Tx1bm9SFr4g&oe=69BDA2CF&_nc_sid=8b3546, https://scontent-sjc6-1.cdninstagram.com/v/t51.82787-15/624605385_18098245945927279_5895230937017004006_n.jpg?stp=dst-jpg_e35_s1080x1080_sh0.08_tt6&_nc_ht=scontent-sjc6-1.cdninstagram.com&_nc_cat=107&_nc_oc=Q6cZ2QF1yPgdmWQ8bSJjpCokyM5dER8QBycS2wh5DAQ7_p1aKTR_oUAMmRTJ8LgSztCvKUA&_nc_ohc=nKW_xPTxoyMQ7kNvwFR3Nfs&_nc_gid=c0a-TjvY6fR91GXlq02zlg&edm=AOQ1c0wBAAAA&ccb=7-5&ig_cache_key=MzQxNzEzMDg5MDQ0MTc2NjU0Mg%3D%3D.3-ccb7-5&oh=00_AfzLGL_4fYnAdoD828YPF1JU9i4XwIIsvUHWCOujAwW9EQ&oe=69BD91B8&_nc_sid=8b3546, https://scontent-sjc3-1.cdninstagram.com/v/t51.82787-15/623026720_18109574080709124_5283023880477568432_n.jpg?stp=dst-jpg_e35_s1080x1080_sh0.08_tt6&_nc_ht=scontent-sjc3-1.cdninstagram.com&_nc_cat=100&_nc_oc=Q6cZ2QF1yPgdmWQ8bSJjpCokyM5dER8QBycS2wh5DAQ7_p1aKTR_oUAMmRTJ8LgSztCvKUA&_nc_ohc=HwslnLQgx0IQ7kNvwFJ7fC2&_nc_gid=c0a-TjvY6fR91GXlq02zlg&edm=AOQ1c0wBAAAA&ccb=7-5&ig_cache_key=MzQxNDc5Mjk3Njk3ODM5MjUyMw%3D%3D.3-ccb7-5&oh=00_Afx6U6qFPwigv8fq7RDK-vipNKxgcMWw9C2sy329o5Gs3w&oe=69BD94B1&_nc_sid=8b3546, https://scontent-sjc3-1.cdninstagram.com/v/t51.82787-15/625045792_18149175013391990_6591410123138496031_n.jpg?stp=dst-jpg_e35_s1080x1080_sh0.08_tt6&_nc_ht=scontent-sjc3-1.cdninstagram.com&_nc_cat=102&_nc_oc=Q6cZ2QF1yPgdmWQ8bSJjpCokyM5dER8QBycS2wh5DAQ7_p1aKTR_oUAMmRTJ8LgSztCvKUA&_nc_ohc=O5-aTX8pWFwQ7kNvwGv10dU&_nc_gid=c0a-TjvY6fR91GXlq02zlg&edm=AOQ1c0wBAAAA&ccb=7-5&ig_cache_key=MzQxNDEyMDc5NTA0MjYxMjM0OA%3D%3D.3-ccb7-5&oh=00_AfzUgj6-cbfGIc2Fje1_TiwPhRShheBLPVO1derp1g0XA | Z4: https://scontent-sjc3-1.cdninstagram.com/o1/v/t16/f2/m69/AQMNeZRpyq8TWkgfRyXuzDXuk6uLI1IFs6X9NEBFEiZVVJVksAuss2J2tJCKScBRjXFoXGbBYv-sM8uWkUcfHInm.mp4?strext=1&_nc_cat=106&_nc_sid=5e9851&_nc_ht=scontent-sjc3-1.cdninstagram.com&_nc_ohc=jN0-HRIXfHUQ7kNvwF62BxK&efg=eyJ2ZW5jb2RlX3RhZyI6Inhwdl9wcm9ncmVzc2l2ZS5JTlNUQUdSQU0uQ0xJUFMuQzMuNzIwLmRhc2hfYmFzZWxpbmVfMV92MSIsInhwdl9hc3NldF9pZCI6MTc5NDkxODkwOTYwOTg5MjgsImFzc2V0X2FnZV9kYXlzIjoxOSwidmlfdXNlY2FzZV9pZCI6MTAwOTksImR1cmF0aW9uX3MiOjUsInVybGdlbl9zb3VyY2UiOiJ3d3cifQ%3D%3D&ccb=17-1&vs=1ea71a9632a3c&_nc_vs=HBkcFQIYOnBhc3N0aHJvdWdoX2V2ZXJzdG9yZS9HRnJzQVNZV19nMFY4M0VDQUxYb3YxeG16eEIxYnNwVEFRQUYVAALIARIAKAAYABsCiAd1c2Vfb2lsATEScHJvZ3Jlc3NpdmVfcmVjaXBlATEVAAAm4LGigais4j8VAigCQzMsF0AUIcrAgxJvGBJkYXNoX2Jhc2VsaW5lXzFfdjERAHX-B2XmnQEA&_nc_gid=c0a-TjvY6fR91GXlq02zlg&_nc_ss=1a&_nc_zt=28&oh=00_Afypp3HHgWwn140esTMLZAAc7ASxErPjYz7EbGrvrBO5CQ&oe=69BDB652, https://scontent-sjc6-1.cdninstagram.com/o1/v/t2/f2/m86/AQOcLDlilfmUY3mo0q6KYA4Z6x5M0d9i2-zljXS8W9Qix8Ddn1X4j63IdMGPeDm7BiK6rSOO9TXVeD4ahkG9tR9KshadO1x3flJfwTY.mp4?_nc_cat=104&_nc_sid=5e9851&_nc_ht=scontent-sjc6-1.cdninstagram.com&_nc_ohc=dSuDp0F62ZwQ7kNvwHQL5s4&efg=eyJ2ZW5jb2RlX3RhZyI6Inhwdl9wcm9ncmVzc2l2ZS5JTlNUQUdSQU0uQ0xJUFMuQzMuMzYwLmRhc2hfYmFzZWxpbmVfM192MSIsInhwdl9hc3NldF9pZCI6OTk2MTQ0OTk4OTkzNTM5LCJhc3NldF9hZ2VfZGF5cyI6NDEzLCJ2aV91c2VjYXNlX2lkIjoxMDA5OSwiZHVyYXRpb25fcyI6OTAsInVybGdlbl9zb3VyY2UiOiJ3d3cifQ%3D%3D&ccb=17-1&_nc_gid=c0a-TjvY6fR91GXlq02zlg&_nc_ss=1a&_nc_zt=28&vs=8f48ae413ff180c&_nc_vs=HBksFQIYUmlnX3hwdl9yZWVsc19wZXJtYW5lbnRfc3JfcHJvZC81MTQ2NTM5QTQ2NzMwRUZGNDMxREYxN0I2OUQ0MUVCMl92aWRlb19kYXNoaW5pdC5tcDQVAALIARIAFQIYRmlnX3hwdl9yZWVsc19wZXJtYW5lbnRfc3JfcHJvZC80OTE1NTQ3NzY5NzUzNDFfNDIyODEyMzU5MDY0MDE3Njc2NS5tcDQVAgLIARIAKAAYABsCiAd1c2Vfb2lsATEScHJvZ3Jlc3NpdmVfcmVjaXBlATEVAAAmhrr6zKL_xAMVAigCQzMsF0BWfU_fO2RaGBJkYXNoX2Jhc2VsaW5lXzNfdjERAHX-B2XmnQEA&oh=00_AfykdFx3VleI8ExLuV_L6mKZ3ccfuDfXMU5RmPXFcik-0w&oe=69B99C59 | AA4: 18 | AB4: 0 | AC4: 46097 | AD4: loupethis | AE4: collector_page | AF4: https://www.instagram.com/noritera24
A5: randallastout | B5: instagram | C5: Randall Stout | E5: 256 | F5: 1903 | G5: 10 | H5: FALSE | I5: FALSE | L5: https://instagram.feat1-1.fna.fbcdn.net/v/t51.2885-19/10995034_751782391607059_1655199174_a.jpg?stp=dst-jpg_e0_s150x150_tt6&efg=eyJ2ZW5jb2RlX3RhZyI6InByb2ZpbGVfcGljLmRqYW5nby4xNTAuYzIifQ&_nc_ht=instagram.feat1-1.fna.fbcdn.net&_nc_cat=107&_nc_oc=Q6cZ2QGOArsAUJST2fM8PXQZS_cKOhakikPL70tu157qONS9ci3Ywo4aoCC_dinQXKn7W1g&_nc_ohc=KSNNFb3rt88Q7kNvwGZwbrg&_nc_gid=Rn5gkxz-WSqp_QmAiqyh9w&edm=AOQ1c0wBAAAA&ccb=7-5&oh=00_AfwZVUBFo7bi0fu0Ih-amqmGLIsj_zocCKqo9LALk7w3pA&oe=69BDA83A&_nc_sid=8b3546 | O5: 0.0949 | P5: Maui always hits the sweet spot! #maui | Apua Point sunrise. #hawaii #sunrise #aloha | Aloha from Hawaii! #hawaii #aloha #rainbow #shaka | Bellows Beach #hawaii #hawaiilife #oahu #beach #ohana #beachlife #sunrise | Monk seals on Kaeana Point at the end of the hike. #kaeanapoint #hawaii #hawaiilife #hiking #oahu | Haleakala Crater epic 3 day hike. #nationalpark #hawaii #maui #backpacking #hiking #haleakala | Pedernales State Park is one of the jewels of Texas. #texashillcountry #texas #texasstaeparks #gooutside | Big Bend National Park. True Texas rugged beauty. #texas #texasoutdoors #nationalpark #bigbend #hiking | Texas/Mexico border at Big Bend National Park. Mexico left USA right. #texas #texasoutdoors #bigbend #riogrande #hiking #nationalpark | Texas Hill Country morning. #texas #hillcountry #rainbow #texashillcountry #morning | Q5: #maui, #hawaii, #sunrise, #aloha, #rainbow, #shaka, #hawaiilife, #oahu, #beach, #ohana, #beachlife, #kaeanapoint, #hiking, #nationalpark, #backpacking, #haleakala, #texashillcountry, #texas, #texasstaeparks, #gooutside, #texasoutdoors, #bigbend, #riogrande, #hillcountry, #morning | S5: https://instagram.com/p/Cq6vGfOsxi5, https://instagram.com/p/B6aU_JwnfXe, https://instagram.com/p/B6aUaCCHNYQ, https://instagram.com/p/Brw3vPHhXC3, https://instagram.com/p/Brw1kmzBQxk, https://instagram.com/p/BrwyueDhCcl, https://instagram.com/p/BqToCKXBEq0, https://instagram.com/p/BqKeYCYBCJQ, https://instagram.com/p/BqKdUQtBbpn, https://instagram.com/p/BqKcbwGhJDR | T5: 21, 20, 14, 36, 26, 33, 25, 32, 21, 10 | U5: 2, 0, 0, 0, 0, 0, 0, 2, 1, 0 | V5: 2023-04-12, 2019-12-23, 2019-12-23, 2018-12-24, 2018-12-24, 2018-12-24, 2018-11-18, 2018-11-14, 2018-11-14, 2018-11-14 | W5: Pedernales Falls State Park | X5: Sidecar, Image, Image, Sidecar, Sidecar, Sidecar, Sidecar, Sidecar, Image, Image | Y5: https://instagram.feat1-1.fna.fbcdn.net/v/t51.29350-15/340657872_1678421362629028_8174987527702465875_n.jpg?stp=dst-jpg_e35_s1080x1080_tt6&_nc_ht=instagram.feat1-1.fna.fbcdn.net&_nc_cat=104&_nc_oc=Q6cZ2QGOArsAUJST2fM8PXQZS_cKOhakikPL70tu157qONS9ci3Ywo4aoCC_dinQXKn7W1g&_nc_ohc=DUW2KkRDmz0Q7kNvwE-dfqi&_nc_gid=Rn5gkxz-WSqp_QmAiqyh9w&edm=AOQ1c0wBAAAA&ccb=7-5&ig_cache_key=MzA3ODk4MDQ0MDM2MjcwNzA4MA%3D%3D.3-ccb7-5&oh=00_AfzfzE2OQ2NbaPtoxI4Y59hNLdh24m_kDGY3WWDlBGDxjA&oe=69BD9510&_nc_sid=8b3546, https://instagram.feat1-1.fna.fbcdn.net/v/t51.29350-15/340657872_1678421362629028_8174987527702465875_n.jpg?stp=dst-jpg_e35_s1080x1080_tt6&_nc_ht=instagram.feat1-1.fna.fbcdn.net&_nc_cat=104&_nc_oc=Q6cZ2QGOArsAUJST2fM8PXQZS_cKOhakikPL70tu157qONS9ci3Ywo4aoCC_dinQXKn7W1g&_nc_ohc=DUW2KkRDmz0Q7kNvwE-dfqi&_nc_gid=Rn5gkxz-WSqp_QmAiqyh9w&edm=AOQ1c0wBAAAA&ccb=7-5&ig_cache_key=MzA3ODk4MDQ0MDM2MjcwNzA4MA%3D%3D.3-ccb7-5&oh=00_AfzfzE2OQ2NbaPtoxI4Y59hNLdh24m_kDGY3WWDlBGDxjA&oe=69BD9510&_nc_sid=8b3546, https://instagram.feat1-1.fna.fbcdn.net/v/t51.29350-15/340803674_691512369330787_3606777905602921519_n.jpg?stp=dst-jpg_e35_s1080x1080_tt6&_nc_ht=instagram.feat1-1.fna.fbcdn.net&_nc_cat=107&_nc_oc=Q6cZ2QGOArsAUJST2fM8PXQZS_cKOhakikPL70tu157qONS9ci3Ywo4aoCC_dinQXKn7W1g&_nc_ohc=78NEwZprkyQQ7kNvwFM_85y&_nc_gid=Rn5gkxz-WSqp_QmAiqyh9w&edm=AOQ1c0wBAAAA&ccb=7-5&ig_cache_key=MzA3ODk4MDQ0MDM3OTQ4MjE2Nw%3D%3D.3-ccb7-5&oh=00_AfxRM8NwOKoqIcNzenniXXYRmkKwGOX7StNv-1wWDdKHEQ&oe=69BDB95E&_nc_sid=8b3546, https://instagram.feat1-1.fna.fbcdn.net/v/t51.29350-15/340503206_3573203953002802_2114604039500305592_n.jpg?stp=dst-jpg_e35_s1080x1080_tt6&_nc_ht=instagram.feat1-1.fna.fbcdn.net&_nc_cat=110&_nc_oc=Q6cZ2QGOArsAUJST2fM8PXQZS_cKOhakikPL70tu157qONS9ci3Ywo4aoCC_dinQXKn7W1g&_nc_ohc=hY1r51imATEQ7kNvwGN7rJh&_nc_gid=Rn5gkxz-WSqp_QmAiqyh9w&edm=AOQ1c0wBAAAA&ccb=7-5&ig_cache_key=MzA3ODk4MDQ0MDM3OTU3NjE4NQ%3D%3D.3-ccb7-5&oh=00_AfzjTRdlq5PrOHd39culsx0Wwsjqowqyg0EzJgZuobGk3A&oe=69BDB9FC&_nc_sid=8b3546, https://instagram.feat1-1.fna.fbcdn.net/v/t51.29350-15/340816586_987792469296223_1944111262783992469_n.jpg?stp=dst-jpg_e35_s1080x1080_tt6&_nc_ht=instagram.feat1-1.fna.fbcdn.net&_nc_cat=107&_nc_oc=Q6cZ2QGOArsAUJST2fM8PXQZS_cKOhakikPL70tu157qONS9ci3Ywo4aoCC_dinQXKn7W1g&_nc_ohc=lLSBqth8XWoQ7kNvwEwRu2E&_nc_gid=Rn5gkxz-WSqp_QmAiqyh9w&edm=AOQ1c0wBAAAA&ccb=7-5&ig_cache_key=MzA3ODk4MDQ0MDM3OTQ5MTc4OA%3D%3D.3-ccb7-5&oh=00_AfyEYizKr79FNYaxhgEd_3d8PdKCbWwuisdU2P0gySKmRQ&oe=69BD9CA3&_nc_sid=8b3546, https://instagram.feat1-1.fna.fbcdn.net/v/t51.29350-15/340862953_146355141489759_8858516828834939274_n.jpg?stp=dst-jpg_e35_s1080x1080_tt6&_nc_ht=instagram.feat1-1.fna.fbcdn.net&_nc_cat=103&_nc_oc=Q6cZ2QGOArsAUJST2fM8PXQZS_cKOhakikPL70tu157qONS9ci3Ywo4aoCC_dinQXKn7W1g&_nc_ohc=-Z_6OA9w5J0Q7kNvwGdkHQO&_nc_gid=Rn5gkxz-WSqp_QmAiqyh9w&edm=AOQ1c0wBAAAA&ccb=7-5&ig_cache_key=MzA3ODk4MDQ0MDM3OTQ5NTY2NA%3D%3D.3-ccb7-5&oh=00_AfwQISOAs2pRMfguq70NbhqBe4HdLLidsoaXuRT39_x7Rw&oe=69BDAE76&_nc_sid=8b3546, https://instagram.feat1-1.fna.fbcdn.net/v/t51.29350-15/340843213_1280612262549588_3785486164969800256_n.jpg?stp=dst-jpg_e35_s1080x1080_tt6&_nc_ht=instagram.feat1-1.fna.fbcdn.net&_nc_cat=100&_nc_oc=Q6cZ2QGOArsAUJST2fM8PXQZS_cKOhakikPL70tu157qONS9ci3Ywo4aoCC_dinQXKn7W1g&_nc_ohc=B6fHTygPbdkQ7kNvwFqrKwF&_nc_gid=Rn5gkxz-WSqp_QmAiqyh9w&edm=AOQ1c0wBAAAA&ccb=7-5&ig_cache_key=MzA3ODk4MDQ0MDM3OTUxNzE5OQ%3D%3D.3-ccb7-5&oh=00_AfzWzJC--CfxKNe7AzhJwddZBj7C2eZ9MoMtbarX-uNyTg&oe=69BDAC59&_nc_sid=8b3546, https://instagram.feat1-1.fna.fbcdn.net/v/t51.29350-15/340476283_1155607365106777_7069126340872624172_n.jpg?stp=dst-jpg_e35_s1080x1080_tt6&_nc_ht=instagram.feat1-1.fna.fbcdn.net&_nc_cat=101&_nc_oc=Q6cZ2QGOArsAUJST2fM8PXQZS_cKOhakikPL70tu157qONS9ci3Ywo4aoCC_dinQXKn7W1g&_nc_ohc=0dVq5JA12cEQ7kNvwH3_Yy4&_nc_gid=Rn5gkxz-WSqp_QmAiqyh9w&edm=AOQ1c0wBAAAA&ccb=7-5&ig_cache_key=MzA3ODk4MDQ0MDM3OTU1MjYxOA%3D%3D.3-ccb7-5&oh=00_AfwfMO-BpyMMkVCKmSL1J2-VadVhlUIOOhG6WXnMTODDIw&oe=69BDB561&_nc_sid=8b3546, https://instagram.feat1-1.fna.fbcdn.net/v/t51.82787-15/649826470_18078968930377800_6276643227960842282_n.jpg?stp=dst-jpg_e35_s1080x1080_sh0.08_tt6&_nc_ht=instagram.feat1-1.fna.fbcdn.net&_nc_cat=100&_nc_oc=Q6cZ2QGOArsAUJST2fM8PXQZS_cKOhakikPL70tu157qONS9ci3Ywo4aoCC_dinQXKn7W1g&_nc_ohc=v6YLAGhJ9kkQ7kNvwHN8-W-&_nc_gid=Rn5gkxz-WSqp_QmAiqyh9w&edm=AOQ1c0wBAAAA&ccb=7-5&ig_cache_key=MzA3ODk4MDQ0MDM3MTEyNDQzNw%3D%3D.3-ccb7-5&oh=00_AfwdJGbj4Rz_dXROC1dLTLbO6awGb2wdt8TQAb6MrdI8Gg&oe=69BD907F&_nc_sid=8b3546, https://instagram.feat1-1.fna.fbcdn.net/v/t51.82787-15/651459367_18013884842669995_3238469732425330579_n.jpg?stp=dst-jpg_e35_s1080x1080_sh0.08_tt6&_nc_ht=instagram.feat1-1.fna.fbcdn.net&_nc_cat=107&_nc_oc=Q6cZ2QGOArsAUJST2fM8PXQZS_cKOhakikPL70tu157qONS9ci3Ywo4aoCC_dinQXKn7W1g&_nc_ohc=JPuuzPRyLTIQ7kNvwEKrFHv&_nc_gid=Rn5gkxz-WSqp_QmAiqyh9w&edm=AOQ1c0wBAAAA&ccb=7-5&ig_cache_key=MzA3ODk4MDQ0MDU0NzI1MTA2MA%3D%3D.3-ccb7-5&oh=00_AfwO4eXrLcPNPPFE9M68qlFn7ixAF89q1sJT50f1hlBAIQ&oe=69BDA901&_nc_sid=8b3546, https://instagram.feat1-1.fna.fbcdn.net/v/t51.29350-15/34 | Z5: https://instagram.feat1-1.fna.fbcdn.net/o1/v/t16/f2/m84/AQNjHVM0OvtuIgtzD3hkGUkKZ_i1VnLdL53wOAdgYAVwjL96fSjEbojfBkW1uMoriBcd6lQtZwu60t1wvr8iWJOuiSTXG-A1nL5hNJU.mp4?_nc_cat=111&_nc_oc=AdlAdZQlMrN6XTjsPO86kB4OpbM2J3TbYJ7nNT4tMw0-cIYLvjFIpI7fwqQkJopv3rU&_nc_sid=5e9851&_nc_ht=instagram.feat1-1.fna.fbcdn.net&_nc_ohc=owOmB7zJ33MQ7kNvwHzUlsl&efg=eyJ2ZW5jb2RlX3RhZyI6Inhwdl9wcm9ncmVzc2l2ZS5JTlNUQUdSQU0uQ0FST1VTRUxfSVRFTS5DMy42NDAuZGFzaF9iYXNlbGluZV8xX3YxIiwieHB2X2Fzc2V0X2lkIjoyOTU5NjgxODMyNDYzMjQsImFzc2V0X2FnZV9kYXlzIjoyNjUxLCJ2aV91c2VjYXNlX2lkIjoxMDE0NiwiZHVyYXRpb25fcyI6MjgsInVybGdlbl9zb3VyY2UiOiJ3d3cifQ%3D%3D&ccb=17-1&vs=3a48baf433d5b46f&_nc_vs=HBkcFQIYTGlnX2JhY2tmaWxsX3RpbWVsaW5lX3ZvZC8wMjQwRDFBNjI0MTUwOTE5OUQxMzJFRjBGM0RBNDFBRV92aWRlb19kYXNoaW5pdC5tcDQVAALIARIAKAAYABsCiAd1c2Vfb2lsATEScHJvZ3Jlc3NpdmVfcmVjaXBlATEVAAAm6Pfq5s7LhgEVAigCQzMsF0A8ogxJul41GBJkYXNoX2Jhc2VsaW5lXzFfdjERAHXuB2XEngEA&_nc_gid=Rn5gkxz-WSqp_QmAiqyh9w&_nc_ss=1a&_nc_zt=28&oh=00_AfxF9qWkaA1s39EbglTarE20-FuWpq0otSz9rBVe_3g0rA&oe=69B9BB6D | AA5: 24 | AB5: 1 | AC5: 46097 | AD5: loupethis | AE5: collector_page | AF5: https://www.instagram.com/randallastout
A6: gustavo_lopes_imagens | B6: instagram | C6: Gustavo Lopes | D6: Fotografia profissional. Whatsapp 16 99223 5263 | E6: 783 | F6: 1179 | G6: 220 | H6: FALSE | I6: FALSE | J6: Artist | K6: https://gustavolopesimagens.myportfolio.com/ | L6: https://scontent-phl2-1.cdninstagram.com/v/t51.2885-19/122009770_972297033262195_847262146995685250_n.jpg?stp=dst-jpg_e0_s150x150_tt6&efg=eyJ2ZW5jb2RlX3RhZyI6InByb2ZpbGVfcGljLmRqYW5nby4xMDgwLmMyIn0&_nc_ht=scontent-phl2-1.cdninstagram.com&_nc_cat=107&_nc_oc=Q6cZ2QFPWgNUb1KpcUUyXr4ds-2fIkhkHYd08XdLrBtvUKiX5WEtS6FVKMdUJCwbFCV3xCEfHlpcQYB_FSv18iWqwT6Y&_nc_ohc=iwsaVP3FaD0Q7kNvwFo49DP&_nc_gid=1pFHKT8-V7u_uRgJew64Sw&edm=AOQ1c0wBAAAA&ccb=7-5&oh=00_Afxlf1Y9oHxCyW4PEMea1rr6t9zowukcxCBnmwtYPEWo5g&oe=69BD95D6&_nc_sid=8b3546 | N6: 16 99223 5263 | O6: 0.0105 | P6: Trabalho realizado para @crizzapibolsasoficial ! | ... passagem de Som/Luz ! @sescfranca apresenta, @mawaca_oficial ! 06/12/2025 | ... passagem de Som/Luz ! @sescfranca apresenta, @mawaca_oficial ! | Para @cyateliebio ! | R6: @crizzapibolsasoficial, @sescfranca, @mawaca_oficial, @cyateliebio | S6: https://instagram.com/p/DV1zgRXia3y, https://instagram.com/p/DV1sImciWJw, https://instagram.com/p/DV1q5gVCS-d, https://instagram.com/p/DV1pjwmCR7q, https://instagram.com/p/DV1osJAiTPW, https://instagram.com/p/DV1oNiQCZFb, https://instagram.com/p/DUBk9yxibqb, https://instagram.com/p/DSoFFFZDF2V, https://instagram.com/p/DSP4yGIkQY5, https://instagram.com/p/DSAWoOCjQaF, https://instagram.com/p/DR-8RfRjI59, https://instagram.com/p/DRTpjPGjSAB | T6: 6, 3, 8, 3, 4, 3, 15, 1, 14, 22, 13, 5 | U6: 0, 0, 0, 0, 0, 0, 1, 0, 0, 1, 0, 0 | V6: 2026-03-13, 2026-03-13, 2026-03-13, 2026-03-13, 2026-03-13, 2026-03-13, 2026-01-27, 2025-12-24, 2025-12-14, 2025-12-08, 2025-12-08, 2025-11-21 | W6: Franca-SP, Taipu de Fora - Península de Maraú, Parque Nacional da Serra da Canastra, Sesc Franca, Franca SP | X6: Image, Video, Video, Video, Video, Video, Image, Image, Image, Image, Image, Image | Y6: https://scontent-phl2-1.cdninstagram.com/v/t51.82787-15/651921918_18075128885417012_1362013392195175345_n.webp?stp=dst-jpg_e35_s1080x1080_sh0.08_tt6&_nc_ht=scontent-phl2-1.cdninstagram.com&_nc_cat=108&_nc_oc=Q6cZ2QFPWgNUb1KpcUUyXr4ds-2fIkhkHYd08XdLrBtvUKiX5WEtS6FVKMdUJCwbFCV3xCEfHlpcQYB_FSv18iWqwT6Y&_nc_ohc=fFo-MREnCRIQ7kNvwE1Sp2e&_nc_gid=1pFHKT8-V7u_uRgJew64Sw&edm=AOQ1c0wBAAAA&ccb=7-5&ig_cache_key=Mzg1MjIxMTU3NDMyOTE1OTE1NA%3D%3D.3-ccb7-5&oh=00_AfxJNzBY90IRHxcWdnur5V-2ATFko7xCWtgvbXYnmFQOjQ&oe=69BDAEE8&_nc_sid=8b3546, https://scontent-phl2-1.cdninstagram.com/v/t51.82787-15/623834036_18070714028417012_1840575428941451126_n.webp?stp=dst-jpg_e35_s1080x1080_sh0.08_tt6&_nc_ht=scontent-phl2-1.cdninstagram.com&_nc_cat=108&_nc_oc=Q6cZ2QFPWgNUb1KpcUUyXr4ds-2fIkhkHYd08XdLrBtvUKiX5WEtS6FVKMdUJCwbFCV3xCEfHlpcQYB_FSv18iWqwT6Y&_nc_ohc=3kki3aiJZc0Q7kNvwEmRu9b&_nc_gid=1pFHKT8-V7u_uRgJew64Sw&edm=AOQ1c0wBAAAA&ccb=7-5&ig_cache_key=MzgxOTQ5NjUzNTA2NzU3Mjg5MQ%3D%3D.3-ccb7-5&oh=00_AfyVZLBXSkhlRPXmASWStRsBLABr9g6561BlECRuhTc4jQ&oe=69BD8881&_nc_sid=8b3546, https://scontent-phl2-1.cdninstagram.com/v/t51.82787-15/605709807_18067465175417012_6147621685105692945_n.webp?stp=dst-jpg_e35_s1080x1080_sh0.08_tt6&_nc_ht=scontent-phl2-1.cdninstagram.com&_nc_cat=108&_nc_oc=Q6cZ2QFPWgNUb1KpcUUyXr4ds-2fIkhkHYd08XdLrBtvUKiX5WEtS6FVKMdUJCwbFCV3xCEfHlpcQYB_FSv18iWqwT6Y&_nc_ohc=TidaMP0OMkoQ7kNvwFUBQN1&_nc_gid=1pFHKT8-V7u_uRgJew64Sw&edm=AOQ1c0wBAAAA&ccb=7-5&ig_cache_key=Mzc5NDMwNTAyNTY3ODUzMTk4OQ%3D%3D.3-ccb7-5&oh=00_AfxKVPt0HDSVC83SqMRyKrUNuo6E1J7mvqH4KRLZY8CzPQ&oe=69BD949A&_nc_sid=8b3546, https://scontent-phl2-1.cdninstagram.com/v/t51.82787-15/591571878_18066621008417012_4456102103001143751_n.webp?stp=dst-jpg_e35_s1080x1080_sh0.08_tt6&_nc_ht=scontent-phl2-1.cdninstagram.com&_nc_cat=108&_nc_oc=Q6cZ2QFPWgNUb1KpcUUyXr4ds-2fIkhkHYd08XdLrBtvUKiX5WEtS6FVKMdUJCwbFCV3xCEfHlpcQYB_FSv18iWqwT6Y&_nc_ohc=afcyM3T04PsQ7kNvwHi95Ev&_nc_gid=1pFHKT8-V7u_uRgJew64Sw&edm=AOQ1c0wBAAAA&ccb=7-5&ig_cache_key=Mzc4NzQ5NTU0NDgwNjUwODA4OQ%3D%3D.3-ccb7-5&oh=00_Afz4f9CfiJQso1RDz2LVcjo9gOCsAyCdqlmlwfSDbK0d-Q&oe=69BDA8BF&_nc_sid=8b3546, https://scontent-phl2-1.cdninstagram.com/v/t51.82787-15/590362270_18066045839417012_1317985682267789910_n.webp?stp=dst-jpg_e35_s1080x1080_sh0.08_tt6&_nc_ht=scontent-phl2-1.cdninstagram.com&_nc_cat=108&_nc_oc=Q6cZ2QFPWgNUb1KpcUUyXr4ds-2fIkhkHYd08XdLrBtvUKiX5WEtS6FVKMdUJCwbFCV3xCEfHlpcQYB_FSv18iWqwT6Y&_nc_ohc=67LFTq1dpRsQ7kNvwH__Zhl&_nc_gid=1pFHKT8-V7u_uRgJew64Sw&edm=AOQ1c0wBAAAA&ccb=7-5&ig_cache_key=Mzc4MzEyMzIwNzg2ODcxMjU4MQ%3D%3D.3-ccb7-5&oh=00_AfzswaFG_BZwVcwp335AwjBncIBePH6C_yXAyeEjYuhC7Q&oe=69BD834F&_nc_sid=8b3546, https://scontent-phl2-1.cdninstagram.com/v/t51.82787-15/591164059_18065984405417012_2561544330395023426_n.webp?stp=dst-jpg_e35_s1080x1080_sh0.08_tt6&_nc_ht=scontent-phl2-1.cdninstagram.com&_nc_cat=108&_nc_oc=Q6cZ2QFPWgNUb1KpcUUyXr4ds-2fIkhkHYd08XdLrBtvUKiX5WEtS6FVKMdUJCwbFCV3xCEfHlpcQYB_FSv18iWqwT6Y&_nc_ohc=JYVQditDp3UQ7kNvwEjf-qC&_nc_gid=1pFHKT8-V7u_uRgJew64Sw&edm=AOQ1c0wBAAAA&ccb=7-5&ig_cache_key=Mzc4MjcyNTgyMTYzOTk4NjgxMw%3D%3D.3-ccb7-5&oh=00_Afwq2dh9GBs-sWkDJ_GkjjEeBNyquX05tA5MoiVTh__YLA&oe=69BD9B34&_nc_sid=8b3546, https://scontent-phl2-1.cdninstagram.com/v/t51.82787-15/584366518_18064435880417012_6105331510785573369_n.webp?stp=dst-jpg_e35_s1080x1080_sh0.08_tt6&_nc_ht=scontent-phl2-1.cdninstagram.com&_nc_cat=108&_nc_oc=Q6cZ2QFPWgNUb1KpcUUyXr4ds-2fIkhkHYd08XdLrBtvUKiX5WEtS6FVKMdUJCwbFCV3xCEfHlpcQYB_FSv18iWqwT6Y&_nc_ohc=GyRhJgJNvRkQ7kNvwGJJVvB&_nc_gid=1pFHKT8-V7u_uRgJew64Sw&edm=AOQ1c0wBAAAA&ccb=7-5&ig_cache_key=Mzc3MDU0MDA1NDM0MzkxNzU2OQ%3D%3D.3-ccb7-5&oh=00_Afyw9PvqFQdzX5bi6vYifnFdvE9hn4zboi-RZ6YDeIV9OA&oe=69BDAB59&_nc_sid=8b3546 | Z6: https://scontent-phl2-1.cdninstagram.com/o1/v/t16/f2/m69/AQOLrX_DzFYXvdtnGa82YIH8Z5Yyf4hEvUt9q1XNybgd92u1oLTjrAeiS-rFiwO2ln_eFBStixihybqCdfL_Fwfh.mp4?strext=1&_nc_cat=108&_nc_sid=5e9851&_nc_ht=scontent-phl2-1.cdninstagram.com&_nc_ohc=XpaHJa3CupgQ7kNvwFBqXLo&efg=eyJ2ZW5jb2RlX3RhZyI6Inhwdl9wcm9ncmVzc2l2ZS5JTlNUQUdSQU0uQ0xJUFMuQzMuNzIwLmRhc2hfYmFzZWxpbmVfMV92MSIsInhwdl9hc3NldF9pZCI6MTgwNzUxMjQ2NzY0MTcwMTIsImFzc2V0X2FnZV9kYXlzIjoyLCJ2aV91c2VjYXNlX2lkIjoxMDA5OSwiZHVyYXRpb25fcyI6NSwidXJsZ2VuX3NvdXJjZSI6Ind3dyJ9&ccb=17-1&_nc_gid=1pFHKT8-V7u_uRgJew64Sw&_nc_ss=1a&_nc_zt=28&vs=c2cb3f12a3817c86&_nc_vs=HBkcFQIYOnBhc3N0aHJvdWdoX2V2ZXJzdG9yZS9HQ3Rqb0Nid1dUeXZ3TFFDQU5jZlR3ZE5LUmhBYnNwVEFRQUYVAALIARIAKAAYABsCiAd1c2Vfb2lsATEScHJvZ3Jlc3NpdmVfcmVjaXBlATEVAAAm6Nfemd3Om0AVAigCQzMsF0AUIcrAgxJvGBJkYXNoX2Jhc2VsaW5lXzFfdjERAHX-B2XmnQEA&oh=00_AfyPx1ZSenBHy5AaEZR38O0rYARKD727MtG-KUZ_ic1LCw&oe=69BDB994, https://scontent-phl2-1.cdninstagram.com/o1/v/t16/f2/m69/AQMAV2ctX29sKSeIQZpKQG3Ctgv-yfCdnExg24ihnMlCOVAa-ngSq4prG6-Fji3oPhGrUngN4cfqICHsBd3t77aH.mp4?strext=1&_nc_cat=107&_nc_sid=5e9851&_nc_ht=scontent-phl2-1.cdninstagram.com&_nc_ohc=Cvemj7HwIHkQ7kNvwE_6FRY&efg=eyJ2ZW5jb2RlX3RhZyI6Inhwdl9wcm9ncmVzc2l2ZS5JTlNUQUdSQU0uQ0xJUFMuQzMuNzIwLmRhc2hfYmFzZWxpbmVfMV92MSIsInhwdl9hc3NldF9pZCI6MTgwNzUxMjQyMTQ0MTcwMTIsImFzc2V0X2FnZV9kYXlzIjoyLCJ2aV91c2VjYXNlX2lkIjoxMDA5OSwiZHVyYXRpb25fcyI6NSwidXJsZ2VuX3NvdXJjZSI6Ind3dyJ9&ccb=17-1&_nc_gid=1pFHKT8-V7u_uRgJew64Sw&_nc_ss=1a&_nc_zt=28&vs=2fde5ed498b16528&_nc_vs=HBkcFQIYOnBhc3N0aHJvdWdoX2V2ZXJzdG9yZS9HRFk1cENiYmtwUm94d2dGQUlqdVVFdlF2M0FIYnNwVEFRQUYVAALIARIAKAAYABsCiAd1c2Vfb2lsATEScHJvZ3Jlc3NpdmVfcmVjaXBlATEVAAAm6JmS4dnOm0AVAigCQzMsF0AUIcrAgxJvGBJkYXNoX2Jhc2VsaW5lXzFfdjERAHX-B2XmnQEA&oh=00_Afx3fNwKEy2CG2l0og5g2IFIiyQk9ngXc8OvLuwh3y0-8Q&oe=69BD94FD, https://scontent-phl2-1.cdninstagram.com/o1/v/t16/f2/m69/AQMLbx7VysntC_VPg9hPEpNToyCID-m9mvPMwW7DQcyLb4T7uwnoY9auvBjPZ0kqIM6OED_DiiD8AYk4DXnmQl9N.mp4?strext=1&_nc_cat=111&_nc_sid=5e9851&_nc_ht=scontent-phl2-1.cdninstagram.com&_nc_ohc=S7OsF6E5rqYQ7kNvwFjZQyI&efg=eyJ2ZW5jb2RlX3RhZyI6Inhwdl9wcm9ncmVzc2l2ZS5JTlNUQUdSQU0uQ0xJUFMuQzMuNzIwLmRhc2hfYmFzZWxpbmVfMV92MSIsInhwdl9hc3NldF9pZCI6MTgwNzUxMjMzOTg0MTcwMTIsImFzc2V0X2FnZV9kYXlzIjoyLCJ2aV91c2VjYXNlX2lkIjoxMDA5OSwiZHVyYXRpb25fcyI6NSwidXJsZ2VuX3NvdXJjZSI6Ind3dyJ9&ccb=17-1&_nc_gid=1pFHKT8-V7u_uRgJew64Sw&_nc_ss=1a&_nc_zt=28&vs=824d553fa2ab5a3e&_nc_vs=HBkcFQIYOnBhc3N0aHJvdWdoX2V2ZXJzdG9yZS9HQWFFdmliQ2Z0ZkVHT0lEQU03VEhFZC1kcjFvYnNwVEFRQUYVAALIARIAKAAYABsCiAd1c2Vfb2lsATEScHJvZ3Jlc3NpdmVfcmVjaXBlATEVAAAm6On41tPOm0AVAigCQzMsF0AUIcrAgxJvGBJkYXNoX2Jhc2VsaW5lXzFfdjERAHX-B2XmnQEA&oh=00_AfxYxna72tbr-SfNeo-3HDPhXtl3mNnydDY5li3RII5MLg&oe=69BD8F21, https://scontent-phl2-1.cdninstagram.com/o1/v/t16/f2/m69/AQNHgx1viqChHfbgG-jq44QRjuZa2sBhRQhvq1K9O5KHFveNPQi4eQIiQ9LOH6EEIlKX5STgPBXX1SlzUnbeDDGx.mp4?strext=1&_nc_cat=107&_nc_sid=5e9851&_nc_ht=scontent-phl2-1.cdninstagram.com&_nc_ohc=9v1HjNLk-UwQ7kNvwERWd_V&efg=eyJ2ZW5jb2RlX3RhZyI6Inhwdl9wcm9ncmVzc2l2ZS5JTlNUQUdSQU0uQ0xJUFMuQzMuNzIwLmRhc2hfYmFzZWxpbmVfMV92MSIsInhwdl9hc3NldF9pZCI6MTgwNzUxMjI2NzU0MTcwMTIsImFzc2V0X2FnZV9kYXlzIjoyLCJ2aV91c2VjYXNlX2lkIjoxMDA5OSwiZHVyYXRpb25fcyI6NSwidXJsZ2VuX3NvdXJjZSI6Ind3dyJ9&ccb=17-1&_nc_gid=1pFHKT8-V7u_uRgJew64Sw&_nc_ss=1a&_nc_zt=28&vs=7ed5900c0f091787&_nc_vs=HBkcFQIYOnBhc3N0aHJvdWdoX2V2ZXJzdG9yZS9HS3VtdHliOHRwVGpEVXdEQUVuSG5MRUZRamRTYnNwVEFRQUYVAALIARIAKAAYABsCiAd1c2Vfb2lsATEScHJvZ3Jlc3NpdmVfcmVjaXBlATEVAAAm6P63pc7Om0AVAigCQzMsF0AUIcrAgxJvGBJkYXNoX2Jhc2VsaW5lXzFfdjERAHX-B2XmnQEA&oh=00_AfwLm9NMnX7zXhDPY5qXdXfU-WtoTIZlz8VPdjTZIzbicw&oe=69BDB321, https://scontent-phl2-1.cdninstagram.com/o1/v/t16/f2/m69/AQMADcVlBs31O_whCMjSgpTnE1l4FGNubYJZcooTYQ6iBnZvvG7u37mzizKGHHLawx3YI3meoiZ2BVVExTdKbRMZ.mp4?strext=1&_nc_cat=100&_nc_sid=5e9851&_nc_ht=scontent-phl2-1.cdninstagram.com&_nc_ohc=MCmBy5LxA3oQ7kNvwEmI4NE&efg=eyJ2ZW5jb2RlX3RhZyI6Inhwdl9wcm9ncmVzc2l2ZS5JTlNUQUdSQU0uQ0xJUFMuQzMuNzE2LmRhc2hfYmFzZWxpbmVfMV92MSIsInhwdl9hc3NldF9pZCI6MTgwNzUxMjIzNDU0MTcwMTIsImFzc2V0X2FnZV9kYXlzIjoyLCJ2aV91c2VjYXNlX2lkIjoxMDA5OSwiZHVyYXRpb25fcyI6NSwidXJsZ2VuX3NvdXJjZSI6Ind3dyJ9&ccb=17-1&_nc_gid=1pFHKT8-V7u_uRgJew64Sw&_nc_ss=1a&_nc_zt=28&vs=47f892d7476196f9&_nc_vs=HBkcFQIYOnBhc3N0aHJvdWdoX2V2ZXJzdG9yZS9HTllXMENiN0JacURMYk1FQURyVFRUMXp3b3BoYnNwVEFRQUYVAALIARIAKAAYABsCiAd1c2Vfb2lsATEScHJvZ3Jlc3NpdmVfcmVjaXBlATEVAAAm6OTc6svOm0AVAigCQzMsF0AUIcrAgxJvGBJkYXNoX2Jhc2VsaW5lXzFfdjERAHX-B2XmnQEA&oh=00_AfxDF1bKZ0IYmH8Jda1rTKqjGYagUGE6wOIvjFdX1SCz9g&oe=69BD9594 | AA6: 8 | AB6: 0 | AC6: 46097 | AD6: loupethis | AE6: collector_page | AF6: https://www.instagram.com/gustavo_lopes_imagens
A7: nazirhf | B7: instagram | C7: nhf | D7: Runs @tintabudi, @jurnalsvara & @apiapipublishing | E7: 2400 | F7: 3030 | G7: 207 | H7: FALSE | I7: FALSE | L7: https://scontent-lga3-1.cdninstagram.com/v/t51.82787-19/547828688_18524490142046327_604398495974004236_n.jpg?stp=dst-jpg_e0_s150x150_tt6&efg=eyJ2ZW5jb2RlX3RhZyI6InByb2ZpbGVfcGljLmRqYW5nby4xMDgwLmMyIn0&_nc_ht=scontent-lga3-1.cdninstagram.com&_nc_cat=111&_nc_oc=Q6cZ2QEr7COU0OD49weWTisnOg9_wfMTZJz9jfGWq62CTY2saGJpV34cqSIVXNGBFy_uyvY&_nc_ohc=6Ua0_Is5t5gQ7kNvwFndXH3&_nc_gid=Z0sderZHODGW2oHirMfPmA&edm=AOQ1c0wBAAAA&ccb=7-5&oh=00_AfyI9cbXeePO5KFjg-M4kJ9bzc5TYEmB5Ixmp2NzMOyygg&oe=69BD8D01&_nc_sid=8b3546 | O7: 0.0365 | P7: Halaqah Urban oleh @aliasalleh_ | ⁨ إِنَّا ِلِلَّٰهِ وَإِنَّا إِلَيْهِ رَاجِعُونَ Prof. Dr. Syed Muhammad Naquib al-Attas (1931-2026)⁩ | 3000 used books moved in, sorted, displayed and sold in a week time.Thanks @p_sharmin for the trust in running this. And grateful to friends of Tintabudi who came to help out and made the event lit (pun intended). Any other personal collection needs clearing the @tintabudi way? #shelflife | Closing on Sunday @tintabudi | Bucket list selesai. Terima kasih kepada @mdsyazreen yang menguruskan isu kali ini Dapatkan @jurnalsvara di @tintabudi, @imanshoppe.official, @pelitadhihin, @bukuibde, @ilhambooks, @kinokuniyamalaysia dan @riwayatmy | Some of Alatas’s works | I have several authors that I try to find every book that they ever wrote and Guenon’s is one of them. | Goodbye 2025. Let's go 2026. | The only books that matter 2025 #mastercraft | This one hits close to home. Patterson does a great job weaving his own journey as a reader into a serious reminder of why books and libraries are still so vital today. #nhfreads | Anak-anak skena. Jakarta-Jogja-KL | Kenangan bersama lukisan Raden Salleh ‘Penangkapan Pangeran Diponegoro’ sebelum dibawa pulang ke Istana Presiden. | Q7: #shelflife, #mastercraft, #nhfreads | R7: @aliasalleh_, @p_sharmin, @tintabudi, @mdsyazreen, @jurnalsvara, @imanshoppe.official, @pelitadhihin, @bukuibde, @ilhambooks, @kinokuniyamalaysia, @riwayatmy | S7: https://instagram.com/p/DV1OEXQk3uz, https://instagram.com/p/DVoKbN2E4zm, https://instagram.com/p/DVV_XNKkyXU, https://instagram.com/p/DUf1k20E8ZH, https://instagram.com/p/DUcHB8vE4kI, https://instagram.com/p/DTmBbzOkzqO, https://instagram.com/p/DTc-nG1E-gd, https://instagram.com/p/DS9F4HFE7fC, https://instagram.com/p/DS7InRAE_oH, https://instagram.com/p/DSo4pOhE14J, https://instagram.com/p/DSEpkUME9x0, https://instagram.com/p/DSB67E6k_90 | T7: 54, 261, 181, 88, 145, 43, 28, 43, 33, 64, 38, 58 | U7: 0, 2, 10, 0, 2, 0, 0, 1, 0, 0, 0, 1 | V7: 2026-03-13, 2026-03-08, 2026-03-01, 2026-02-08, 2026-02-07, 2026-01-17, 2026-01-13, 2026-01-01, 2025-12-31, 2025-12-24, 2025-12-10, 2025-12-09 | X7: Image, Image, Sidecar, Sidecar, Image, Image, Image, Image, Image, Image, Image, Image | Y7: https://scontent-lga3-1.cdninstagram.com/v/t51.82787-15/651545328_18567462412046327_5913143982973801096_n.jpg?stp=dst-jpg_e35_s1080x1080_sh0.08_tt6&_nc_ht=scontent-lga3-1.cdninstagram.com&_nc_cat=111&_nc_oc=Q6cZ2QEr7COU0OD49weWTisnOg9_wfMTZJz9jfGWq62CTY2saGJpV34cqSIVXNGBFy_uyvY&_nc_ohc=uzu8sZs7Z_EQ7kNvwGPCqW8&_nc_gid=Z0sderZHODGW2oHirMfPmA&edm=AOQ1c0wBAAAA&ccb=7-5&ig_cache_key=Mzg1MjA0NjkyODc4ODU1MjYyNw%3D%3D.3-ccb7-5&oh=00_Afygg41OG1Fqzv177dxmcdtMSuP7y5ucz6SUZ6BzZe7mYQ&oe=69BD81F2&_nc_sid=8b3546, https://scontent-lga3-1.cdninstagram.com/v/t51.82787-15/649107994_18566291695046327_6491534715431841470_n.jpg?stp=dst-jpg_e35_p1080x1080_sh0.08_tt6&_nc_ht=scontent-lga3-1.cdninstagram.com&_nc_cat=111&_nc_oc=Q6cZ2QEr7COU0OD49weWTisnOg9_wfMTZJz9jfGWq62CTY2saGJpV34cqSIVXNGBFy_uyvY&_nc_ohc=KDyweTZRd4UQ7kNvwGLZiUL&_nc_gid=Z0sderZHODGW2oHirMfPmA&edm=AOQ1c0wBAAAA&ccb=7-5&ig_cache_key=Mzg0ODM3MTczMjM0NDk2NjM3NA%3D%3D.3-ccb7-5&oh=00_Afyih9l_0StUx0oQGRWNwkKlknuGlYtXXFQYeOB0ZA_95w&oe=69BDB2A1&_nc_sid=8b3546, https://scontent-lga3-1.cdninstagram.com/v/t51.82787-15/645480132_18564825706046327_5959084862260944426_n.jpg?stp=dst-jpg_e35_s1080x1080_sh0.08_tt6&_nc_ht=scontent-lga3-1.cdninstagram.com&_nc_cat=111&_nc_oc=Q6cZ2QEr7COU0OD49weWTisnOg9_wfMTZJz9jfGWq62CTY2saGJpV34cqSIVXNGBFy_uyvY&_nc_ohc=qsZ1B25Sn00Q7kNvwFcDo2c&_nc_gid=Z0sderZHODGW2oHirMfPmA&edm=AOQ1c0wBAAAA&ccb=7-5&ig_cache_key=Mzg0MzI1NjUxNTI5ODU1OTUxNg%3D%3D.3-ccb7-5&oh=00_Afw4J_WqT3gCElbJvJheJ_b5-P49r7H0fQYv-DoNLlhHxA&oe=69BD97E6&_nc_sid=8b3546, https://scontent-lga3-1.cdninstagram.com/v/t51.82787-15/645480132_18564825706046327_5959084862260944426_n.jpg?stp=dst-jpg_e35_s1080x1080_sh0.08_tt6&_nc_ht=scontent-lga3-1.cdninstagram.com&_nc_cat=111&_nc_oc=Q6cZ2QEr7COU0OD49weWTisnOg9_wfMTZJz9jfGWq62CTY2saGJpV34cqSIVXNGBFy_uyvY&_nc_ohc=qsZ1B25Sn00Q7kNvwFcDo2c&_nc_gid=Z0sderZHODGW2oHirMfPmA&edm=AOQ1c0wBAAAA&ccb=7-5&ig_cache_key=Mzg0MzI1NjUxNTI5ODU1OTUxNg%3D%3D.3-ccb7-5&oh=00_Afw4J_WqT3gCElbJvJheJ_b5-P49r7H0fQYv-DoNLlhHxA&oe=69BD97E6&_nc_sid=8b3546, https://scontent-lga3-1.cdninstagram.com/v/t51.82787-15/642429724_18564825721046327_2255569224988633943_n.jpg?stp=dst-jpg_e35_s1080x1080_sh0.08_tt6&_nc_ht=scontent-lga3-1.cdninstagram.com&_nc_cat=111&_nc_oc=Q6cZ2QEr7COU0OD49weWTisnOg9_wfMTZJz9jfGWq62CTY2saGJpV34cqSIVXNGBFy_uyvY&_nc_ohc=EMcmSXQekT0Q7kNvwHgbjPY&_nc_gid=Z0sderZHODGW2oHirMfPmA&edm=AOQ1c0wBAAAA&ccb=7-5&ig_cache_key=Mzg0MzI1NjUxNTIzMTQ3MTAzMQ%3D%3D.3-ccb7-5&oh=00_AfyvmtXOYwKj-9P2KFeq1FtKGz8wY8W1L9vFuMA8rYxYwA&oe=69BD9C41&_nc_sid=8b3546, https://scontent-lga3-1.cdninstagram.com/v/t51.82787-15/642505697_18564825730046327_800853939227956884_n.jpg?stp=dst-jpg_e35_s1080x1080_sh0.08_tt6&_nc_ht=scontent-lga3-1.cdninstagram.com&_nc_cat=111&_nc_oc=Q6cZ2QEr7COU0OD49weWTisnOg9_wfMTZJz9jfGWq62CTY2saGJpV34cqSIVXNGBFy_uyvY&_nc_ohc=jTGhnYpHSqQQ7kNvwGaFu5y&_nc_gid=Z0sderZHODGW2oHirMfPmA&edm=AOQ1c0wBAAAA&ccb=7-5&ig_cache_key=Mzg0MzI1NjUxNTM0MDQ4NTE0Nw%3D%3D.3-ccb7-5&oh=00_AfyuWX0qrksODdc7Lqe68RQmOMWlvMkwjO4DEENTM6XRyw&oe=69BD88E9&_nc_sid=8b3546, https://scontent-lga3-1.cdninstagram.com/v/t51.82787-15/641365918_18564825739046327_3496938757983816521_n.jpg?stp=dst-jpg_e35_s1080x1080_sh0.08_tt6&_nc_ht=scontent-lga3-1.cdninstagram.com&_nc_cat=111&_nc_oc=Q6cZ2QEr7COU0OD49weWTisnOg9_wfMTZJz9jfGWq62CTY2saGJpV34cqSIVXNGBFy_uyvY&_nc_ohc=pXq-xbQIu2AQ7kNvwGiZUUa&_nc_gid=Z0sderZHODGW2oHirMfPmA&edm=AOQ1c0wBAAAA&ccb=7-5&ig_cache_key=Mzg0MzI1NjUxNTE0NzU5NTc1MQ%3D%3D.3-ccb7-5&oh=00_AfyTaI88po-1RP6sAea3qSB03tErsr938_jcbRlR88qdpA&oe=69BDAC7A&_nc_sid=8b3546, https://scontent-lga3-1.cdninstagram.com/v/t51.82787-15/643647273_18564825748046327_609466065879150444_n.jpg?stp=dst-jpg_e35_s1080x1080_sh0.08_tt6&_nc_ht=scontent-lga3-1.cdninstagram.com&_nc_cat=111&_nc_oc=Q6cZ2QEr7COU0OD49weWTisnOg9_wfMTZJz9jfGWq62CTY2saGJpV34cqSIVXNGBFy_uyvY&_nc_ohc=u6T57f9ecIAQ7kNvwETYOSD&_nc_gid=Z0sderZHODGW2oHirMfPmA&edm=AOQ1c0wBAAAA&ccb=7-5&ig_cache_key=Mzg0MzI1NjUxNTA4MDQ1MzcxMg%3D%3D.3-ccb7-5&oh=00_AfzwWioAUyFtWUJifItOUq_aJ6M4baKJFaoFKWW_2nCx3Q&oe=69BD9082&_nc_sid=8b3546, https://scontent-lga3-1.cdninstagram.com/v/t51.82787-15/630116463_18554537902046327_3500699800795890596_n.jpg?stp=dst-jpg_e35_s1080x1080_sh0.08_tt6&_nc_ht=scontent-lga3-1.cdninstagram.com&_nc_cat=111&_nc_oc=Q6cZ2QEr7COU0OD49weWTisnOg9_wfMTZJz9jfGWq62CTY2saGJpV34cqSIVXNGBFy_uyvY&_nc_ohc=mgJb8ZC3LE4Q7kNvwHfBCKk&_nc_gid=Z0sderZHODGW2oHirMfPmA&edm=AOQ1c0wBAAAA&ccb=7-5&ig_cache_key=MzgyODAxMzM5NDYxNjg4MjY0NQ%3D%3D.3-ccb7-5&oh=00_Afx6W1EM-Zroxi5JIfSYJZ6UK95KfLp6ntzOyK0ajmmJGA&oe=69BD9510&_nc_sid=8b3546, https://scontent-lga3-1.cdninstagram.com/v/t51.82787-15/630116463_18554537902046327_3500699800795890596_n.jpg?stp=dst-jpg_e35_s1080x1080_sh0.08_tt6&_nc_ht=scontent-lga3-1.cdninstagram.com&_nc_cat=111&_nc_oc=Q6cZ2QEr7COU0OD49weWTisnOg9_wfMTZJz9jfGWq62CTY2saGJpV34cqSIVXNGBFy_uyvY&_nc_ohc=mgJb8ZC3LE4Q7kNvwHfBCKk&_nc_gid=Z0sderZHODGW2oHirMfPmA&edm=AOQ1c0wBAAAA&ccb=7-5&ig_cache_key=MzgyODAxMzM5NDYxNjg4MjY0NQ%3D%3D.3-ccb7-5&oh=00_Afx6W1EM-Zroxi5JIfSYJZ6UK95KfLp6ntzOyK0ajmmJGA& | AA7: 86 | AB7: 1 | AC7: 46097 | AD7: loupethis | AE7: collector_page | AF7: https://www.instagram.com/nazirhf
A8: watch.hannya | B8: instagram | C8: Watch.Hannya | D8: • Made by passion, worn by addiction • Watch enthusiast based in🇨🇭 ☕️ Co-Founder @coffee.up.ge | E8: 4125 | F8: 450 | G8: 80 | H8: FALSE | I8: FALSE | L8: https://scontent-mia3-1.cdninstagram.com/v/t51.2885-19/487409001_1185285409739862_5408177916598286634_n.jpg?stp=dst-jpg_e0_s150x150_tt6&efg=eyJ2ZW5jb2RlX3RhZyI6InByb2ZpbGVfcGljLmRqYW5nby4xMDgwLmMyIn0&_nc_ht=scontent-mia3-1.cdninstagram.com&_nc_cat=106&_nc_oc=Q6cZ2QE9zaJNS1gG7BHZXRG1gFMU2O-FBl257JHroIzU68q-rlYlcZDPqr0h3RySZJT3bso&_nc_ohc=BiX8nLCp0bYQ7kNvwHZ8tjE&_nc_gid=9Os7afGw5OW3bcUeGLo6vA&edm=AOQ1c0wBAAAA&ccb=7-5&oh=00_AfwqV5lBt0A1Qep5Q7Q-cPrcWMQxDYrb9A_QeZoeyhTgdw&oe=69BD97A4&_nc_sid=8b3546 | O8: 0.1108 | P8: • Some recent nice shots • - Thanks to the owners - | • Some recent nice shots • - Thanks to the owners - | • Some recent nice shots • - Thanks to the owners - | SOLD 💸 🚨 FOR SALE 🚨 FP Journe Chronomètre Souverain 2019 Very rare “Embossé” Dial Platinum 40mm Serviced by FP Journe 06/2024 | • Masterpiece and insane craftsmanship from @langheyne • -Thanks to my friend @penny_watch_seoul for the shot- | • Some recent nice shots • - Thanks to the owners - | • Some recent nice shots • - Thanks to the owners - | • Some recent nice shots • - Thanks to the owners - | • Some recent nice shots • - Thanks to the owners - | • Some recent nice shots • - Thanks to the owners - | • Always good stuff @davidoffbrothers • | • Amazing craftsmanship from @herve_schluechter • | R8: @langheyne, @penny_watch_seoul, @davidoffbrothers, @herve_schluechter | S8: https://instagram.com/p/DVQWhRdjJge, https://instagram.com/p/DUsGILIDDRv, https://instagram.com/p/DUh3mo3jHuc, https://instagram.com/p/DT-oZn-jJVm, https://instagram.com/p/DT2RHxAjIZD, https://instagram.com/p/DTkKgBvjJnb, https://instagram.com/p/DTR9QWzjLk3, https://instagram.com/p/DS9gJNrDOBd, https://instagram.com/p/DSuEN4GjEnW, https://instagram.com/p/DSjsLLVjB5o, https://instagram.com/p/DSegpxPDObo, https://instagram.com/p/DSZeOkCDMmS | T8: 425, 310, 321, 912, 1109, 265, 186, 154, 328, 261, 418, 586 | U8: 19, 22, 7, 15, 34, 19, 11, 12, 11, 19, 21, 22 | V8: 2026-02-27, 2026-02-13, 2026-02-09, 2026-01-26, 2026-01-23, 2026-01-16, 2026-01-09, 2026-01-01, 2025-12-26, 2025-12-22, 2025-12-20, 2025-12-18 | W8: Geneva, Switzerland, Coffee UP Genève , El Gouna, Red Sea, Roy & Sacha Davidoff SA | X8: Sidecar, Sidecar, Sidecar, Sidecar, Sidecar, Sidecar, Sidecar, Sidecar, Sidecar, Sidecar, Sidecar, Sidecar | Y8: https://scontent-mia5-1.cdninstagram.com/v/t51.82787-15/641742317_17945478627112921_984117960037857577_n.jpg?stp=dst-jpg_e35_p1080x1080_sh0.08_tt6&_nc_ht=scontent-mia5-1.cdninstagram.com&_nc_cat=101&_nc_oc=Q6cZ2QE9zaJNS1gG7BHZXRG1gFMU2O-FBl257JHroIzU68q-rlYlcZDPqr0h3RySZJT3bso&_nc_ohc=mUWrEQ7IycUQ7kNvwHXuK1k&_nc_gid=9Os7afGw5OW3bcUeGLo6vA&edm=AOQ1c0wBAAAA&ccb=7-5&ig_cache_key=Mzg0MTY2ODU0NzAwNTQxOTk1Ng%3D%3D.3-ccb7-5&oh=00_AfwFGprGFk1SGAoCVWXwOQ_kYFCYxvM7APUdj1zp5777XQ&oe=69BDAFF2&_nc_sid=8b3546, https://scontent-mia5-1.cdninstagram.com/v/t51.82787-15/641742317_17945478627112921_984117960037857577_n.jpg?stp=dst-jpg_e35_p1080x1080_sh0.08_tt6&_nc_ht=scontent-mia5-1.cdninstagram.com&_nc_cat=101&_nc_oc=Q6cZ2QE9zaJNS1gG7BHZXRG1gFMU2O-FBl257JHroIzU68q-rlYlcZDPqr0h3RySZJT3bso&_nc_ohc=mUWrEQ7IycUQ7kNvwHXuK1k&_nc_gid=9Os7afGw5OW3bcUeGLo6vA&edm=AOQ1c0wBAAAA&ccb=7-5&ig_cache_key=Mzg0MTY2ODU0NzAwNTQxOTk1Ng%3D%3D.3-ccb7-5&oh=00_AfwFGprGFk1SGAoCVWXwOQ_kYFCYxvM7APUdj1zp5777XQ&oe=69BDAFF2&_nc_sid=8b3546, https://scontent-mia5-1.cdninstagram.com/v/t51.82787-15/642473468_17945478636112921_4465286423035737907_n.jpg?stp=dst-jpg_e35_p1080x1080_sh0.08_tt6&_nc_ht=scontent-mia5-1.cdninstagram.com&_nc_cat=101&_nc_oc=Q6cZ2QE9zaJNS1gG7BHZXRG1gFMU2O-FBl257JHroIzU68q-rlYlcZDPqr0h3RySZJT3bso&_nc_ohc=XbDl-LPRsFsQ7kNvwFpw2bz&_nc_gid=9Os7afGw5OW3bcUeGLo6vA&edm=AOQ1c0wBAAAA&ccb=7-5&ig_cache_key=Mzg0MTY2ODU0ODcxNjY5OTc5Nw%3D%3D.3-ccb7-5&oh=00_AfzMBZtiTGIQ14kejVmWs5pvqHXG4uI8DXrNMamvSGrpDA&oe=69BD83EF&_nc_sid=8b3546, https://scontent-mia5-1.cdninstagram.com/v/t51.82787-15/643022161_17945478645112921_1420987333123176952_n.jpg?stp=dst-jpg_e35_p1080x1080_sh0.08_tt6&_nc_ht=scontent-mia5-1.cdninstagram.com&_nc_cat=101&_nc_oc=Q6cZ2QE9zaJNS1gG7BHZXRG1gFMU2O-FBl257JHroIzU68q-rlYlcZDPqr0h3RySZJT3bso&_nc_ohc=tl_Lp-oP3UwQ7kNvwHfC9e6&_nc_gid=9Os7afGw5OW3bcUeGLo6vA&edm=AOQ1c0wBAAAA&ccb=7-5&ig_cache_key=Mzg0MTY2ODU1MTI2NjgyNTM0MA%3D%3D.3-ccb7-5&oh=00_AfxcH62b9dEtoR3fSJVxIXCV7Tw5x0aEs224273nLFJHOw&oe=69BD9867&_nc_sid=8b3546, https://scontent-mia5-1.cdninstagram.com/v/t51.82787-15/642961626_17945478654112921_4436091111268376464_n.jpg?stp=dst-jpg_e35_p1080x1080_sh0.08_tt6&_nc_ht=scontent-mia5-1.cdninstagram.com&_nc_cat=101&_nc_oc=Q6cZ2QE9zaJNS1gG7BHZXRG1gFMU2O-FBl257JHroIzU68q-rlYlcZDPqr0h3RySZJT3bso&_nc_ohc=MoHEn_42wJgQ7kNvwHWF71K&_nc_gid=9Os7afGw5OW3bcUeGLo6vA&edm=AOQ1c0wBAAAA&ccb=7-5&ig_cache_key=Mzg0MTY2ODU1MzczMzA5NTc3NA%3D%3D.3-ccb7-5&oh=00_AfxEPuGZ95i7joUINMBGMyhgSAC4-ayaUks9aztEm59ViQ&oe=69BD9F1F&_nc_sid=8b3546, https://scontent-mia5-1.cdninstagram.com/v/t51.82787-15/632376899_17942752125112921_2957067744531306457_n.jpg?stp=dst-jpg_e35_p1080x1080_sh0.08_tt6&_nc_ht=scontent-mia5-1.cdninstagram.com&_nc_cat=101&_nc_oc=Q6cZ2QE9zaJNS1gG7BHZXRG1gFMU2O-FBl257JHroIzU68q-rlYlcZDPqr0h3RySZJT3bso&_nc_ohc=VJ4SDl3Qn7gQ7kNvwG8Hcm2&_nc_gid=9Os7afGw5OW3bcUeGLo6vA&edm=AOQ1c0wBAAAA&ccb=7-5&ig_cache_key=MzgzMTQ2MzQ4Nzc3MjMyNjM2OQ%3D%3D.3-ccb7-5&oh=00_Afw_Rz0XB0y4hLJsHIB7r40agjvUapeOqcdx7vgLTsgW4A&oe=69BD9012&_nc_sid=8b3546, https://scontent-mia5-1.cdninstagram.com/v/t51.82787-15/632376899_17942752125112921_2957067744531306457_n.jpg?stp=dst-jpg_e35_p1080x1080_sh0.08_tt6&_nc_ht=scontent-mia5-1.cdninstagram.com&_nc_cat=101&_nc_oc=Q6cZ2QE9zaJNS1gG7BHZXRG1gFMU2O-FBl257JHroIzU68q-rlYlcZDPqr0h3RySZJT3bso&_nc_ohc=VJ4SDl3Qn7gQ7kNvwG8Hcm2&_nc_gid=9Os7afGw5OW3bcUeGLo6vA&edm=AOQ1c0wBAAAA&ccb=7-5&ig_cache_key=MzgzMTQ2MzQ4Nzc3MjMyNjM2OQ%3D%3D.3-ccb7-5&oh=00_Afw_Rz0XB0y4hLJsHIB7r40agjvUapeOqcdx7vgLTsgW4A&oe=69BD9012&_nc_sid=8b3546, https://scontent-mia5-1.cdninstagram.com/v/t51.82787-15/632377524_17942752134112921_2339004234029664523_n.jpg?stp=dst-jpg_e35_p1080x1080_sh0.08_tt6&_nc_ht=scontent-mia5-1.cdninstagram.com&_nc_cat=101&_nc_oc=Q6cZ2QE9zaJNS1gG7BHZXRG1gFMU2O-FBl257JHroIzU68q-rlYlcZDPqr0h3RySZJT3bso&_nc_ohc=5htMgsqxNUQQ7kNvwG5JKxB&_nc_gid=9Os7afGw5OW3bcUeGLo6vA&edm=AOQ1c0wBAAAA&ccb=7-5&ig_cache_key=MzgzMTQ2MzQ5MjY3OTY4NjkyNQ%3D%3D.3-ccb7-5&oh=00_AfyPQEK6rH89_OMr-vCxmHfUs6TlKeSH5hbBLc7Hf6Xdcg&oe=69BD81CA&_nc_sid=8b3546, https://scontent-mia5-1.cdninstagram.com/v/t51.82787-15/632007586_17942752143112921_6062397008574708529_n.jpg?stp=dst-jpg_e35_p1080x1080_sh0.08_tt6&_nc_ht=scontent-mia5-1.cdninstagram.com&_nc_cat=101&_nc_oc=Q6cZ2QE9zaJNS1gG7BHZXRG1gFMU2O-FBl257JHroIzU68q-rlYlcZDPqr0h3RySZJT3bso&_nc_ohc=wjq12vqJe6EQ7kNvwGhJeXT&_nc_gid=9Os7afGw5OW3bcUeGLo6vA&edm=AOQ1c0wBAAAA&ccb=7-5&ig_cache_key=MzgzMTQ2MzQ5ODMzMzYxMjY0Nw%3D%3D.3-ccb7-5&oh=00_AfzNHbz95H7kXfovvbkSzri_cXSFotuQX87QR4FVHzfIOg&oe=69BD8E50&_nc_sid=8b3546, https://scontent-mia5-1.cdninstagram.com/v/t51.82787-15/632911281_17942752152112921_6439576999263774520_n.jpg?stp=dst-jpg_e35_p1080x1080_sh0.08_tt6&_nc_ht=scontent-mia5-1.cdninstagram.com&_nc_cat=101&_nc_oc=Q6cZ2QE9zaJNS1gG7BHZXRG1gFMU2O-FBl257JHroIzU68q-rlYlcZDPqr0h3RySZJT3bso&_nc_ohc=ULpgph3-KR0Q7kNvwEzGM55&_nc_gid=9Os7afGw5OW3bcUeGLo6vA&edm=AOQ1c0wBAAAA&ccb=7-5&ig_cache_key=MzgzMTQ2MzUwMTYwNTEzNzkzMA%3D%3D.3-ccb7-5&oh=00_AfwuIgNGYpvie70ePsMi_bS7DUhSSb5ZRh7P71Es_sYDaQ& | Z8: https://scontent-mia3-3.cdninstagram.com/o1/v/t16/f2/m84/AQPWLLQBy5VtUYZzKJmaUD2fE2QWqr7ldOe68hhx3xL4ZRmWkrns0lw74LIF96fc91m2xZCvoe5hbulbXl-pdk-Ht2DHmomkwm6Lr7E.mp4?_nc_cat=108&_nc_sid=5e9851&_nc_ht=scontent-mia3-3.cdninstagram.com&_nc_ohc=LRbuT7NC6FgQ7kNvwES95HN&efg=eyJ2ZW5jb2RlX3RhZyI6Inhwdl9wcm9ncmVzc2l2ZS5JTlNUQUdSQU0uQ0FST1VTRUxfSVRFTS5DMy43MjAuZGFzaF9iYXNlbGluZV8xX3YxIiwieHB2X2Fzc2V0X2lkIjoxNTg0MjE4ODY2MDMzMTgzLCJhc3NldF9hZ2VfZGF5cyI6NDgsInZpX3VzZWNhc2VfaWQiOjEwMTQ2LCJkdXJhdGlvbl9zIjoxNCwidXJsZ2VuX3NvdXJjZSI6Ind3dyJ9&ccb=17-1&_nc_gid=9Os7afGw5OW3bcUeGLo6vA&_nc_ss=1a&_nc_zt=28&vs=d0c88616a7d21e64&_nc_vs=HBkcFQIYTGlnX2JhY2tmaWxsX3RpbWVsaW5lX3ZvZC9DQzRDRDkwMDE4NjEzOTFCRUI5QTI1QkE2NzkzODZBNV92aWRlb19kYXNoaW5pdC5tcDQVAALIARIAKAAYABsCiAd1c2Vfb2lsATEScHJvZ3Jlc3NpdmVfcmVjaXBlATEVAAAmvoiNrNa10AUVAigCQzMsF0As3bItDlYEGBJkYXNoX2Jhc2VsaW5lXzFfdjERAHXuB2XEngEA&oh=00_AfwtuHfqh7riZVof_77AuMbOhR1Qfos3IAXfRn5gwyziwA&oe=69B9AF98, https://scontent-mia3-2.cdninstagram.com/o1/v/t16/f2/m84/AQNC-Zc3FdqBK67kRyBKxhNK4IoRaJ_NHp3cnc7JQUtNN5cjjO6NwejUT8XbAMnxLtTM5eFfyeOcXiLmBQenEcXdw8001fVVnaT2y0c.mp4?_nc_cat=105&_nc_sid=5e9851&_nc_ht=scontent-mia3-2.cdninstagram.com&_nc_ohc=0hDnBrN0E4EQ7kNvwFmryYD&efg=eyJ2ZW5jb2RlX3RhZyI6Inhwdl9wcm9ncmVzc2l2ZS5JTlNUQUdSQU0uQ0FST1VTRUxfSVRFTS5DMy43MjAuZGFzaF9iYXNlbGluZV8xX3YxIiwieHB2X2Fzc2V0X2lkIjo4NzA3MDg0MTkwNDg4MjUsImFzc2V0X2FnZV9kYXlzIjo1MiwidmlfdXNlY2FzZV9pZCI6MTAxNDYsImR1cmF0aW9uX3MiOjgsInVybGdlbl9zb3VyY2UiOiJ3d3cifQ%3D%3D&ccb=17-1&_nc_gid=9Os7afGw5OW3bcUeGLo6vA&_nc_ss=1a&_nc_zt=28&vs=89cb8dc92686f423&_nc_vs=HBkcFQIYTGlnX2JhY2tmaWxsX3RpbWVsaW5lX3ZvZC9CQjQ3NUI0RTZCOEY1NkRGNTcwOEM3NUQwODNBM0NBMF92aWRlb19kYXNoaW5pdC5tcDQVAALIARIAKAAYABsCiAd1c2Vfb2lsATEScHJvZ3Jlc3NpdmVfcmVjaXBlATEVAAAm8tWpoPP5iwMVAigCQzMsF0Ag3bItDlYEGBJkYXNoX2Jhc2VsaW5lXzFfdjERAHXuB2XEngEA&oh=00_Afzxjm3-w-P7IZq25AVFtm8Y28P9U973vY3qkvzHJIBHTA&oe=69B99A03, https://scontent-mia5-1.cdninstagram.com/o1/v/t16/f2/m84/AQNAW_bsGAY8gXgfTlITbcUwVU9rKoBS8-lkQNt5QEcRVjbRj2iwjVmVCtFWeMN0YrfbXSY1UKI2-egoXm_s-Cb7Ba3f4ZjWPBmHeHA.mp4?_nc_cat=102&_nc_sid=5e9851&_nc_ht=scontent-mia5-1.cdninstagram.com&_nc_ohc=Y2IfXT-dyWkQ7kNvwE0gq4w&efg=eyJ2ZW5jb2RlX3RhZyI6Inhwdl9wcm9ncmVzc2l2ZS5JTlNUQUdSQU0uQ0FST1VTRUxfSVRFTS5DMy43MjAuZGFzaF9iYXNlbGluZV8xX3YxIiwieHB2X2Fzc2V0X2lkIjoxMTUwNjYyNzMzODA4MzE2LCJhc3NldF9hZ2VfZGF5cyI6NTIsInZpX3VzZWNhc2VfaWQiOjEwMTQ2LCJkdXJhdGlvbl9zIjo4LCJ1cmxnZW5fc291cmNlIjoid3d3In0%3D&ccb=17-1&_nc_gid=9Os7afGw5OW3bcUeGLo6vA&_nc_ss=1a&_nc_zt=28&vs=45c6c5d0ef4044bd&_nc_vs=HBkcFQIYTGlnX2JhY2tmaWxsX3RpbWVsaW5lX3ZvZC84NzQwQkIxRUNCMjU2QjYwNjk0OTc1REQ5OTBGRURBNV92aWRlb19kYXNoaW5pdC5tcDQVAALIARIAKAAYABsCiAd1c2Vfb2lsATEScHJvZ3Jlc3NpdmVfcmVjaXBlATEVAAAm-IqKuLGhiwQVAigCQzMsF0AgRBiTdLxqGBJkYXNoX2Jhc2VsaW5lXzFfdjERAHXuB2XEngEA&oh=00_AfzDaXXn6qSg8NXYuXs9eshjK6o0LnhZJFpO9_B3O8i1mg&oe=69B99066, https://scontent-mia3-2.cdninstagram.com/o1/v/t16/f2/m84/AQOtSmmbUMEz8SSEZVsDnJEGSFhDCV37KHrVMGEgN09oGzMETZkxdxFLX8kqTUvZ6okHm5He2_blhcgWIyqkCFqX14vPOJ3trDQmc2U.mp4?_nc_cat=105&_nc_sid=5e9851&_nc_ht=scontent-mia3-2.cdninstagram.com&_nc_ohc=2-dr-v6oWh8Q7kNvwFReOjW&efg=eyJ2ZW5jb2RlX3RhZyI6Inhwdl9wcm9ncmVzc2l2ZS5JTlNUQUdSQU0uQ0FST1VTRUxfSVRFTS5DMy43MjAuZGFzaF9iYXNlbGluZV8xX3YxIiwieHB2X2Fzc2V0X2lkIjozOTg5MjkxMDk0Njk1OTAxLCJhc3NldF9hZ2VfZGF5cyI6ODgsInZpX3VzZWNhc2VfaWQiOjEwMTQ2LCJkdXJhdGlvbl9zIjoxMiwidXJsZ2VuX3NvdXJjZSI6Ind3dyJ9&ccb=17-1&_nc_gid=9Os7afGw5OW3bcUeGLo6vA&_nc_ss=1a&_nc_zt=28&vs=ddced2b3afe5347c&_nc_vs=HBkcFQIYTGlnX2JhY2tmaWxsX3RpbWVsaW5lX3ZvZC85MTRFMzdCODMyOTY4QTk4NjcyMUEyRDYxQURFMzU5OV92aWRlb19kYXNoaW5pdC5tcDQVAALIARIAKAAYABsCiAd1c2Vfb2lsATEScHJvZ3Jlc3NpdmVfcmVjaXBlATEVAAAmuv_W6aaPlg4VAigCQzMsF0Aod0vGp--eGBJkYXNoX2Jhc2VsaW5lXzFfdjERAHXuB2XEngEA&oh=00_Afxuuykk-m2YE4JwSsYSPdsW78cuNqgSepVzYePABc9KgA&oe=69B9BBB3 | AA8: 440 | AB8: 18 | AC8: 46097 | AD8: loupethis | AE8: collector_page | AF8: https://www.instagram.com/watch.hannya
A9: watchreleases | B9: instagram | C9: Watch Releases | Microbrand Release Calendar 📅 | D9: 🔔 Latest drops • Microbrand focus⌚️ 🏆 Includes best under $500 & $1000 💡 Discover new watch brands 🌎 “Posting all the watches I can’t buy” 😅 🇨🇦 | E9: 707 | F9: 1804 | G9: 61 | H9: FALSE | I9: TRUE | J9: None,News & media website | K9: https://ocarat.com/montre-reef-395-mm-blue-coral-formex-x-ocarat-edition-speciale-bracelet-caoutchouc-bleu-formex | L9: https://scontent-dfw5-1.cdninstagram.com/v/t51.82787-19/640457993_18032447117599137_6427850351051794001_n.jpg?stp=dst-jpg_e0_s150x150_tt6&efg=eyJ2ZW5jb2RlX3RhZyI6InByb2ZpbGVfcGljLmRqYW5nby44NTkuYzIifQ&_nc_ht=scontent-dfw5-1.cdninstagram.com&_nc_cat=109&_nc_oc=Q6cZ2QFBh6zu8d24HRXhgfd3NDisSVhjqlKMZICfWPm4aaVrmr6OCV3ANtd2VAVFx1_yWMU&_nc_ohc=0vO9nbvKHlsQ7kNvwGHn4UB&_nc_gid=x2-bXAKRrL1aAizBGrVbiQ&edm=AOQ1c0wBAAAA&ccb=7-5&oh=00_Afzor-99upl6Am9jWgAvLnjHy9Om63XlaN5VunTYyP5WqA&oe=69BDB040&_nc_sid=8b3546 | O9: 0.056 | P9: The 2026 microbrand scene is hitting different. 🌍⌚ From technical powerhouses to design disruptors, here are the top 10 names you need to know right now. 🏆 🏆 The Top 10 1. Christopher Ward 🇬🇧 – The Swiss-engineered technical powerhouse. @chriswardlondon 🧬 2. Zelos 🇸🇬 – The innovative mast | 🌊 @formexwatch x @ocarat: The “Blue Coral” Special Edition 🪸✨ We’re diving deep with Ocarat to bring you a truly unique take on the REEF 39.5mm! ⌚️💙 Here’s the breakdown of these two stunners: 🔹 The Special Edition (Pic 1): Features an exclusive “Blue Coral” dial with a hand-applied, textured | The Ultimate Tool Watch: @laventurewatches Marine Type 3 🌑⚓️ The Marine Type 3 Titanium Black is the perfect blend of rugged adventure and refined Swiss engineering. 🇨🇭🛠️ Crafted from high-strength Grade 5 Titanium, it’s incredibly lightweight yet built to withstand the toughest conditions—from | NEW RELEASE: The @yema_watches Superman Titanium Moontide CMM.11 🇫🇷✨ From the depths of the ocean to the craters of the moon! 🌊🌕 YEMA has officially launched a celestial masterpiece: the Superman Titanium Moontide. This limited edition combines iconic French diver DNA with a high-tech, lunar-in | Pre-Order Now: The @ballwatch Engineer Hydrocarbon AeroGMT II Patriot 🇺🇸✨ History meets the heavens in this stunning new release! 🌌 For the first time ever, Ball Watch introduces a breathtaking Aventurine dial—a shimmering glass infused with metallic crystals that looks like a starry night on yo | 🎨 @swatch AI-DADA: Where Chaos Meets Code! 🤖🌀 Get ready to disrupt the timeline! 💥 The new Swatch AI-DADA collection is officially here, and it’s a total vibe shift. 🕰️🚀 We’ve taken the rebellious, “no-rules” spirit of Dadaism 🎭 and fused it with the limitless power of Artificial Intelligenc | Heritage flight DNA meets modern titanium toughness in the all-new @rzewatches 🇸🇬 Resolute Type A. ✈️🏔️ We’ve reimagined the classic aviator’s tool with our signature angular design and UltraHex™ scratch-resistant coating—making it light enough for the cockpit and tough enough for the climb. 💪⌚ | The @doxawatchesofficial x @gioielleriagrande SUB 200 Grande Roma ☕️✨🏛️ A masterclass in sunray gradients and sophisticated styling! The SUB 200 Grande Roma takes that iconic 1960s diver silhouette and elevates it with a stunning “fumé” dial that shifts beautifully from deep espresso to warm bronz | 🧭 THE ADVENTURE STARTS HERE 🧭 @dasherwatchco Meet the all-new 🇺🇸 Dasher Scout Automatic—the ultimate “Go Anywhere, Do Anything” field watch! 🌲⌚️ We’ve taken a timeless, vintage-inspired design and beefed it up for the modern explorer. 🛡️⛰️ Why you’ll love it: • ⚙️ Reliable Automatic Movement | The Ultimate Explorer Has Arrived! ⌚️🔥 @noduswatches x @raven_watches 🇺🇸 The wait is OVER! Introducing the Trailtrekker — an epic powerhouse collaboration between Nodus and Raven Watches 🤝⛰️ This isn’t just a watch; it’s your new favorite travel companion, blending Nodus’ technical precision wi | 🌌 @rampart.studio x @havenwatchco 🌌 🚀 Studio Rampart has teamed up with Haven Watches to bring you the Trespass Limited Edition—a masterclass in high-contrast utility and modern-vintage design. Featuring a striking deep indigo dial and electric cyan numerals, this isn’t just a watch; it’s a wea | @avi_8 Honoring a legend with the luck of the Irish. ☘️✈️ Introducing the Spitfire Smith 24 Hour Automatic Paddy Limited Edition. ⌚️ This isn’t just a watch; it’s a tribute to Brendan “Paddy” Finucane, the top-scoring Irish ace of WWII. 🎖️ From the aviation-green dial to the iconic shamrock motif | R9: @chriswardlondon, @zeloswatches, @studio.underd0g, @sericawatches, @formexwatch, @fareruniversal, @brewwatches, @beaucroftwatches, @noduswatches, @balticwatches, @varioeveryday, @traskawatch, @traffordwatchco, @lorierwatches, @halioswatches, @ocarat, @laventurewatches, @yema_watches, @ballwatch, @swatch, @rzewatches, @doxawatchesofficial, @gioielleriagrande, @dasherwatchco, @raven_watches, @rampart.studio, @havenwatchco, @avi_8 | S9: https://instagram.com/p/DV3khbokSkH, https://instagram.com/p/DV7sB2tDXVU, https://instagram.com/p/DV6_YgOiZww, https://instagram.com/p/DV6T_F2kQIM, https://instagram.com/p/DV5xrKTDhE2, https://instagram.com/p/DV5Clb6DJ-3, https://instagram.com/p/DV4ZPlbCRqX, https://instagram.com/p/DV2_nixjuYj, https://instagram.com/p/DV2gDN2DPA7, https://instagram.com/p/DV11S_cCYCX, https://instagram.com/p/DV1HRJCEdqf, https://instagram.com/p/DV0L7flDrOP | T9: 32, 8, 14, 19, 10, 8, 22, 24, 43, 114, 15, 117 | U9: 16, 0, 3, 2, 0, 1, 0, 0, 7, 8, 5, 7 | V9: 2026-03-14, 2026-03-16, 2026-03-15, 2026-03-15, 2026-03-15, 2026-03-15, 2026-03-14, 2026-03-14, 2026-03-14, 2026-03-13, 2026-03-13, 2026-03-13 | W9: Canada, Switzerland, France, USA, Singapore | X9: Sidecar, Sidecar, Sidecar, Sidecar, Sidecar, Sidecar, Sidecar, Sidecar, Sidecar, Sidecar, Sidecar, Sidecar | Y9: https://scontent-dfw5-1.cdninstagram.com/v/t51.82787-15/652774030_18037158683599137_6079653412609096910_n.jpg?stp=dst-jpg_e15_tt6&_nc_ht=scontent-dfw5-1.cdninstagram.com&_nc_cat=109&_nc_oc=Q6cZ2QFBh6zu8d24HRXhgfd3NDisSVhjqlKMZICfWPm4aaVrmr6OCV3ANtd2VAVFx1_yWMU&_nc_ohc=yq8wEjRTHZEQ7kNvwG5xMtt&_nc_gid=x2-bXAKRrL1aAizBGrVbiQ&edm=AOQ1c0wBAAAA&ccb=7-5&ig_cache_key=Mzg1MjcwNDY1MDY5MzI0ODYxMg%3D%3D.3-ccb7-5&oh=00_Afy5FpDV4fzS9LnBnfkVqZPoXKWzC5AbUBoDv0ZXo9QgVQ&oe=69BD8408&_nc_sid=8b3546, https://scontent-dfw5-1.cdninstagram.com/v/t51.82787-15/652774030_18037158683599137_6079653412609096910_n.jpg?stp=dst-jpg_e15_tt6&_nc_ht=scontent-dfw5-1.cdninstagram.com&_nc_cat=109&_nc_oc=Q6cZ2QFBh6zu8d24HRXhgfd3NDisSVhjqlKMZICfWPm4aaVrmr6OCV3ANtd2VAVFx1_yWMU&_nc_ohc=yq8wEjRTHZEQ7kNvwG5xMtt&_nc_gid=x2-bXAKRrL1aAizBGrVbiQ&edm=AOQ1c0wBAAAA&ccb=7-5&ig_cache_key=Mzg1MjcwNDY1MDY5MzI0ODYxMg%3D%3D.3-ccb7-5&oh=00_Afy5FpDV4fzS9LnBnfkVqZPoXKWzC5AbUBoDv0ZXo9QgVQ&oe=69BD8408&_nc_sid=8b3546, https://scontent-dfw5-1.cdninstagram.com/v/t51.82787-15/652677695_18037158680599137_3279263665419642400_n.jpg?stp=dst-jpg_e15_tt6&_nc_ht=scontent-dfw5-1.cdninstagram.com&_nc_cat=109&_nc_oc=Q6cZ2QFBh6zu8d24HRXhgfd3NDisSVhjqlKMZICfWPm4aaVrmr6OCV3ANtd2VAVFx1_yWMU&_nc_ohc=QybKt4jgVG4Q7kNvwGIhDNl&_nc_gid=x2-bXAKRrL1aAizBGrVbiQ&edm=AOQ1c0wBAAAA&ccb=7-5&ig_cache_key=Mzg1MjcwNDY1MjMyMDY2Mjk0Ng%3D%3D.3-ccb7-5&oh=00_AfwxESPbOltEOZfej7TxMeTWphrkQwANYWqNGhDQujITfQ&oe=69BDAF5F&_nc_sid=8b3546, https://scontent-dfw5-1.cdninstagram.com/v/t51.82787-15/653681369_18037508219599137_1058117385057602988_n.jpg?stp=dst-jpg_e15_tt6&_nc_ht=scontent-dfw5-1.cdninstagram.com&_nc_cat=109&_nc_oc=Q6cZ2QFBh6zu8d24HRXhgfd3NDisSVhjqlKMZICfWPm4aaVrmr6OCV3ANtd2VAVFx1_yWMU&_nc_ohc=G3ywLvu0YoIQ7kNvwE2Ftx4&_nc_gid=x2-bXAKRrL1aAizBGrVbiQ&edm=AOQ1c0wBAAAA&ccb=7-5&ig_cache_key=Mzg1Mzg2NzQ4NTgwODYyNTgxNA%3D%3D.3-ccb7-5&oh=00_AfyOUp_DVE_lodLw01FuUnCj8jHW7UE9rNPVVQUfF7excw&oe=69BDB516&_nc_sid=8b3546, https://scontent-dfw5-1.cdninstagram.com/v/t51.82787-15/653681369_18037508219599137_1058117385057602988_n.jpg?stp=dst-jpg_e15_tt6&_nc_ht=scontent-dfw5-1.cdninstagram.com&_nc_cat=109&_nc_oc=Q6cZ2QFBh6zu8d24HRXhgfd3NDisSVhjqlKMZICfWPm4aaVrmr6OCV3ANtd2VAVFx1_yWMU&_nc_ohc=G3ywLvu0YoIQ7kNvwE2Ftx4&_nc_gid=x2-bXAKRrL1aAizBGrVbiQ&edm=AOQ1c0wBAAAA&ccb=7-5&ig_cache_key=Mzg1Mzg2NzQ4NTgwODYyNTgxNA%3D%3D.3-ccb7-5&oh=00_AfyOUp_DVE_lodLw01FuUnCj8jHW7UE9rNPVVQUfF7excw&oe=69BDB516&_nc_sid=8b3546, https://scontent-dfw5-1.cdninstagram.com/v/t51.82787-15/652738398_18037508228599137_3590323524558380266_n.jpg?stp=dst-jpg_e15_fr_s1080x1080_tt6&_nc_ht=scontent-dfw5-1.cdninstagram.com&_nc_cat=109&_nc_oc=Q6cZ2QFBh6zu8d24HRXhgfd3NDisSVhjqlKMZICfWPm4aaVrmr6OCV3ANtd2VAVFx1_yWMU&_nc_ohc=0ivKOG5TOIcQ7kNvwHzZzXV&_nc_gid=x2-bXAKRrL1aAizBGrVbiQ&edm=AOQ1c0wBAAAA&ccb=7-5&ig_cache_key=Mzg1Mzg2NzQ4Nzk5ODA4Mzg5Ng%3D%3D.3-ccb7-5&oh=00_AfyK_dDGtBSWuxI-92QKLCSI1hNh14I3gCZPFDzHIeGbqQ&oe=69BD8C0C&_nc_sid=8b3546, https://scontent-dfw5-1.cdninstagram.com/v/t51.82787-15/652972712_18037508240599137_8591631498868698405_n.jpg?stp=dst-jpg_e15_fr_s1080x1080_tt6&_nc_ht=scontent-dfw5-1.cdninstagram.com&_nc_cat=109&_nc_oc=Q6cZ2QFBh6zu8d24HRXhgfd3NDisSVhjqlKMZICfWPm4aaVrmr6OCV3ANtd2VAVFx1_yWMU&_nc_ohc=Srz26jHD_SkQ7kNvwH8xSkt&_nc_gid=x2-bXAKRrL1aAizBGrVbiQ&edm=AOQ1c0wBAAAA&ccb=7-5&ig_cache_key=Mzg1Mzg2NzQ5MDIyOTQzNDk3Nw%3D%3D.3-ccb7-5&oh=00_AfzGtpIgHnMX_lLxguyFWnvfzhCgI1yq6CtYht1mbQBhzg&oe=69BD9DCE&_nc_sid=8b3546, https://scontent-dfw5-1.cdninstagram.com/v/t51.82787-15/652747554_18037508249599137_1621378714349753800_n.jpg?stp=dst-jpg_e15_fr_s1080x1080_tt6&_nc_ht=scontent-dfw5-1.cdninstagram.com&_nc_cat=109&_nc_oc=Q6cZ2QFBh6zu8d24HRXhgfd3NDisSVhjqlKMZICfWPm4aaVrmr6OCV3ANtd2VAVFx1_yWMU&_nc_ohc=UHvx2wzE0wgQ7kNvwH0qnMi&_nc_gid=x2-bXAKRrL1aAizBGrVbiQ&edm=AOQ1c0wBAAAA&ccb=7-5&ig_cache_key=Mzg1Mzg2NzQ5MjA4MzM0MTA2OQ%3D%3D.3-ccb7-5&oh=00_Afxvi1nL2vwW7gbMuvJ3mm6MoHnCyQ3Qolbtc1jhIHE-vA&oe=69BD829E&_nc_sid=8b3546, https://scontent-dfw5-1.cdninstagram.com/v/t51.82787-15/652568392_18037463342599137_1624408587812995856_n.jpg?stp=dst-jpg_e35_p1080x1080_sh0.08_tt6&_nc_ht=scontent-dfw5-1.cdninstagram.com&_nc_cat=109&_nc_oc=Q6cZ2QFBh6zu8d24HRXhgfd3NDisSVhjqlKMZICfWPm4aaVrmr6OCV3ANtd2VAVFx1_yWMU&_nc_ohc=ZbmeFmzTFREQ7kNvwFCkso-&_nc_gid=x2-bXAKRrL1aAizBGrVbiQ&edm=AOQ1c0wBAAAA&ccb=7-5&ig_cache_key=Mzg1MzY3MDQ2NTkyNzc0NDc0MQ%3D%3D.3-ccb7-5&oh=00_AfzMeGu-sKJ1VSf7lOSZNS8RvDdVK5__oNQJRvhXqYW49g&oe=69BDA3F0&_nc_sid=8b3546, https://scontent-dfw5-1.cdninstagram.com/v/t51.82787-15/652568392_18037463342599137_1624408587812995856_n.jpg?stp=dst-jpg_e35_p1080x1080_sh0.08_tt6&_nc_ht=scontent-dfw5-1.cdninstagram.com&_nc_cat=109&_nc_oc=Q6cZ2QFBh6zu8d24HRXhgfd3NDisSVhjqlKMZICfWPm4aaVrmr6OCV3ANtd2VAVFx1_yWMU&_nc_ohc=ZbmeFmzTFREQ7kNvwFCkso-&_nc_gid=x2-bXAKRrL1aAizBGrVbiQ&edm=AOQ1c0wBAAAA&ccb=7-5&ig_cache_key=Mzg1MzY3MDQ2NTkyNzc0NDc0MQ%3D%3D.3-ccb7-5&oh=00_AfzMeGu-sKJ1VSf7lOSZNS8RvDdVK5__oNQJRvhXqYW49g&oe=69BDA3F0&_nc_sid=8b3546, https://scontent-dfw5-1.cdninstagram.com/v/t51.82787-15/651876061_180374 | AA9: 36 | AB9: 4 | AC9: 46097 | AD9: loupethis | AE9: collector_page | AF9: https://www.instagram.com/watchreleases
A10: arthur_leroux_mrs | B10: instagram | C10: Arthur Leroux | D10: Entrepreneur engagé, marseillais exigeant #landscape #food #travel #streetphotography #sailing #nature #vintagelens | E10: 701 | F10: 3613 | G10: 524 | H10: FALSE | I10: FALSE | K10: http://www.enogia.com/ | L10: https://scontent-ord5-3.cdninstagram.com/v/t51.2885-19/434201302_430590642839238_7006826567109940978_n.jpg?stp=dst-jpg_e0_s150x150_tt6&efg=eyJ2ZW5jb2RlX3RhZyI6InByb2ZpbGVfcGljLmRqYW5nby4xMDgwLmMyIn0&_nc_ht=scontent-ord5-3.cdninstagram.com&_nc_cat=106&_nc_oc=Q6cZ2QFryhgakpRT0gWGKrjZj6ThnrOR3foMaGfLbqNwzJMmef8PB3PNLYlA_dJzkonJRuI&_nc_ohc=pGIMWDeRWYUQ7kNvwHHd28y&_nc_gid=9tdv6bUA0gfXcHUy2rj3QA&edm=AOQ1c0wBAAAA&ccb=7-5&oh=00_Afw5XfpYJ7vltW0qknwzmxl1haAtnweYbvT-Zqdg9alTPA&oe=69BD8AD1&_nc_sid=8b3546 | O10: 0.0169 | P10: Le commentaire qui tue ... | Waaaat ? | RIP Rick ... | Busan by night | Mon premier budai Ippei Uemura Bon même décongelé avec soin le sashimi était vraiment pas incroyable, mais sauté au beurre et shoyu ça marche très bien ! | Belle nav' | Pays de moutons ! | Enogia Skunk Works, la crème de la crème ! | Incendie a Itaewon | Les aires d'autoroute en Corée c'est quand même le futur ... | Last train for ... | Naniii ? | S10: https://instagram.com/p/DRZGWTxCJEW, https://instagram.com/p/DPhYwLFCMPY, https://instagram.com/p/DOVnk98CLWu, https://instagram.com/p/DKm-qGrqP_G, https://instagram.com/p/DJlW7woKidi, https://instagram.com/p/DJMflZ_KnSE, https://instagram.com/p/DIzI3L4KOVu, https://instagram.com/p/DHwPR_EoAgU, https://instagram.com/p/DGlARP7oxcn, https://instagram.com/p/DGhidpPo2Y1, https://instagram.com/p/DGecutDoZqN, https://instagram.com/p/DGebOCGsA4M | T10: 5, 2, 4, 24, 13, 15, 13, 22, 7, 11, 16, 10 | U10: 0, 0, 0, 0, 0, 0, 0, 0, 0, 0, 0, 0 | V10: 2025-11-23, 2025-10-07, 2025-09-08, 2025-06-07, 2025-05-13, 2025-05-03, 2025-04-23, 2025-03-28, 2025-02-27, 2025-02-26, 2025-02-25, 2025-02-25 | X10: Image, Image, Image, Sidecar, Image, Image, Sidecar, Image, Sidecar, Sidecar, Image, Image | Y10: https://scontent-ord5-3.cdninstagram.com/v/t39.30808-6/584458044_10162151175300897_4581801579681546549_n.jpg?stp=dst-jpg_e15_fr_p1080x1080_tt6&_nc_ht=scontent-ord5-3.cdninstagram.com&_nc_cat=109&_nc_oc=Q6cZ2QFryhgakpRT0gWGKrjZj6ThnrOR3foMaGfLbqNwzJMmef8PB3PNLYlA_dJzkonJRuI&_nc_ohc=rUzKkluIdEAQ7kNvwG0BM9E&_nc_gid=9tdv6bUA0gfXcHUy2rj3QA&edm=AOQ1c0wAAAAA&ccb=7-5&ig_cache_key=Mzc3MjA3NDA4NDIzMDc5NTU0Mg%3D%3D.3-ccb7-5&oh=00_Afzx6DMPVlWhOJKsogfmfg13zUD_IcFeq23CbXz3IkfKiA&oe=69BDB8BE&_nc_sid=8b3546, https://scontent-ord5-3.cdninstagram.com/v/t39.30808-6/558903251_10161967521345897_8323761216754531530_n.jpg?stp=dst-jpg_e15_fr_p1080x1080_tt6&_nc_ht=scontent-ord5-3.cdninstagram.com&_nc_cat=109&_nc_oc=Q6cZ2QFryhgakpRT0gWGKrjZj6ThnrOR3foMaGfLbqNwzJMmef8PB3PNLYlA_dJzkonJRuI&_nc_ohc=TEr6-uC_DQoQ7kNvwHcwboR&_nc_gid=9tdv6bUA0gfXcHUy2rj3QA&edm=AOQ1c0wAAAAA&ccb=7-5&ig_cache_key=MzczODM3ODAyOTI0MDk5MjcyOA%3D%3D.3-ccb7-5&oh=00_Afz7SGB6mrAwbT01ElXrSGClohc1jTuE_rCJ3ggRutjh_Q&oe=69BD9549&_nc_sid=8b3546, https://scontent-ord5-3.cdninstagram.com/v/t39.30808-6/544976554_10161853609110897_6154365983244646742_n.jpg?stp=dst-jpg_e15_tt6&_nc_ht=scontent-ord5-3.cdninstagram.com&_nc_cat=109&_nc_oc=Q6cZ2QFryhgakpRT0gWGKrjZj6ThnrOR3foMaGfLbqNwzJMmef8PB3PNLYlA_dJzkonJRuI&_nc_ohc=oOMNThI1IYQQ7kNvwEdlcO5&_nc_gid=9tdv6bUA0gfXcHUy2rj3QA&edm=AOQ1c0wAAAAA&ccb=7-5&ig_cache_key=MzcxNzA1MTEzMTY4NDc2MzA1NA%3D%3D.3-ccb7-5&oh=00_Afx0G6yymtUY9K4pky8vCU8vGaDdTfceOyDoXbg6E_B18Q&oe=69BDAD19&_nc_sid=8b3546, https://scontent-ord5-3.cdninstagram.com/v/t39.30808-6/505135126_10161444059205897_818812211620757396_n.jpg?stp=dst-jpg_e35_p1080x1080_sh0.08_tt6&_nc_ht=scontent-ord5-3.cdninstagram.com&_nc_cat=109&_nc_oc=Q6cZ2QFryhgakpRT0gWGKrjZj6ThnrOR3foMaGfLbqNwzJMmef8PB3PNLYlA_dJzkonJRuI&_nc_ohc=JlFRcVHeHYQQ7kNvwHYH7NA&_nc_gid=9tdv6bUA0gfXcHUy2rj3QA&edm=AOQ1c0wAAAAA&ccb=7-5&ig_cache_key=MzY0OTg4MDA4MTgzNjkwOTg3NA%3D%3D.3-ccb7-5&oh=00_AfwQp4Ysoe106K0-pp4EdPGIg9hqU_mclgDMasP82rt0_w&oe=69BDB6C0&_nc_sid=8b3546, https://scontent-ord5-3.cdninstagram.com/v/t39.30808-6/505135126_10161444059205897_818812211620757396_n.jpg?stp=dst-jpg_e35_p1080x1080_sh0.08_tt6&_nc_ht=scontent-ord5-3.cdninstagram.com&_nc_cat=109&_nc_oc=Q6cZ2QFryhgakpRT0gWGKrjZj6ThnrOR3foMaGfLbqNwzJMmef8PB3PNLYlA_dJzkonJRuI&_nc_ohc=JlFRcVHeHYQQ7kNvwHYH7NA&_nc_gid=9tdv6bUA0gfXcHUy2rj3QA&edm=AOQ1c0wAAAAA&ccb=7-5&ig_cache_key=MzY0OTg4MDA4MTgzNjkwOTg3NA%3D%3D.3-ccb7-5&oh=00_AfwQp4Ysoe106K0-pp4EdPGIg9hqU_mclgDMasP82rt0_w&oe=69BDB6C0&_nc_sid=8b3546, https://scontent-ord5-3.cdninstagram.com/v/t39.30808-6/505415731_10161444058650897_4881082333167838992_n.jpg?stp=dst-jpg_e35_p1080x1080_sh0.08_tt6&_nc_ht=scontent-ord5-3.cdninstagram.com&_nc_cat=109&_nc_oc=Q6cZ2QFryhgakpRT0gWGKrjZj6ThnrOR3foMaGfLbqNwzJMmef8PB3PNLYlA_dJzkonJRuI&_nc_ohc=PcFbn9aiddcQ7kNvwEvFle6&_nc_gid=9tdv6bUA0gfXcHUy2rj3QA&edm=AOQ1c0wAAAAA&ccb=7-5&ig_cache_key=MzY0OTg4MDA4MTAxNDg1MTA4Mw%3D%3D.3-ccb7-5&oh=00_Afw3VRbxXhgiVHJmiSGhmj37ksmDd7RqX8qrY8wWPws4jg&oe=69BDB489&_nc_sid=8b3546, https://scontent-ord5-1.cdninstagram.com/v/t39.30808-6/505116182_10161444059575897_197184069360052613_n.jpg?stp=dst-jpg_e35_s1080x1080_sh0.08_tt6&_nc_ht=scontent-ord5-1.cdninstagram.com&_nc_cat=101&_nc_oc=Q6cZ2QFryhgakpRT0gWGKrjZj6ThnrOR3foMaGfLbqNwzJMmef8PB3PNLYlA_dJzkonJRuI&_nc_ohc=kCCuAMdO2WkQ7kNvwGIY8qt&_nc_gid=9tdv6bUA0gfXcHUy2rj3QA&edm=AOQ1c0wAAAAA&ccb=7-5&ig_cache_key=MzY0OTg4MDA4MjE3MjQ4NDQwNw%3D%3D.3-ccb7-5&oh=00_Afz-DQCOuByOCABxjg4X5TiLGk2ghWhsLlCOigILBhLKyA&oe=69BDA1E1&_nc_sid=8b3546, https://scontent-ord5-3.cdninstagram.com/v/t39.30808-6/505188802_10161444058935897_7347537946640860430_n.jpg?stp=dst-jpg_e35_s1080x1080_sh0.08_tt6&_nc_ht=scontent-ord5-3.cdninstagram.com&_nc_cat=109&_nc_oc=Q6cZ2QFryhgakpRT0gWGKrjZj6ThnrOR3foMaGfLbqNwzJMmef8PB3PNLYlA_dJzkonJRuI&_nc_ohc=nFfRLLRNNG8Q7kNvwElHuPl&_nc_gid=9tdv6bUA0gfXcHUy2rj3QA&edm=AOQ1c0wAAAAA&ccb=7-5&ig_cache_key=MzY0OTg4MDA4MTAwNjQ3MDg5Mw%3D%3D.3-ccb7-5&oh=00_AfzNhF71Sp1XUiWhvILzNnDv9mDwiV__znbxhB0WycP_dg&oe=69BD97AC&_nc_sid=8b3546, https://scontent-ord5-2.cdninstagram.com/v/t39.30808-6/496857807_10161346936430897_5868247948732170941_n.jpg?stp=dst-jpg_e35_s1080x1080_sh0.08_tt6&_nc_ht=scontent-ord5-2.cdninstagram.com&_nc_cat=105&_nc_oc=Q6cZ2QFryhgakpRT0gWGKrjZj6ThnrOR3foMaGfLbqNwzJMmef8PB3PNLYlA_dJzkonJRuI&_nc_ohc=7A9ixzDmBYsQ7kNvwFXR0wM&_nc_gid=9tdv6bUA0gfXcHUy2rj3QA&edm=AOQ1c0wAAAAA&ccb=7-5&ig_cache_key=MzYzMTQwOTUzODIzMDAwMzU1NA%3D%3D.3-ccb7-5&oh=00_AfwJe67s1kAZ7NgPaRqioL_QwndeoEpb_G2u_AOj6ggmKQ&oe=69BD8B36&_nc_sid=8b3546, https://scontent-ord5-2.cdninstagram.com/v/t39.30808-6/495196854_10161312265880897_5074574647325931998_n.jpg?stp=dst-jpg_e15_fr_s1080x1080_tt6&_nc_ht=scontent-ord5-2.cdninstagram.com&_nc_cat=105&_nc_oc=Q6cZ2QFryhgakpRT0gWGKrjZj6ThnrOR3foMaGfLbqNwzJMmef8PB3PNLYlA_dJzkonJRuI&_nc_ohc=kfjiRI0lmIUQ7kNvwGvNFdZ&_nc_gid=9tdv6bUA0gfXcHUy2rj3QA&edm=AOQ1c0wAAAAA&ccb=7-5&ig_cache_key=MzYyNDQxMDcxMDA5MjE4MjY2MA%3D%3D.3-ccb7-5&oh=00_AfyUr2exRO533PoUBPgfBbnJI3D5WPpbHGF-EA7Qsv9yig&oe=69BDB324&_nc_sid=8b3546, https://scont | AA10: 12 | AB10: 0 | AC10: 46097 | AD10: loupethis | AE10: collector_page | AF10: https://www.instagram.com/arthur_leroux_mrs
A11: thefinancialwrist | B11: instagram | C11: Wristy Business | D11: Wristing It All ⚠️ All photos are mine and best enjoyed with sound on 🔊 | E11: 56 | F11: 291 | G11: 14 | H11: FALSE | I11: FALSE | J11: Financial Consultant | L11: https://instagram.fagc1-2.fna.fbcdn.net/v/t51.82787-19/642364068_17917766478461408_5250971267696881435_n.jpg?stp=dst-jpg_e0_s150x150_tt6&efg=eyJ2ZW5jb2RlX3RhZyI6InByb2ZpbGVfcGljLmRqYW5nby45MTEuYzIifQ&_nc_ht=instagram.fagc1-2.fna.fbcdn.net&_nc_cat=108&_nc_oc=Q6cZ2QEiAh4T4nk0gqIF3qnvXyNEEUo2HbxO3tauZzg8kRJRXXm5YR95-MbFeuJLxeXsEgA&_nc_ohc=qnA35JSSpngQ7kNvwFUwXtG&_nc_gid=lo0P6mamMwu4MpvA6gaIMA&edm=AOQ1c0wBAAAA&ccb=7-5&oh=00_AfwKUCLP1F7SVKwppVEV68TwIu03vn_yzXU_ghvThTjX7A&oe=69BD95E3&_nc_sid=8b3546 | O11: 0.2455 | P11: The Rolex Oyster Perpetual 126000 Pistachio today 🥜 Always find myself tussling between this and the Patek Philippe Aquanaut 5065a. Both are equally as comfortable as a daily driver, and both whisper (not shout), especially in office settings. Today, the 👑 wins. | The Patek Philippe Nautilus 3800 on a sunny day and basking in all its glory ☀️ The matching yellow tritium lumes on the hands and hour markers are always a sight for sore eyes. Always grateful to @strictlyvintagewatches @ericmwind for the patience and guidance, especially when they knew it was g | The JLC Reverso Tribute Monoface at 40mm x 24mm 🙇🏻‍♂️ Has to be the best modern iteration of the Reverso. Its the closest you can get to the 1931 original models, with a modern finish to the case and dial! The sunburst blue dial is just mesmerising! Great price, great proportions! And thickness | Speedmaster on a Milanese! 🤩 Swapped out the nato strap for this Milanese bracelet. Entirely different Speedy and I love it. Just means one thing - more wrist time. Also, is it me or the way the hesalite crystal reflects the sun just gorgeously resembles the visor on an astronaut's helmet? Last | Ever look down on your wrist, be enamoured by your watch, stare at it for a good 30 secs, all while twisting your wrist (like you're playing foosball in college) just to admire all angles of it - only to look up to your wife rolling her eyes 🙄🙄🙄? I cannot be the only one. This Patek Philippe Aq | The Audemars Piguet Code 11.59 Starwheel. Good guys at AP House Singapore were gracious enough to let me tinker with it and we had a great time chatting. Always been a fan of the Wandering Hours complication and this one is no exception. Truth be told, was never a fan of the Code 11.59 but this ri | The Nomos Club Campus "Blurple" at 36mm. This is a 1-of-1! only because it was a wedding gift from the siblings, engraved cleverly at the back - NOMOSingle. Goes without saying, a special piece! | No idea what Dunhill model this is 😅 But stole it from my dad to wear for a day, back in my corporate finance days, it was easily on my wrist for 16 hours that day My father is not a "watch guy", but he sure did pick a beauty as his first "luxury" timepiece. The cushion case, lugs, sector dial, a | The Omega Speedmaster Professional 1861. Or to be more specific in true Omega fashion, the ref 311.30.42.30.01.005 (can never memorise them). At 42mm case diameter and 14mm thickness, its rarely on my wrist these days. Feels just a tad bit hefty, and not in my current rotation. but who knows? The | The (destro) Toledano and Chan B/1.2 Tahitian Mother of Pearl. Thinking about this today. Was too late to pull the trigger, sold out in split second when it launched in mid 2025. and missed it again when they found a few pieces in their inventory late 2025! Regardless! Got a chance to fiddle wit | My first Rolex (from the AD!), the Rolex Submariner 124060 👑 at 41mm. No bells and whistles. Just a clean dial with no date window, crisp ceramic bezel and sharp overall case (as Rolex always do). Not much to say really, but 👌🏼👌🏼👌🏼 | The Rolex Oyster Perpetual 126000 "Pistachio" at 36mm 👑 Fave piece in the rotation now. Am a sucker for dials, its the life of the watch imo. Have never seen a green like this on a watch dial before. Some even call it the "Matcha Latte" lol. A thoughtful gift from my wife, for my birthday and to | R11: @strictlyvintagewatches, @ericmwind, @forstnerofficial, @theminutemon, @toledanoandchan, @alfredkkchan, @misterenthusiast, @constant.kw, @revolution.watch, @wei_koh_revolution | S11: https://instagram.com/p/DVsOhT1ktFy, https://instagram.com/p/DVc0EzxElDy, https://instagram.com/p/DVaQewcktq-, https://instagram.com/p/DVSrNrlEgz8, https://instagram.com/p/DVP8_aXElz9, https://instagram.com/p/DVNWSGKEqm3, https://instagram.com/p/DVJEof1EvSE, https://instagram.com/p/DVC-5wLkuUE, https://instagram.com/p/DVAtHI5ki4X, https://instagram.com/p/DU9ro1Mkvel, https://instagram.com/p/DU6-Qz5ks-p, https://instagram.com/p/DU4jOpCEv_3 | T11: 2, 10, 13, 13, 12, 8, 15, 14, 9, 15, 13, 16 | U11: 1, 3, 4, 1, 1, 1, 1, 5, 3, 3, 1, 1 | V11: 2026-03-10, 2026-03-04, 2026-03-03, 2026-02-28, 2026-02-27, 2026-02-26, 2026-02-24, 2026-02-22, 2026-02-21, 2026-02-20, 2026-02-19, 2026-02-18 | W11: Jaeger-LeCoultre, AP House Singapore | X11: Image, Image, Sidecar, Sidecar, Image, Sidecar, Image, Image, Image, Image, Image, Image | Y11: https://instagram.fagc1-2.fna.fbcdn.net/v/t51.82787-15/649064926_17919173280461408_4299181232838686150_n.jpg?stp=dst-jpg_e35_p1080x1080_sh0.08_tt6&_nc_ht=instagram.fagc1-2.fna.fbcdn.net&_nc_cat=108&_nc_oc=Q6cZ2QEiAh4T4nk0gqIF3qnvXyNEEUo2HbxO3tauZzg8kRJRXXm5YR95-MbFeuJLxeXsEgA&_nc_ohc=DxDiOlq8oPQQ7kNvwHKq6Jb&_nc_gid=lo0P6mamMwu4MpvA6gaIMA&edm=AOQ1c0wBAAAA&ccb=7-5&ig_cache_key=Mzg0OTUxNTY0MzE4ODcyODE3OA%3D%3D.3-ccb7-5&oh=00_AfyNhNRDysf1tZimpLpQ5fo6TtYLQzWRGp3JiDlAiWKH9A&oe=69BD8382&_nc_sid=8b3546, https://instagram.fagc1-2.fna.fbcdn.net/v/t51.82787-15/641281760_17918285358461408_7847502817245749732_n.jpg?stp=dst-jpg_e35_p1080x1080_sh0.08_tt6&_nc_ht=instagram.fagc1-2.fna.fbcdn.net&_nc_cat=108&_nc_oc=Q6cZ2QEiAh4T4nk0gqIF3qnvXyNEEUo2HbxO3tauZzg8kRJRXXm5YR95-MbFeuJLxeXsEgA&_nc_ohc=HqdajbSeuaIQ7kNvwG1mZ2k&_nc_gid=lo0P6mamMwu4MpvA6gaIMA&edm=AOQ1c0wBAAAA&ccb=7-5&ig_cache_key=Mzg0NTE3NzIxMDc0ODE2MjI5MA%3D%3D.3-ccb7-5&oh=00_AfwcaQHKtiY1Q96ZNt3gaJloSEP5whfnZ0KJRK9BV6y-0g&oe=69BD95BF&_nc_sid=8b3546, https://instagram.fagc1-2.fna.fbcdn.net/v/t51.82787-15/642413818_17918140278461408_6288490020204688188_n.jpg?stp=dst-jpg_e35_p1080x1080_sh0.08_tt6&_nc_ht=instagram.fagc1-2.fna.fbcdn.net&_nc_cat=108&_nc_oc=Q6cZ2QEiAh4T4nk0gqIF3qnvXyNEEUo2HbxO3tauZzg8kRJRXXm5YR95-MbFeuJLxeXsEgA&_nc_ohc=O_XOq3VJglcQ7kNvwFpwXTX&_nc_gid=lo0P6mamMwu4MpvA6gaIMA&edm=AOQ1c0wBAAAA&ccb=7-5&ig_cache_key=Mzg0NDQ1NzcwNjU4NTk5NDkwMQ%3D%3D.3-ccb7-5&oh=00_AfytKPpwVN-wtfGnhBwgLNcmmKUa_4zqDiaNegMAs6bvnQ&oe=69BD9663&_nc_sid=8b3546, https://instagram.fagc1-2.fna.fbcdn.net/v/t51.82787-15/642413818_17918140278461408_6288490020204688188_n.jpg?stp=dst-jpg_e35_p1080x1080_sh0.08_tt6&_nc_ht=instagram.fagc1-2.fna.fbcdn.net&_nc_cat=108&_nc_oc=Q6cZ2QEiAh4T4nk0gqIF3qnvXyNEEUo2HbxO3tauZzg8kRJRXXm5YR95-MbFeuJLxeXsEgA&_nc_ohc=O_XOq3VJglcQ7kNvwFpwXTX&_nc_gid=lo0P6mamMwu4MpvA6gaIMA&edm=AOQ1c0wBAAAA&ccb=7-5&ig_cache_key=Mzg0NDQ1NzcwNjU4NTk5NDkwMQ%3D%3D.3-ccb7-5&oh=00_AfytKPpwVN-wtfGnhBwgLNcmmKUa_4zqDiaNegMAs6bvnQ&oe=69BD9663&_nc_sid=8b3546, https://instagram.fagc1-2.fna.fbcdn.net/v/t51.82787-15/640404517_17918140287461408_1576327605658583057_n.jpg?stp=dst-jpg_e35_p1080x1080_sh0.08_tt6&_nc_ht=instagram.fagc1-2.fna.fbcdn.net&_nc_cat=108&_nc_oc=Q6cZ2QEiAh4T4nk0gqIF3qnvXyNEEUo2HbxO3tauZzg8kRJRXXm5YR95-MbFeuJLxeXsEgA&_nc_ohc=uJSZ-3F0ChIQ7kNvwHnTb_k&_nc_gid=lo0P6mamMwu4MpvA6gaIMA&edm=AOQ1c0wBAAAA&ccb=7-5&ig_cache_key=Mzg0NDQ1NzcwNjI5MjQwNTM5NA%3D%3D.3-ccb7-5&oh=00_AfwCmDBu84HPRRvCJEEzkTgs7u5S6JWT61OHfqBx01A5cQ&oe=69BDA84C&_nc_sid=8b3546, https://instagram.fagc1-2.fna.fbcdn.net/v/t51.82787-15/639882648_17918140299461408_5165427753481985340_n.jpg?stp=dst-jpg_e35_p1080x1080_sh0.08_tt6&_nc_ht=instagram.fagc1-2.fna.fbcdn.net&_nc_cat=108&_nc_oc=Q6cZ2QEiAh4T4nk0gqIF3qnvXyNEEUo2HbxO3tauZzg8kRJRXXm5YR95-MbFeuJLxeXsEgA&_nc_ohc=4MnXoGJJLTsQ7kNvwH0J_mr&_nc_gid=lo0P6mamMwu4MpvA6gaIMA&edm=AOQ1c0wBAAAA&ccb=7-5&ig_cache_key=Mzg0NDQ1NzcwNjI5MjQyNzg5OA%3D%3D.3-ccb7-5&oh=00_AfxRSX10c7cZRDYFtSHM40Y9ZntbvVZPYHl3Jby0SfS3HA&oe=69BD8F9E&_nc_sid=8b3546, https://instagram.fagc1-2.fna.fbcdn.net/v/t51.82787-15/642523133_17917719717461408_6853224574642221141_n.jpg?stp=dst-jpg_e35_p1080x1080_sh0.08_tt6&_nc_ht=instagram.fagc1-2.fna.fbcdn.net&_nc_cat=108&_nc_oc=Q6cZ2QEiAh4T4nk0gqIF3qnvXyNEEUo2HbxO3tauZzg8kRJRXXm5YR95-MbFeuJLxeXsEgA&_nc_ohc=I1FPATfE2xEQ7kNvwGBhutt&_nc_gid=lo0P6mamMwu4MpvA6gaIMA&edm=AOQ1c0wBAAAA&ccb=7-5&ig_cache_key=Mzg0MjMyMzQ3ODY1ODMzNTIxNQ%3D%3D.3-ccb7-5&oh=00_Afxb9ZqJSyjPq4j0bPPWvjOY8oVC5-85R8rGOashAIgWtQ&oe=69BD870B&_nc_sid=8b3546, https://instagram.fagc1-2.fna.fbcdn.net/v/t51.82787-15/642523133_17917719717461408_6853224574642221141_n.jpg?stp=dst-jpg_e35_p1080x1080_sh0.08_tt6&_nc_ht=instagram.fagc1-2.fna.fbcdn.net&_nc_cat=108&_nc_oc=Q6cZ2QEiAh4T4nk0gqIF3qnvXyNEEUo2HbxO3tauZzg8kRJRXXm5YR95-MbFeuJLxeXsEgA&_nc_ohc=I1FPATfE2xEQ7kNvwGBhutt&_nc_gid=lo0P6mamMwu4MpvA6gaIMA&edm=AOQ1c0wBAAAA&ccb=7-5&ig_cache_key=Mzg0MjMyMzQ3ODY1ODMzNTIxNQ%3D%3D.3-ccb7-5&oh=00_Afxb9ZqJSyjPq4j0bPPWvjOY8oVC5-85R8rGOashAIgWtQ&oe=69BD870B&_nc_sid=8b3546, https://instagram.fagc1-2.fna.fbcdn.net/v/t51.82787-15/639921922_17917571493461408_6010134188781232266_n.jpg?stp=dst-jpg_e35_p1080x1080_sh0.08_tt6&_nc_ht=instagram.fagc1-2.fna.fbcdn.net&_nc_cat=108&_nc_oc=Q6cZ2QEiAh4T4nk0gqIF3qnvXyNEEUo2HbxO3tauZzg8kRJRXXm5YR95-MbFeuJLxeXsEgA&_nc_ohc=_6KnXfbQafcQ7kNvwHzNJHw&_nc_gid=lo0P6mamMwu4MpvA6gaIMA&edm=AOQ1c0wBAAAA&ccb=7-5&ig_cache_key=Mzg0MTU1NzI0NzU5MjM4OTg4NQ%3D%3D.3-ccb7-5&oh=00_AfxaxFDZGuVZRv-gOZG3hCVdpuH5clyCyPF66TPcN4bgPQ&oe=69BDAE68&_nc_sid=8b3546, https://instagram.fagc1-2.fna.fbcdn.net/v/t51.82787-15/640273766_17917434756461408_2071996644453996650_n.jpg?stp=dst-jpg_e35_p1080x1080_sh0.08_tt6&_nc_ht=instagram.fagc1-2.fna.fbcdn.net&_nc_cat=108&_nc_oc=Q6cZ2QEiAh4T4nk0gqIF3qnvXyNEEUo2HbxO3tauZzg8kRJRXXm5YR95-MbFeuJLxeXsEgA&_nc_ohc=jkN50ii56RkQ7kNvwFyKt40&_nc_gid=lo0P6mamMwu4MpvA6gaIMA&edm=AOQ1c0wBAAAA&ccb=7-5&ig_cache_key=Mzg0MDgyNDA0OTE4NzAzNTk3NQ%3D%3D.3-ccb7-5&oh=00_AfzBT3SD0uN8QeUvKFjUuY-eEu1ncuZ3xz_2liNSYuSeCQ&oe=69BD82A2&_nc_si | Z11: https://instagram.fagc1-2.fna.fbcdn.net/o1/v/t16/f2/m84/AQOrI3i_Zoar6PDZjbk9HXbiQ6ZvMtvWZxCjkywauI8WyBCpyqXl4U7lxO6gbRqpLFI4kUfTB4po-Y8KatKIPNCsTB1TCNvixTmEBMg.mp4?_nc_cat=107&_nc_oc=AdkiL9lqdBgd50i_9tMOsb9Rb42mJMtSClPuur18eidOusre0-qF2xtZo4m1LY5j_bY&_nc_sid=5e9851&_nc_ht=instagram.fagc1-2.fna.fbcdn.net&_nc_ohc=VSxbyQ8NZlUQ7kNvwEDf5nq&efg=eyJ2ZW5jb2RlX3RhZyI6Inhwdl9wcm9ncmVzc2l2ZS5JTlNUQUdSQU0uQ0FST1VTRUxfSVRFTS5DMy43MjAuZGFzaF9iYXNlbGluZV8xX3YxIiwieHB2X2Fzc2V0X2lkIjoxNzkxNzcxOTcyMzQ2MTQwOCwiYXNzZXRfYWdlX2RheXMiOjE2LCJ2aV91c2VjYXNlX2lkIjoxMDE0NiwiZHVyYXRpb25fcyI6NCwidXJsZ2VuX3NvdXJjZSI6Ind3dyJ9&ccb=17-1&_nc_gid=lo0P6mamMwu4MpvA6gaIMA&_nc_ss=1a&_nc_zt=28&vs=f456e6aef477f321&_nc_vs=HBkcFQIYTGlnX2JhY2tmaWxsX3RpbWVsaW5lX3ZvZC81MzQ5QjkwQUU2OUJCOEY3NjlCRTM1M0Y1REQ0RkI5NF92aWRlb19kYXNoaW5pdC5tcDQVAALIARIAKAAYABsCiAd1c2Vfb2lsATEScHJvZ3Jlc3NpdmVfcmVjaXBlATEVAAAmwKzq9MaE1D8VAigCQzMsF0ASqfvnbItEGBJkYXNoX2Jhc2VsaW5lXzFfdjERAHXuB2XEngEA&oh=00_Afzd59oBAXZ4QVAN1odpCXrycVpoz_pHWMmw4e1cxBCF7g&oe=69B9A619 | AA11: 12 | AB11: 2 | AC11: 46097 | AD11: loupethis | AE11: collector_page | AF11: https://www.instagram.com/thefinancialwrist
A12: professorkrl | B12: instagram | C12: Karim Lakhani | D12: Read, write, teach @harvardhbs @digitaldatadesignharvard - oh and have fun! | E12: 816 | F12: 1468 | G12: 54 | H12: TRUE | I12: FALSE | K12: http://www.hbs.edu/klakhani | L12: https://scontent-ord5-1.cdninstagram.com/v/t51.2885-19/418762204_284231517636056_4847107266742965460_n.jpg?stp=dst-jpg_e0_s150x150_tt6&efg=eyJ2ZW5jb2RlX3RhZyI6InByb2ZpbGVfcGljLmRqYW5nby4xMDgwLmMyIn0&_nc_ht=scontent-ord5-1.cdninstagram.com&_nc_cat=108&_nc_oc=Q6cZ2QHDuIupvV2dS__F9f1SotmLeLxkbjD-8YCFKpY3T_HLHr9KtcdwtwPD8RBJGk33ozo&_nc_ohc=Tfu69miok9kQ7kNvwHAf11C&_nc_gid=Ue9rTNHJi0NSTEIBm6_kQQ&edm=AOQ1c0wBAAAA&ccb=7-5&oh=00_AfxLm3ummaOk0DZyZi9JvIsSmc2JJX1RIOJbwM0oZg8a1w&oe=69BD839C&_nc_sid=8b3546 | O12: 0.0431 | P12: At the @microsoft #ignite summit announcing a collaboration with @digitaldatadesignharvard on Frontier Firms Research and Learning. | Going up and going down. | @robertglasper is not just the best jazz pianist or the best pianist but he is the best musician! Birthday weekend celebration at the @bluenotenyc for Robtober Season 7. With @shaheen.studios & @sitarahlakhani | Living my heavy metal high school dreams. Cambridge MA was rocking @mideastclub with the amazing @mistress.doom @demonchrome and of course the incredible @castle.rat - such great resonance with Iron Maiden Judas Priest Rush Ratt | It feels like summer with the @chriswardlondon Loco. Yeah it’s waterproof for sure. Somewhere in the Atlantic Ocean. | It’s a microbrand kind of a trip. These time pieces hit just right for @shaheen.studios and me. Thank you @alterumwatchcompany @revolution.watch & @paparwatches for your beautiful work. | Summer sailing in Salerno Harbor with the @mingwatches Bluefin - cool design great vibes amazing weather. | A perfectly useless Sunday afternoon with my favorite weekend watch - what an inspiration to just chill thank you @mrjoneswatches #umbria | Gentle Brutalism on my wrist with the new @paparwatches Anillo. Wears incredibly well. Amazing to see Massachusetts based watch company having a revival. | Celebrating Father’s Day with @sitarahlakhani, @shaheen.studios digging up old memories - creating new ones. Love my girls! | My @mbandf lucky charm for the @celtics win!!! | Q12: #ignite, #umbria | R12: @microsoft, @digitaldatadesignharvard, @robertglasper, @bluenotenyc, @shaheen.studios, @sitarahlakhani, @mideastclub, @mistress.doom, @demonchrome, @castle.rat, @chriswardlondon, @alterumwatchcompany, @revolution.watch, @paparwatches, @mingwatches, @mrjoneswatches, @mbandf, @celtics | S12: https://instagram.com/p/DRP_3mXku1t, https://instagram.com/p/DRFfE2VEdqT, https://instagram.com/p/DP_xmSrAESV, https://instagram.com/p/DPZEoc2gJWQ, https://instagram.com/p/DOQ_h8EgEFM, https://instagram.com/p/DNML3LfvQEE, https://instagram.com/p/DL2EygPN-Y_, https://instagram.com/p/DLpWoLLtAXk, https://instagram.com/p/DLhkEQqND5w, https://instagram.com/p/DLOGOvjPjSv, https://instagram.com/p/DK8KCBcP2-H, https://instagram.com/p/DJqFbfQxHGf | T12: 17, 23, 27, 14, 43, 12, 28, 24, 32, 25, 106, 36 | U12: 0, 1, 3, 3, 2, 0, 11, 2, 2, 5, 2, 4 | V12: 2025-11-19, 2025-11-15, 2025-10-19, 2025-10-04, 2025-09-06, 2025-08-10, 2025-07-08, 2025-07-03, 2025-06-30, 2025-06-22, 2025-06-15, 2025-05-15 | W12: Dubai, Montmartre, Boston, Massachusetts | X12: Video, Sidecar, Sidecar, Image, Sidecar, Sidecar, Sidecar, Sidecar, Sidecar, Sidecar, Sidecar, Sidecar | Y12: https://scontent-ord5-3.cdninstagram.com/v/t51.82787-15/581833901_18529792618025337_2140026576180308656_n.jpg?stp=dst-jpg_e15_tt6&_nc_ht=scontent-ord5-3.cdninstagram.com&_nc_cat=109&_nc_oc=Q6cZ2QHDuIupvV2dS__F9f1SotmLeLxkbjD-8YCFKpY3T_HLHr9KtcdwtwPD8RBJGk33ozo&_nc_ohc=shoB-8hFVqUQ7kNvwE-2hvS&_nc_gid=Ue9rTNHJi0NSTEIBm6_kQQ&edm=AOQ1c0wBAAAA&ccb=7-5&oh=00_AfxJJ0adL9ThZsmATLixYVoI1zEMU1WPXr_nIi9qr5i0XQ&oe=69BDB529&_nc_sid=8b3546, https://scontent-ord5-3.cdninstagram.com/v/t51.82787-15/567144947_18524580169025337_8676603285278861969_n.jpg?stp=dst-jpg_e15_tt6&_nc_ht=scontent-ord5-3.cdninstagram.com&_nc_cat=109&_nc_oc=Q6cZ2QHDuIupvV2dS__F9f1SotmLeLxkbjD-8YCFKpY3T_HLHr9KtcdwtwPD8RBJGk33ozo&_nc_ohc=1laZb_WOgSYQ7kNvwFUKQIu&_nc_gid=Ue9rTNHJi0NSTEIBm6_kQQ&edm=AOQ1c0wBAAAA&ccb=7-5&oh=00_AfwLNENKA8-3XwyQIL1eHwauW-IL-w7nhhbPqIlZxgiRVQ&oe=69BD8FA3&_nc_sid=8b3546, https://scontent-ord5-3.cdninstagram.com/v/t51.82787-15/567403487_18524580082025337_6786937869271346086_n.jpg?stp=dst-jpg_e35_p1080x1080_sh0.08_tt6&_nc_ht=scontent-ord5-3.cdninstagram.com&_nc_cat=109&_nc_oc=Q6cZ2QHDuIupvV2dS__F9f1SotmLeLxkbjD-8YCFKpY3T_HLHr9KtcdwtwPD8RBJGk33ozo&_nc_ohc=p9IfYuhSvbIQ7kNvwFMdtBJ&_nc_gid=Ue9rTNHJi0NSTEIBm6_kQQ&edm=AOQ1c0wBAAAA&ccb=7-5&ig_cache_key=Mzc0NjkzMTU0NTUwNDU0MTM4OQ%3D%3D.3-ccb7-5&oh=00_AfxsdbBB05HPQAw9TXgTl3gwJUoMelqKEUnP3XYG9NDqsg&oe=69BD8835&_nc_sid=8b3546, https://scontent-ord5-3.cdninstagram.com/v/t51.82787-15/559125315_18521545462025337_1026646953254150269_n.jpg?stp=dst-jpg_e35_p1080x1080_sh0.08_tt6&_nc_ht=scontent-ord5-3.cdninstagram.com&_nc_cat=109&_nc_oc=Q6cZ2QHDuIupvV2dS__F9f1SotmLeLxkbjD-8YCFKpY3T_HLHr9KtcdwtwPD8RBJGk33ozo&_nc_ohc=qmXg2l3F5VAQ7kNvwExbLB4&_nc_gid=Ue9rTNHJi0NSTEIBm6_kQQ&edm=AOQ1c0wBAAAA&ccb=7-5&ig_cache_key=MzczNjAzNzczNzgyNDgxODU3Ng%3D%3D.3-ccb7-5&oh=00_AfxT7P_gAi3lSXTbY4a7LVso3spEvviaVYA795X03vdFQA&oe=69BD840C&_nc_sid=8b3546, https://scontent-ord5-3.cdninstagram.com/v/t51.82787-15/543591141_18516424171025337_8842504482409020368_n.jpg?stp=dst-jpg_e35_p1080x1080_sh0.08_tt6&_nc_ht=scontent-ord5-3.cdninstagram.com&_nc_cat=109&_nc_oc=Q6cZ2QHDuIupvV2dS__F9f1SotmLeLxkbjD-8YCFKpY3T_HLHr9KtcdwtwPD8RBJGk33ozo&_nc_ohc=4yVImKqs8t0Q7kNvwEIJngi&_nc_gid=Ue9rTNHJi0NSTEIBm6_kQQ&edm=AOQ1c0wBAAAA&ccb=7-5&ig_cache_key=MzcxNTc0OTA5MDA0MzE2NjI1NQ%3D%3D.3-ccb7-5&oh=00_AfyO-8h8wxwm0U2lEUNA4ePXjajbJ2J6nFNth3t4cPu5VA&oe=69BD93CB&_nc_sid=8b3546, https://scontent-ord5-3.cdninstagram.com/v/t51.82787-15/543591141_18516424171025337_8842504482409020368_n.jpg?stp=dst-jpg_e35_p1080x1080_sh0.08_tt6&_nc_ht=scontent-ord5-3.cdninstagram.com&_nc_cat=109&_nc_oc=Q6cZ2QHDuIupvV2dS__F9f1SotmLeLxkbjD-8YCFKpY3T_HLHr9KtcdwtwPD8RBJGk33ozo&_nc_ohc=4yVImKqs8t0Q7kNvwEIJngi&_nc_gid=Ue9rTNHJi0NSTEIBm6_kQQ&edm=AOQ1c0wBAAAA&ccb=7-5&ig_cache_key=MzcxNTc0OTA5MDA0MzE2NjI1NQ%3D%3D.3-ccb7-5&oh=00_AfyO-8h8wxwm0U2lEUNA4ePXjajbJ2J6nFNth3t4cPu5VA&oe=69BD93CB&_nc_sid=8b3546, https://scontent-ord5-3.cdninstagram.com/v/t51.82787-15/539510128_18516424183025337_9177624095005719173_n.jpg?stp=dst-jpg_e35_p1080x1080_sh0.08_tt6&_nc_ht=scontent-ord5-3.cdninstagram.com&_nc_cat=109&_nc_oc=Q6cZ2QHDuIupvV2dS__F9f1SotmLeLxkbjD-8YCFKpY3T_HLHr9KtcdwtwPD8RBJGk33ozo&_nc_ohc=isDK2-4x9voQ7kNvwHJAW-b&_nc_gid=Ue9rTNHJi0NSTEIBm6_kQQ&edm=AOQ1c0wBAAAA&ccb=7-5&ig_cache_key=MzcxNTc0OTA4OTc5OTg3NzU4OQ%3D%3D.3-ccb7-5&oh=00_AfzQDPe-foldoS7nq27pZa84Asj3zkFucWiCKrIb1OVGrQ&oe=69BD8D4F&_nc_sid=8b3546, https://scontent-ord5-3.cdninstagram.com/v/t51.82787-15/540767540_18516424195025337_5779151184834490583_n.jpg?stp=dst-jpg_e35_p1080x1080_sh0.08_tt6&_nc_ht=scontent-ord5-3.cdninstagram.com&_nc_cat=109&_nc_oc=Q6cZ2QHDuIupvV2dS__F9f1SotmLeLxkbjD-8YCFKpY3T_HLHr9KtcdwtwPD8RBJGk33ozo&_nc_ohc=j3NMkICJPrMQ7kNvwH5EcTS&_nc_gid=Ue9rTNHJi0NSTEIBm6_kQQ&edm=AOQ1c0wBAAAA&ccb=7-5&ig_cache_key=MzcxNTc0OTA4OTc4MzA1NTM1Nw%3D%3D.3-ccb7-5&oh=00_AfwJCgP4YTrCb9KdxbTbdNgYFYYk1eUX9DVOsbMXif57JA&oe=69BDB234&_nc_sid=8b3546, https://scontent-ord5-3.cdninstagram.com/v/t51.82787-15/540628492_18516424204025337_5033546632664999806_n.jpg?stp=dst-jpg_e35_p1080x1080_sh0.08_tt6&_nc_ht=scontent-ord5-3.cdninstagram.com&_nc_cat=109&_nc_oc=Q6cZ2QHDuIupvV2dS__F9f1SotmLeLxkbjD-8YCFKpY3T_HLHr9KtcdwtwPD8RBJGk33ozo&_nc_ohc=E9uz3BULw20Q7kNvwHS12y4&_nc_gid=Ue9rTNHJi0NSTEIBm6_kQQ&edm=AOQ1c0wBAAAA&ccb=7-5&ig_cache_key=MzcxNTc0OTA4OTc5OTg3NDYxOQ%3D%3D.3-ccb7-5&oh=00_Afzp1hMPbi9-c4vrUyjipXqtmzblNq1QzEJNjGtvLEW40w&oe=69BD9DDD&_nc_sid=8b3546, https://scontent-ord5-3.cdninstagram.com/v/t51.82787-15/542993275_18516424213025337_3738553143169379758_n.jpg?stp=dst-jpg_e35_p1080x1080_sh0.08_tt6&_nc_ht=scontent-ord5-3.cdninstagram.com&_nc_cat=109&_nc_oc=Q6cZ2QHDuIupvV2dS__F9f1SotmLeLxkbjD-8YCFKpY3T_HLHr9KtcdwtwPD8RBJGk33ozo&_nc_ohc=uw5qccinjpQQ7kNvwG9_U1L&_nc_gid=Ue9rTNHJi0NSTEIBm6_kQQ&edm=AOQ1c0wBAAAA&ccb=7-5&ig_cache_key=MzcxNTc0OTA4OTc5OTg0MjkwNw%3D%3D.3-ccb7-5&oh=00_AfzkMnlK3Z-ED1p8qI6Y0d-RdGDTUhdtkNCaybXRIG7xHA&oe=69BD8E51&_nc_sid=8b3546, https://scontent-ord5-3.cdninstagram.com/v/t51.82787-15/529814593_18511427962025337_1892314455693071563_n.jpg?stp=ds | Z12: https://scontent-ord5-2.cdninstagram.com/o1/v/t2/f2/m86/AQNCG8kyQlGIzee9ffg08XXBDFhx7-BD1FxvC5flLwyi2F2MfhaEuQjaXLN4Kc1ocT44OvcZYXJESKp8vDW8P9CYNCWx7XqBczX6zDU.mp4?_nc_cat=105&_nc_sid=5e9851&_nc_ht=scontent-ord5-2.cdninstagram.com&_nc_ohc=xmMXl-hmEx4Q7kNvwGLZyRI&efg=eyJ2ZW5jb2RlX3RhZyI6Inhwdl9wcm9ncmVzc2l2ZS5JTlNUQUdSQU0uQ0xJUFMuQzMuNzIwLmRhc2hfYmFzZWxpbmVfMV92MSIsInhwdl9hc3NldF9pZCI6ODQzOTQ3Mjc1MDUzMDI2LCJhc3NldF9hZ2VfZGF5cyI6MTE2LCJ2aV91c2VjYXNlX2lkIjoxMDA5OSwiZHVyYXRpb25fcyI6MTYsIndhdGNoX3RpbWVfcyI6ODIsInVybGdlbl9zb3VyY2UiOiJ3d3cifQ%3D%3D&ccb=17-1&vs=d59167a7fd5193ff&_nc_vs=HBksFQIYUmlnX3hwdl9yZWVsc19wZXJtYW5lbnRfc3JfcHJvZC9BRTQzQjM2Q0NCNDg0MUYzQzRGMDVENjI2NEFCNjg5OF92aWRlb19kYXNoaW5pdC5tcDQVAALIARIAFQIYR2lnX3hwdl9yZWVsc19wZXJtYW5lbnRfc3JfcHJvZC8xNTQwNjkzOTAwNTc3MTk1XzM5NzgzMTI5OTYzMDEzOTk0NjgubXA0FQICyAESACgAGAAbAogHdXNlX29pbAExEnByb2dyZXNzaXZlX3JlY2lwZQExFQAAJsSfz5iZ5P8CFQIoAkMzLBdAMAAAAAAAABgSZGFzaF9iYXNlbGluZV8xX3YxEQB1_gdl5p0BAA&_nc_gid=Ue9rTNHJi0NSTEIBm6_kQQ&_nc_ss=1a&_nc_zt=28&oh=00_AfySFPyHWFBmYdl5P091bDm34A4yqY1Ad2UwA5Q7KvGerg&oe=69B9927E, https://scontent-ord5-1.cdninstagram.com/o1/v/t16/f2/m84/AQOuE4FkzVDZqKgXl28gZ8EZqGUu8nsbd-Nv0PsijDkwkwfJmgnr3vSpPgRibCIcy8pc3bn83p1KEPs_9Y_kiPCukNOIO07Zxarzn40.mp4?_nc_cat=101&_nc_sid=5e9851&_nc_ht=scontent-ord5-1.cdninstagram.com&_nc_ohc=9Yhi9xDnsRkQ7kNvwH3MciK&efg=eyJ2ZW5jb2RlX3RhZyI6Inhwdl9wcm9ncmVzc2l2ZS5JTlNUQUdSQU0uQ0FST1VTRUxfSVRFTS5DMy4zNjAuZGFzaF9iYXNlbGluZV8zX3YxIiwieHB2X2Fzc2V0X2lkIjoxMzQ1MDc4ODk5OTQ3MDQ4LCJhc3NldF9hZ2VfZGF5cyI6MTIwLCJ2aV91c2VjYXNlX2lkIjoxMDE0NiwiZHVyYXRpb25fcyI6MzQsInVybGdlbl9zb3VyY2UiOiJ3d3cifQ%3D%3D&ccb=17-1&_nc_gid=Ue9rTNHJi0NSTEIBm6_kQQ&_nc_ss=1a&_nc_zt=28&vs=4cada4cb3fa82925&_nc_vs=HBkcFQIYTGlnX2JhY2tmaWxsX3RpbWVsaW5lX3ZvZC9EMzRENzg5MTVDNUEwOTE5NzYwM0NEN0Q4QjJFOURBQV92aWRlb19kYXNoaW5pdC5tcDQVAALIARIAKAAYABsCiAd1c2Vfb2lsATEScHJvZ3Jlc3NpdmVfcmVjaXBlATEVAAAm0Ni14PLV4wQVAigCQzMsF0BBJcKPXCj2GBJkYXNoX2Jhc2VsaW5lXzNfdjERAHXuB2XEngEA&oh=00_Afz-XmV_dqzyB4snIkmVWf0N2h7hT2ycLFy9Aipoalqinw&oe=69B9B82B, https://scontent-ord5-3.cdninstagram.com/o1/v/t16/f2/m84/AQM5BVT3UnIP_gw5tJMajWFANFFglE3PGrKSswPUOAKa3xQoBPolhxZDWSYV8FS4T_wMBugpixv1T9yMN8FD2x39AMr2XWQgMkeX2Wo.mp4?_nc_cat=100&_nc_sid=5e9851&_nc_ht=scontent-ord5-3.cdninstagram.com&_nc_ohc=rhKQsmslDioQ7kNvwHYxGcJ&efg=eyJ2ZW5jb2RlX3RhZyI6Inhwdl9wcm9ncmVzc2l2ZS5JTlNUQUdSQU0uQ0FST1VTRUxfSVRFTS5DMy4zNjAuZGFzaF9iYXNlbGluZV8zX3YxIiwieHB2X2Fzc2V0X2lkIjoxMzM0MDE4MzgxNzg1NTYyLCJhc3NldF9hZ2VfZGF5cyI6MTIwLCJ2aV91c2VjYXNlX2lkIjoxMDE0NiwiZHVyYXRpb25fcyI6MzMsInVybGdlbl9zb3VyY2UiOiJ3d3cifQ%3D%3D&ccb=17-1&_nc_gid=Ue9rTNHJi0NSTEIBm6_kQQ&_nc_ss=1a&_nc_zt=28&vs=b534738032509dd8&_nc_vs=HBkcFQIYTGlnX2JhY2tmaWxsX3RpbWVsaW5lX3ZvZC8zQjQyMTdDMzA4Mzc4QkYwQUQxQzM3MzdBRDRBRjRBM192aWRlb19kYXNoaW5pdC5tcDQVAALIARIAKAAYABsCiAd1c2Vfb2lsATEScHJvZ3Jlc3NpdmVfcmVjaXBlATEVAAAmtKepvIvS3gQVAigCQzMsF0BAsCDEm6XjGBJkYXNoX2Jhc2VsaW5lXzNfdjERAHXuB2XEngEA&oh=00_AfyZL_FOkTb_MT0RWf_ZpsGj1Y-xRh-ytUJfSklbzw3sGg&oe=69B9B25C, https://scontent-ord5-1.cdninstagram.com/o1/v/t16/f2/m84/AQNLEGm-T2cBDRK_TSKa2QPY72yD6c9mS4X2pl73gnsNQiSW0AH6AYSt-_lbZp0Y8FiI6hMZyKP9fmE0NXM1_5r5bBZT0YltzCgc18Y.mp4?_nc_cat=108&_nc_sid=5e9851&_nc_ht=scontent-ord5-1.cdninstagram.com&_nc_ohc=MOPY79cPwrAQ7kNvwFNuQdb&efg=eyJ2ZW5jb2RlX3RhZyI6Inhwdl9wcm9ncmVzc2l2ZS5JTlNUQUdSQU0uQ0FST1VTRUxfSVRFTS5DMy4zNjAuZGFzaF9iYXNlbGluZV8zX3YxIiwieHB2X2Fzc2V0X2lkIjo4MjYzMDQ5OTk4MDU5NzgsImFzc2V0X2FnZV9kYXlzIjoxMjAsInZpX3VzZWNhc2VfaWQiOjEwMTQ2LCJkdXJhdGlvbl9zIjozMywidXJsZ2VuX3NvdXJjZSI6Ind3dyJ9&ccb=17-1&_nc_gid=Ue9rTNHJi0NSTEIBm6_kQQ&_nc_ss=1a&_nc_zt=28&vs=fab9c85098e5b88f&_nc_vs=HBkcFQIYTGlnX2JhY2tmaWxsX3RpbWVsaW5lX3ZvZC81RjRFODlERjM1MjE2RTgxNDNDMDI3MzNDNURBQTk4QV92aWRlb19kYXNoaW5pdC5tcDQVAALIARIAKAAYABsCiAd1c2Vfb2lsATEScHJvZ3Jlc3NpdmVfcmVjaXBlATEVAAAmtNDq_6Ph9wIVAigCQzMsF0BAi-dsi0OWGBJkYXNoX2Jhc2VsaW5lXzNfdjERAHXuB2XEngEA&oh=00_Afy0Yqq28pEMniCUNrmbYsQP8-cMXTUQTko42ptfrCrkqg&oe=69B9C380, https://scontent-ord5-2.cdninstagram.com/o1/v/t16/f2/m84/AQMR_JxyTNHciYJJ7ScL2T3uRrxds-jiPh_7nGfR8AqM6eE0VIlfiM4kaiGgrTCuKFb2OCEedboYr22-uTtbjh2byxQPNLznvVSwJWM.mp4?_nc_cat=103&_nc_sid=5e9851&_nc_ht=scontent-ord5-2.cdninstagram.com&_nc_ohc=9jD7atskedMQ7kNvwGvnuQa&efg=eyJ2ZW5jb2RlX3RhZyI6Inhwdl9wcm9ncmVzc2l2ZS5JTlNUQUdSQU0uQ0FST1VTRUxfSVRFTS5DMy4zNjAuZGFzaF9iYXNlbGluZV8zX3YxIiwieHB2X2Fzc2V0X2lkIjoxMzU2NjQ1NDkyNjM0MDk1LCJhc3NldF9hZ2VfZGF5cyI6MTIwLCJ2aV91c2VjYXNlX2lkIjoxMDE0NiwiZHVyYXRpb25fcyI6MzMsIndhdGNoX3RpbWVfcyI6OSwidXJsZ2VuX3NvdXJjZSI6Ind3dyJ9&ccb=17-1&vs=73c5091ae28564d9&_nc_vs=HBkcFQIYTGlnX2JhY2tmaWxsX3RpbWVsaW5lX3ZvZC83NDQ0OUIzQ0M3NDhDNDMxOEMwMUU2QjBDRjE1OUE4Rl92aWRlb19kYXNoaW5pdC5tcDQVAALIARIAKAAYABsCiAd1c2Vfb2lsATEScHJvZ3Jlc3NpdmVfcmVjaXBlATEVAAAm3sflypT36AQVAigCQzMsF0BA3dLxqfvnGBJkYXNoX2Jhc2VsaW5lXzNfdjERAHXuB2XEngEA&_nc_gid=Ue9rTNHJi0NSTEIBm6_kQQ&_nc_ss=1a&_nc_zt=28&oh=00_AfzUSUVsJOv3kTvOYfst3v48Z3AdF1ASQaxYXQyms31Pxg&oe=69B99E75 | AA12: 32 | AB12: 3 | AC12: 46097 | AD12: loupethis | AE12: collector_page | AF12: https://www.instagram.com/professorkrl
A13: vintagetimes_1 | B13: instagram | C13: Vintagetimes | D13: Watch Enthusiast/Collector- Sale & Buy Vintage & Contemporary Pre-Owned 🌎Worldwide Shipping Contact us:👇🏻 📲Whatsup +9613357474 | E13: 520 | F13: 1186 | G13: 105 | H13: FALSE | I13: TRUE | J13: None,Shopping & retail | L13: https://scontent-ord5-3.cdninstagram.com/v/t51.2885-19/273759368_146391131173003_8228321373779400220_n.jpg?stp=dst-jpg_e0_s150x150_tt6&efg=eyJ2ZW5jb2RlX3RhZyI6InByb2ZpbGVfcGljLmRqYW5nby42NDMuYzIifQ&_nc_ht=scontent-ord5-3.cdninstagram.com&_nc_cat=107&_nc_oc=Q6cZ2QFD9NVXmMzDIdsv6i_AI4tYuNjNCZPkVrXCeueAsWZg6wi38UCVNd6i-bWG6psiD5o&_nc_ohc=FLP5WwuyyU8Q7kNvwGmqL0I&_nc_gid=Kka_B9zrlbZqnVQWiktOpg&edm=AOQ1c0wBAAAA&ccb=7-5&oh=00_AfyrTsfqIpjAHcNceTT84yngZxoiJhaK2fPILfjgVkLnSQ&oe=69BDB63A&_nc_sid=8b3546 | N13: 9613357474 | O13: 0.0183 | P13: -NFS- RARE Vintage TLC FP21 “PARIS DIAL” 80’s original box & papers‼️ #cartier #cartiercollectorsclub #cartierparis | -NFS-Cartier Tank Americaine Vintage ref 2483 Yellow gold, Automatic in Medium size. Probably the best proportioned size in the Tank Americaine collection and the closest to the Cintree! Not an easy catch nowadays! #tankamericaine #cartier #cartiertank #cartierwatch#cartiervintage | ‼️SOLD‼️ New addition! GMT Pepsi 16700 from 1997 like new! Box and papers! Beautiful faded bezel and eggshell patinated hands Particularity? Well its the last GMT Master prior to the release of the GMT II and it has it all! Open holes, tritium, quick date, and more! And so called “Neo-Vintage” with | Submariner 5513 MK1 in pristine condition like NOS!🔥🔥 crispy, sharp edges🔪 and unpolished!#rolexvintage #rolexvintagewatch #rolex #rolexvintage #rolexsubmariner #rolexnodate #rolex5513 #rolexmattedial #submariner | ‼️SOLD‼️ Submariner 16610 Pre Ceramic with engraved rehaut, full set!🔥A nice and classic time piece to start a collection#rolexsubmariner #rolexclassic #submariner #rolextimepieces#rolexvintage #rolexmania #daytona#rolexpassion | SUBMARINER 16610 with engraved rehaut. A nice example of the pre ceramic release! A start for a Neo Vintage collection! Box and papers🔥#rolexsubmariner #rolexwatch #neovintage #divingwatch #rolex | Rolex GMT “Vintage” 16758 fill gold from the 80’s! Original box and papers🔥🔥#rolexwatch #vintagewatches #rolexvintagewatch #rolexgmt #rolexwatch | Gorgeous GMT 16710 from early 2000’s with original box and papers 👆🏻UNPOLISHED!🔥🔥#rolexgmt #gmtmaster #rolexmasters #rolexwatch #rolexpepsi #gmtpepsi #rolexcokegmt#rolexwatch #16710 | Sunday Ride #rolexsubmariner #rolex5513 #rolexvintage #vintagewatches #rolexwatches | ‼️SOLD‼️ ⚠️JUST IN Like new never worn!🔥 In my opinion the best understated watch! Unparalleled elegance and versatility with a low profile presence on the wrist. A must have in every watch collection which is becoming a rare bird to find in such condition! Box and papers of course👆🏻#patekphilipp | SUB 2003/14060M NOS!🔥💥 NOS=UNWORN | Q13: #cartier, #cartiercollectorsclub, #cartierparis, #tankamericaine, #cartiertank, #cartierwatch, #cartiervintage, #rolexvintage, #rolexvintagewatch, #rolex, #rolexsubmariner, #rolexnodate, #rolex5513, #rolexmattedial, #submariner, #rolexclassic, #rolextimepieces, #rolexmania, #daytona, #rolexpassion, #rolexwatch, #neovintage, #divingwatch, #vintagewatches, #rolexgmt, #gmtmaster, #rolexmasters, #rolexpepsi, #gmtpepsi, #rolexcokegmt, #16710, #rolexwatches, #patekphilipp | S13: https://instagram.com/p/DQ1TSpOiG-_, https://instagram.com/p/DHQUqCRowLE, https://instagram.com/p/DD4jE_cIh38, https://instagram.com/p/CzEPRUZNVEj, https://instagram.com/p/Cwb_MdQt1Os, https://instagram.com/p/CwZ7RIMLfbG, https://instagram.com/p/CwKDXC2tkk4, https://instagram.com/p/CwJ_55BtlHY, https://instagram.com/p/CwHYU76NTau, https://instagram.com/p/CuxVCyhrBhb, https://instagram.com/p/CtT0c8sr3oT, https://instagram.com/p/Co7KWUDLruO | T13: 3, 5, 5, 19, 22, 7, 3, 3, 4, 15, 12, 12 | U13: 0, 0, 0, 0, 1, 0, 0, 1, 0, 0, 0, 2 | V13: 2025-11-09, 2025-03-16, 2024-12-22, 2023-10-31, 2023-08-27, 2023-08-26, 2023-08-20, 2023-08-20, 2023-08-19, 2023-07-16, 2023-06-10, 2023-02-21 | X13: Image, Image, Image, Image, Sidecar, Image, Image, Sidecar, Image, Image, Image, Sidecar | Y13: https://scontent-ord5-3.cdninstagram.com/v/t51.82787-15/574775314_18301923652265200_7630742066594940500_n.jpg?stp=dst-jpg_e35_s1080x1080_sh0.08_tt6&_nc_ht=scontent-ord5-3.cdninstagram.com&_nc_cat=104&_nc_oc=Q6cZ2QFD9NVXmMzDIdsv6i_AI4tYuNjNCZPkVrXCeueAsWZg6wi38UCVNd6i-bWG6psiD5o&_nc_ohc=v4PGv-ZIv2gQ7kNvwFX-0MB&_nc_gid=Kka_B9zrlbZqnVQWiktOpg&edm=AOQ1c0wBAAAA&ccb=7-5&ig_cache_key=Mzc2MTk5NzkwNzgzOTQ0Njk3NQ%3D%3D.3-ccb7-5&oh=00_AfwXaPpIb7peERFgLEnebk0al3WFVYHRxWtfYgAULXgilA&oe=69BD94A5&_nc_sid=8b3546, https://scontent-ord5-3.cdninstagram.com/v/t51.2885-15/484494641_18272753344265200_755530372377706518_n.jpg?stp=dst-jpg_e35_s1080x1080_sh0.08_tt6&_nc_ht=scontent-ord5-3.cdninstagram.com&_nc_cat=104&_nc_oc=Q6cZ2QFD9NVXmMzDIdsv6i_AI4tYuNjNCZPkVrXCeueAsWZg6wi38UCVNd6i-bWG6psiD5o&_nc_ohc=sb6gHgpERwsQ7kNvwEQz7N1&_nc_gid=Kka_B9zrlbZqnVQWiktOpg&edm=AOQ1c0wBAAAA&ccb=7-5&ig_cache_key=MzU4OTQ1OTc1MjYwNTkwOTcwMA%3D%3D.3-ccb7-5&oh=00_AfyNNvWEWYfgYnFgVCacZlXGrowRbyM_HutSxgRTdILiEA&oe=69BD9CE7&_nc_sid=8b3546, https://scontent-ord5-3.cdninstagram.com/v/t51.82787-15/625277350_18082546148350173_8151647017596106998_n.jpg?stp=dst-jpg_e35_p1080x1080_sh0.08_tt6&_nc_ht=scontent-ord5-3.cdninstagram.com&_nc_cat=109&_nc_oc=Q6cZ2QFD9NVXmMzDIdsv6i_AI4tYuNjNCZPkVrXCeueAsWZg6wi38UCVNd6i-bWG6psiD5o&_nc_ohc=adffEZ8QYUcQ7kNvwEYMI0x&_nc_gid=Kka_B9zrlbZqnVQWiktOpg&edm=AOQ1c0wBAAAA&ccb=7-5&ig_cache_key=MzUyODcyNDU4MjY2ODMxMjA2MA%3D%3D.3-ccb7-5&oh=00_AfzVVaU-LbB2DCdq5Jv2RFxw2gmbDRfaHJ5Z9Pal4C4YBQ&oe=69BDB3BF&_nc_sid=8b3546, https://scontent-ord5-1.cdninstagram.com/v/t51.82787-15/622999081_17998676579906629_4518857214440130043_n.jpg?stp=dst-jpg_e35_p1080x1080_sh0.08_tt6&_nc_ht=scontent-ord5-1.cdninstagram.com&_nc_cat=101&_nc_oc=Q6cZ2QFD9NVXmMzDIdsv6i_AI4tYuNjNCZPkVrXCeueAsWZg6wi38UCVNd6i-bWG6psiD5o&_nc_ohc=1Vwf9yPvLIEQ7kNvwEnDoZP&_nc_gid=Kka_B9zrlbZqnVQWiktOpg&edm=AOQ1c0wBAAAA&ccb=7-5&ig_cache_key=MzIyNTc3MDM5MzkzMDY0OTg5MQ%3D%3D.3-ccb7-5&oh=00_Afy1TbUVkTjxuR-2o45NsM78aEca_GyMiuoqdSbRo7-pEg&oe=69BDB648&_nc_sid=8b3546, https://scontent-ord5-1.cdninstagram.com/v/t51.29350-15/370395893_710235037599745_3325782670592164069_n.jpg?stp=dst-jpg_e35_p1080x1080_tt6&_nc_ht=scontent-ord5-1.cdninstagram.com&_nc_cat=101&_nc_oc=Q6cZ2QFD9NVXmMzDIdsv6i_AI4tYuNjNCZPkVrXCeueAsWZg6wi38UCVNd6i-bWG6psiD5o&_nc_ohc=P2_25oWrYvgQ7kNvwF6VAQc&_nc_gid=Kka_B9zrlbZqnVQWiktOpg&edm=AOQ1c0wBAAAA&ccb=7-5&ig_cache_key=MzE3ODQxMTg5MDY0NDA4Mzk5OQ%3D%3D.3-ccb7-5&oh=00_AfyGVETP1uETftyzbCl-NZrBgvbGLNcEFDYar7ncsg4qvA&oe=69BDAC7E&_nc_sid=8b3546, https://scontent-ord5-1.cdninstagram.com/v/t51.29350-15/370395893_710235037599745_3325782670592164069_n.jpg?stp=dst-jpg_e35_p1080x1080_tt6&_nc_ht=scontent-ord5-1.cdninstagram.com&_nc_cat=101&_nc_oc=Q6cZ2QFD9NVXmMzDIdsv6i_AI4tYuNjNCZPkVrXCeueAsWZg6wi38UCVNd6i-bWG6psiD5o&_nc_ohc=P2_25oWrYvgQ7kNvwF6VAQc&_nc_gid=Kka_B9zrlbZqnVQWiktOpg&edm=AOQ1c0wBAAAA&ccb=7-5&ig_cache_key=MzE3ODQxMTg5MDY0NDA4Mzk5OQ%3D%3D.3-ccb7-5&oh=00_AfyGVETP1uETftyzbCl-NZrBgvbGLNcEFDYar7ncsg4qvA&oe=69BDAC7E&_nc_sid=8b3546, https://scontent-ord5-1.cdninstagram.com/v/t51.29350-15/370521985_682009620074408_4137496300731248195_n.jpg?stp=dst-jpg_e35_p1080x1080_tt6&_nc_ht=scontent-ord5-1.cdninstagram.com&_nc_cat=108&_nc_oc=Q6cZ2QFD9NVXmMzDIdsv6i_AI4tYuNjNCZPkVrXCeueAsWZg6wi38UCVNd6i-bWG6psiD5o&_nc_ohc=HkR4I2VIuEIQ7kNvwFIrSMe&_nc_gid=Kka_B9zrlbZqnVQWiktOpg&edm=AOQ1c0wBAAAA&ccb=7-5&ig_cache_key=MzE3ODQxMTg5MDQ1MDk5ODEyOA%3D%3D.3-ccb7-5&oh=00_AfxZGGjK5RHfrhRDwq4_7TTA2LUfEX9Qe1PPAbT1H9RMhA&oe=69BDAD2B&_nc_sid=8b3546, https://scontent-ord5-2.cdninstagram.com/v/t51.29350-15/370542215_1367581537438445_2207792712365128392_n.jpg?stp=dst-jpg_e35_p1080x1080_tt6&_nc_ht=scontent-ord5-2.cdninstagram.com&_nc_cat=105&_nc_oc=Q6cZ2QFD9NVXmMzDIdsv6i_AI4tYuNjNCZPkVrXCeueAsWZg6wi38UCVNd6i-bWG6psiD5o&_nc_ohc=nyHmpxz7yBMQ7kNvwF_Bx_n&_nc_gid=Kka_B9zrlbZqnVQWiktOpg&edm=AOQ1c0wBAAAA&ccb=7-5&ig_cache_key=MzE3ODQxMTg5MDQzNDMxNjEyMQ%3D%3D.3-ccb7-5&oh=00_AfwZi6J-Ioopz7xxzYD1JN15aVJOluzcqGkJ0eqEVMXGZQ&oe=69BD96CE&_nc_sid=8b3546, https://scontent-ord5-2.cdninstagram.com/v/t51.29350-15/370719677_1045742249938030_8631874460429998941_n.jpg?stp=dst-jpg_e35_p1080x1080_tt6&_nc_ht=scontent-ord5-2.cdninstagram.com&_nc_cat=110&_nc_oc=Q6cZ2QFD9NVXmMzDIdsv6i_AI4tYuNjNCZPkVrXCeueAsWZg6wi38UCVNd6i-bWG6psiD5o&_nc_ohc=j_aojevL4vUQ7kNvwHncTCf&_nc_gid=Kka_B9zrlbZqnVQWiktOpg&edm=AOQ1c0wBAAAA&ccb=7-5&ig_cache_key=MzE3ODQxMTg5MDQ1OTQwMjgzMg%3D%3D.3-ccb7-5&oh=00_AfxmX1sUxpI_vHpQ25zdS4g9rak7qFHXBM9bhwQdA8xQmw&oe=69BDB8B8&_nc_sid=8b3546, https://scontent-ord5-3.cdninstagram.com/v/t51.82787-15/629479272_18346181152238656_7119644693617268080_n.jpg?stp=dst-jpg_e35_p1080x1080_sh0.08_tt6&_nc_ht=scontent-ord5-3.cdninstagram.com&_nc_cat=104&_nc_oc=Q6cZ2QFD9NVXmMzDIdsv6i_AI4tYuNjNCZPkVrXCeueAsWZg6wi38UCVNd6i-bWG6psiD5o&_nc_ohc=Bx_I3SI86R8Q7kNvwGEUXmF&_nc_gid=Kka_B9zrlbZqnVQWiktOpg&edm=AOQ1c0wBAAAA&ccb=7-5&ig_cache_key=MzE3NzgzMTY3Mzg1NjEyODcxMA%3D%3D.3-ccb7-5&oh=00_AfwVPNhLB-KUvXMWEN4dpPP8hmT1oBinf0L0l0ofnpTR3w&oe=69BD90A9&_nc_sid=8b3546, https://sconten | AA13: 9 | AB13: 0 | AC13: 46097 | AD13: loupethis | AE13: collector_page | AF13: https://www.instagram.com/vintagetimes_1
A14: edgarcordero9 | B14: instagram | C14: Edgar Cordero | E14: 239 | F14: 720 | G14: 35 | H14: FALSE | I14: FALSE | L14: https://instagram.fric1-2.fna.fbcdn.net/v/t51.82787-19/623276030_18124725511558793_7691929382419140268_n.jpg?stp=dst-jpg_e0_s150x150_tt6&efg=eyJ2ZW5jb2RlX3RhZyI6InByb2ZpbGVfcGljLmRqYW5nby40NTMuYzIifQ&_nc_ht=instagram.fric1-2.fna.fbcdn.net&_nc_cat=105&_nc_oc=Q6cZ2QGbSvS_oHayYfEFpCxE9eEtQgleWjzgsiZFnXZhuJ6yqp0YIxsjM4W41XLgHxgiu_s&_nc_ohc=O96y9BBT99cQ7kNvwFGWRh1&_nc_gid=gO_or9YlZO9WvgEKjv2POw&edm=AOQ1c0wBAAAA&ccb=7-5&oh=00_AfzbZPfjcr40JpSjGzbG-ac_nJ7kvWAquFzP6HrKXg35HA&oe=69BDAD33&_nc_sid=8b3546 | O14: 0.0561 | P14: 3rd week of training. 3 semana d entrenamiento. | One of my favorite rings. Uno d mis anillos favoritos. | men's gadgets. Dispositivos d hombre. | Beautiful set of vintage lockers in silver for pictures etc. DM for details.Antiguo hermoso set d porta retratos en plata. Para mas informacion enviar MI. | Beautiful set of vintage brooches fro different countries. DM if interested. | XEMEX GMT Automatic Swiss made. DM for price. | Swiss vintage watches from left to right: gold filed Hamilton, women's hand wind Omega, Waltham gold filed hand wind watch and Guccy Swiss battery women's watch. DM for inquiries. | Parte d mis tesoritos. Enviar mensaje si t interesa alguna joya. Part of my treasure. Dm me if interested in any piece. | One of my favorite timepieces. Good luck finding one like it. Not for sale. | I found this very heavy cross with chain and stones, it looks like silver and it is very heavy. It looks very old. Anyone can tell me how old it could be? Thanks | Super rare find: Van Den Bauwede, Coke besal, swiss atomatic 43mm Magnum Diver Caliber 30. One of my favorite watches. | 45mm Kalmar proffesional divers watch. Swiss automatic movement. 3000 meters waterproof. DM for price. | S14: https://instagram.com/p/DNXImaVsjU9, https://instagram.com/p/DNBSFrLRN4Y, https://instagram.com/p/DMdsmJISBZW, https://instagram.com/p/DMdATl9uoiU, https://instagram.com/p/DMIsqelRS8m, https://instagram.com/p/DACd-NnS7EO, https://instagram.com/p/C_ZptI7O5P4, https://instagram.com/p/C_ZfNYquZWE, https://instagram.com/p/C-Rld0FuWRB, https://instagram.com/p/C9tXODRuG0R, https://instagram.com/p/C9qn2inOzDQ, https://instagram.com/p/C9l01f5ul4d | T14: 11, 10, 9, 4, 8, 44, 18, 15, 8, 7, 12, 4 | U14: 4, 1, 2, 1, 1, 0, 0, 2, 0, 0, 0, 0 | V14: 2025-08-15, 2025-08-06, 2025-07-23, 2025-07-23, 2025-07-15, 2024-09-18, 2024-09-02, 2024-09-02, 2024-08-05, 2024-07-22, 2024-07-21, 2024-07-19 | W14: North Miami, Florida, Miami, Florida | X14: Image, Image, Image, Image, Image, Image, Image, Image, Image, Image, Video, Video | Y14: https://instagram.fric1-2.fna.fbcdn.net/v/t51.82787-15/533411306_18107590537558793_6353227979430454981_n.webp?stp=dst-jpg_e15_tt6&_nc_ht=instagram.fric1-2.fna.fbcdn.net&_nc_cat=105&_nc_oc=Q6cZ2QGbSvS_oHayYfEFpCxE9eEtQgleWjzgsiZFnXZhuJ6yqp0YIxsjM4W41XLgHxgiu_s&_nc_ohc=Sb_jCtNbig4Q7kNvwEWvPoK&_nc_gid=gO_or9YlZO9WvgEKjv2POw&edm=AOQ1c0wBAAAA&ccb=7-5&ig_cache_key=MzY5OTQ2MzQ0MjkwMTY0NDYwNQ%3D%3D.3-ccb7-5&oh=00_AfwiNZqnaPgMaAvimnHxOSYUnQA5hfkLHzDordQBLkS8Uw&oe=69BD8D6D&_nc_sid=8b3546, https://instagram.fric1-2.fna.fbcdn.net/v/t51.82787-15/527916107_18106793317558793_7886008624944757447_n.webp?stp=dst-jpg_e15_fr_s1080x1080_tt6&_nc_ht=instagram.fric1-2.fna.fbcdn.net&_nc_cat=105&_nc_oc=Q6cZ2QGbSvS_oHayYfEFpCxE9eEtQgleWjzgsiZFnXZhuJ6yqp0YIxsjM4W41XLgHxgiu_s&_nc_ohc=rL35r8w4KhsQ7kNvwFAg0ey&_nc_gid=gO_or9YlZO9WvgEKjv2POw&edm=AOQ1c0wBAAAA&ccb=7-5&ig_cache_key=MzY5MzMxMjcyNDIxNTA2MjA0MA%3D%3D.3-ccb7-5&oh=00_AfylJ3L69eVEK6havEQORB7tLSIkdRM8OWGTRlv33EBw5Q&oe=69BD90B2&_nc_sid=8b3546, https://instagram.fric1-2.fna.fbcdn.net/v/t51.82787-15/522178246_18105539347558793_3736593402740572297_n.webp?stp=dst-jpg_e15_fr_s1080x1080_tt6&_nc_ht=instagram.fric1-2.fna.fbcdn.net&_nc_cat=105&_nc_oc=Q6cZ2QGbSvS_oHayYfEFpCxE9eEtQgleWjzgsiZFnXZhuJ6yqp0YIxsjM4W41XLgHxgiu_s&_nc_ohc=llPFO3UroBgQ7kNvwE97mM9&_nc_gid=gO_or9YlZO9WvgEKjv2POw&edm=AOQ1c0wBAAAA&ccb=7-5&ig_cache_key=MzY4MzI5NjIwNTQ0ODE1Njc1OA%3D%3D.3-ccb7-5&oh=00_AfwRFENkm6h3Y9HoHVJh0EVSIxg8UsNOJcHb-y9KrM2zkQ&oe=69BDA20E&_nc_sid=8b3546, https://instagram.fric1-2.fna.fbcdn.net/v/t51.82787-15/522216891_18105509023558793_6865507203161749470_n.webp?stp=dst-jpg_e15_fr_s1080x1080_tt6&_nc_ht=instagram.fric1-2.fna.fbcdn.net&_nc_cat=105&_nc_oc=Q6cZ2QGbSvS_oHayYfEFpCxE9eEtQgleWjzgsiZFnXZhuJ6yqp0YIxsjM4W41XLgHxgiu_s&_nc_ohc=2W813bAoIaoQ7kNvwF9-ZbE&_nc_gid=gO_or9YlZO9WvgEKjv2POw&edm=AOQ1c0wBAAAA&ccb=7-5&ig_cache_key=MzY4MzEwMTQxNjY5MzA3NDA2OA%3D%3D.3-ccb7-5&oh=00_AfweaCyvGkQlXtYy9LnQA-fsS2yqk6MyLcr3Nq9mPK8WsQ&oe=69BD8961&_nc_sid=8b3546, https://instagram.fric1-2.fna.fbcdn.net/v/t51.82787-15/519673710_18104802589558793_1027802214845397019_n.webp?stp=dst-jpg_e15_fr_s1080x1080_tt6&_nc_ht=instagram.fric1-2.fna.fbcdn.net&_nc_cat=105&_nc_oc=Q6cZ2QGbSvS_oHayYfEFpCxE9eEtQgleWjzgsiZFnXZhuJ6yqp0YIxsjM4W41XLgHxgiu_s&_nc_ohc=mkLrXYGugEcQ7kNvwGMYO-P&_nc_gid=gO_or9YlZO9WvgEKjv2POw&edm=AOQ1c0wBAAAA&ccb=7-5&ig_cache_key=MzY3NzM4NTUyODg1MDA2NzIzOA%3D%3D.3-ccb7-5&oh=00_AfzW1ZaZXAW71-QLm_okokgILVUYMV_-K2j171bqC7S4Tg&oe=69BD9ED3&_nc_sid=8b3546, https://instagram.fric1-2.fna.fbcdn.net/v/t51.82787-15/622610254_18092437253070791_5297107884964783953_n.webp?stp=dst-jpg_e15_tt6&_nc_ht=instagram.fric1-2.fna.fbcdn.net&_nc_cat=111&_nc_oc=Q6cZ2QGbSvS_oHayYfEFpCxE9eEtQgleWjzgsiZFnXZhuJ6yqp0YIxsjM4W41XLgHxgiu_s&_nc_ohc=ufn4T_JumRUQ7kNvwH1wB7C&_nc_gid=gO_or9YlZO9WvgEKjv2POw&edm=AOQ1c0wBAAAA&ccb=7-5&ig_cache_key=MzQ1OTQ1OTI4MjM0ODI1NzU1MA%3D%3D.3-ccb7-5&oh=00_AfxM8QKwOJ8nWR5gxgumTrgzXzifM7i0MJThDQLAzq4fNA&oe=69BDB03C&_nc_sid=8b3546, https://instagram.fric1-2.fna.fbcdn.net/v/t51.82787-15/626649065_18096585149074119_5238307589226634775_n.webp?stp=dst-jpg_e15_fr_s1080x1080_tt6&_nc_ht=instagram.fric1-2.fna.fbcdn.net&_nc_cat=103&_nc_oc=Q6cZ2QGbSvS_oHayYfEFpCxE9eEtQgleWjzgsiZFnXZhuJ6yqp0YIxsjM4W41XLgHxgiu_s&_nc_ohc=2SBCZ2nkcCoQ7kNvwFPMmM0&_nc_gid=gO_or9YlZO9WvgEKjv2POw&edm=AOQ1c0wBAAAA&ccb=7-5&ig_cache_key=MzQ0Nzk3MDQxMTU5NTkyODU2OA%3D%3D.3-ccb7-5&oh=00_AfyviqptOAYrB9rv5HUhJdT6qm6VzTsnSArH3rKbrHOuow&oe=69BD9042&_nc_sid=8b3546, https://instagram.fric1-1.fna.fbcdn.net/v/t51.82787-15/625974344_18105949318689284_585685809751377853_n.webp?stp=dst-jpg_e15_fr_s1080x1080_tt6&_nc_ht=instagram.fric1-1.fna.fbcdn.net&_nc_cat=108&_nc_oc=Q6cZ2QGbSvS_oHayYfEFpCxE9eEtQgleWjzgsiZFnXZhuJ6yqp0YIxsjM4W41XLgHxgiu_s&_nc_ohc=LmXVSIAoJGkQ7kNvwH8z6Mb&_nc_gid=gO_or9YlZO9WvgEKjv2POw&edm=AOQ1c0wBAAAA&ccb=7-5&ig_cache_key=MzQ0NzkyNDI0OTAxMDQ3NjQyMA%3D%3D.3-ccb7-5&oh=00_AfzCf4uUaZjB1-sbfdOywP88jMThnSgGtwE_9_tG0-jkww&oe=69BD97BA&_nc_sid=8b3546, https://instagram.fric1-2.fna.fbcdn.net/v/t51.82787-15/630099286_18405617401133452_3494389849585993480_n.webp?stp=dst-jpg_e15_fr_s1080x1080_tt6&_nc_ht=instagram.fric1-2.fna.fbcdn.net&_nc_cat=104&_nc_oc=Q6cZ2QGbSvS_oHayYfEFpCxE9eEtQgleWjzgsiZFnXZhuJ6yqp0YIxsjM4W41XLgHxgiu_s&_nc_ohc=QsYKVEmFiAAQ7kNvwHRSMTs&_nc_gid=gO_or9YlZO9WvgEKjv2POw&edm=AOQ1c0wBAAAA&ccb=7-5&ig_cache_key=MzQyNzY4NTU2NzkyMjAwNTA1Nw%3D%3D.3-ccb7-5&oh=00_Afy4OGFfHhLPR8Bev__mwJ2afVJsFQ1R8KhNp95yKoLRXA&oe=69BD8A90&_nc_sid=8b3546, https://instagram.fric1-2.fna.fbcdn.net/v/t51.82787-15/624900665_18086074778158229_9134908921170896493_n.webp?stp=dst-jpg_e15_fr_s1080x1080_tt6&_nc_ht=instagram.fric1-2.fna.fbcdn.net&_nc_cat=105&_nc_oc=Q6cZ2QGbSvS_oHayYfEFpCxE9eEtQgleWjzgsiZFnXZhuJ6yqp0YIxsjM4W41XLgHxgiu_s&_nc_ohc=87-WKQsfxMcQ7kNvwGQtbC1&_nc_gid=gO_or9YlZO9WvgEKjv2POw&edm=AOQ1c0wBAAAA&ccb=7-5&ig_cache_key=MzQxNzQ4OTgxMjkwNTAyODg4MQ%3D%3D.3-ccb7-5&oh=00_AfyZsL5hxmQkF_In9xzWv2Qe_fuol_3ojO60XkcWF_mFSg&oe=69BD8322&_nc_sid=8b3546 | Z14: https://instagram.fric1-2.fna.fbcdn.net/o1/v/t2/f2/m86/AQNSGQ-kc1kUVdldOdjvQkpJK0BOcQ3C_P5YEAkeQB_klATODpmPwmapLOvP3-k8ymwY6a-lsHyL-kbUIpKWpDPESoOAW1UruqFwQ7c.mp4?_nc_cat=103&_nc_oc=AdmqMgJyVRm-IiE3k7m3Ki5-ek1qGbjhHGMtzOyJ7UUq7Ym34aW_eC38wSaiFJSXsR0&_nc_sid=5e9851&_nc_ht=instagram.fric1-2.fna.fbcdn.net&_nc_ohc=ow3GDE623ucQ7kNvwGUGrHs&efg=eyJ2ZW5jb2RlX3RhZyI6Inhwdl9wcm9ncmVzc2l2ZS5JTlNUQUdSQU0uQ0xJUFMuQzMuMzYwLmRhc2hfYmFzZWxpbmVfM192MSIsInhwdl9hc3NldF9pZCI6NzEzMDg3ODI0MjgwMTgzLCJhc3NldF9hZ2VfZGF5cyI6NjAzLCJ2aV91c2VjYXNlX2lkIjoxMDA5OSwiZHVyYXRpb25fcyI6NSwidXJsZ2VuX3NvdXJjZSI6Ind3dyJ9&ccb=17-1&_nc_gid=gO_or9YlZO9WvgEKjv2POw&_nc_ss=1a&_nc_zt=28&vs=1cf3bd0122f517f4&_nc_vs=HBkcFQIYUmlnX3hwdl9yZWVsc19wZXJtYW5lbnRfc3JfcHJvZC9FMzQxQkE5RTYyRDZEMTMxQ0Q0QUUzMDQ3REFBMDM5Ml92aWRlb19kYXNoaW5pdC5tcDQVAALIARIAKAAYABsCiAd1c2Vfb2lsATEScHJvZ3Jlc3NpdmVfcmVjaXBlATEVAAAm7umtp5ajxAIVAigCQzMsF0ASAAAAAAAAGBJkYXNoX2Jhc2VsaW5lXzNfdjERAHX-B2XmnQEA&oh=00_AfykpTFZeU3Qy1cnjCDc6hAqyS2o6bm9VT5goyta4P4PWg&oe=69B9A818, https://instagram.fric1-1.fna.fbcdn.net/o1/v/t2/f2/m86/AQOHjkUn18dwS9lvflji5gPR6uJ8pTFGhapcmXeSm0t-6bUfpMrwLLodzgm_BtgdZvuOoDLgkLGq1NO0fh4SU5miwGPNEJ6alnXNCcE.mp4?_nc_cat=110&_nc_oc=AdnP1TAXkNlHVE1lqwiUR7_bjhZzdN7mqz1osdbggwm42pc-GlGhGwovgTLT7O8Nhgw&_nc_sid=5e9851&_nc_ht=instagram.fric1-1.fna.fbcdn.net&_nc_ohc=o0QD51cctQoQ7kNvwEtX6T4&efg=eyJ2ZW5jb2RlX3RhZyI6Inhwdl9wcm9ncmVzc2l2ZS5JTlNUQUdSQU0uQ0xJUFMuQzMuMzYwLmRhc2hfYmFzZWxpbmVfM192MSIsInhwdl9hc3NldF9pZCI6MTE2NzM4MTExNzkxOTU4MiwiYXNzZXRfYWdlX2RheXMiOjYwNSwidmlfdXNlY2FzZV9pZCI6MTAwOTksImR1cmF0aW9uX3MiOjUsInVybGdlbl9zb3VyY2UiOiJ3d3cifQ%3D%3D&ccb=17-1&_nc_gid=gO_or9YlZO9WvgEKjv2POw&_nc_ss=1a&_nc_zt=28&vs=c8adecef875b7c18&_nc_vs=HBkcFQIYUmlnX3hwdl9yZWVsc19wZXJtYW5lbnRfc3JfcHJvZC84MzRDREY3NjhFRDYzRUQxOTZGMUI2MTJBMzExOUZCNF92aWRlb19kYXNoaW5pdC5tcDQVAALIARIAKAAYABsCiAd1c2Vfb2lsATEScHJvZ3Jlc3NpdmVfcmVjaXBlATEVAAAmvIXPjcPukgQVAigCQzMsF0ASAAAAAAAAGBJkYXNoX2Jhc2VsaW5lXzNfdjERAHX-B2XmnQEA&oh=00_AfyNCIbqab9vU9Uul3rAJGHFwR-blGpn7T4Lo599myA7vA&oe=69B9AFA7 | AA14: 13 | AB14: 1 | AC14: 46097 | AD14: loupethis | AE14: collector_page | AF14: https://www.instagram.com/edgarcordero9
A15: dam3h_333 | B15: instagram | C15: M M K | E15: 719 | F15: 1447 | G15: 198 | H15: FALSE | I15: FALSE | L15: https://scontent-ord5-1.cdninstagram.com/v/t51.2885-19/358016976_320543033632655_6160633656811210839_n.jpg?stp=dst-jpg_e0_s150x150_tt6&efg=eyJ2ZW5jb2RlX3RhZyI6InByb2ZpbGVfcGljLmRqYW5nby43NDMuYzIifQ&_nc_ht=scontent-ord5-1.cdninstagram.com&_nc_cat=111&_nc_oc=Q6cZ2QFUS5Iqj5Nyb6JRtCaIyI_RR05pGLdM3G5BIkpws8aq8MlgOGG_mfCKntaSpmdYr5Q&_nc_ohc=lt-EP_L-n9YQ7kNvwEyEP_s&_nc_gid=9-H2rrphz3nAPU9fHWi-hw&edm=AOQ1c0wBAAAA&ccb=7-5&oh=00_Afw_lkT8QA_7HrtLngO235cAZoR4b7D1gSt7hY0vTG-BPA&oe=69BDB9B9&_nc_sid=8b3546 | O15: 0.0678 | P15: #عيد_مبارك #أضحى | S15: https://instagram.com/p/DP-KEWxCK_v, https://instagram.com/p/Cv2wSRhs_8W, https://instagram.com/p/ClL9YEvjKvj, https://instagram.com/p/ClL9kgBNL1t, https://instagram.com/p/ClL9VfZD_bo, https://instagram.com/p/CG7nNKAACLs, https://instagram.com/p/CDStP0aA6zw, https://instagram.com/p/BgGhkeVHjMF, https://instagram.com/p/BgEze50nDtN, https://instagram.com/p/BKQUlEiAiiw, https://instagram.com/p/BHg1vOVgMI7, https://instagram.com/p/BF_mCW0CqUZ | T15: 29, 11, 23, 55, 36, 11, 12, 48, 47, 116, 99, 66 | U15: 0, 0, 0, 6, 0, 15, 0, 0, 0, 6, 2, 3 | V15: 2025-10-19, 2023-08-12, 2022-11-20, 2022-11-20, 2022-11-20, 2020-10-29, 2020-07-31, 2018-03-09, 2018-03-08, 2016-09-12, 2016-07-06, 2016-05-29 | W15: Four Seasons Hotel Doha, Al Kharrarah, Ad Dawḩah, Qatar, Al Wukair, Ankara, Turkey | X15: Image, Image, Video, Image, Video, Image, Image, Image, Image, Image, Image, Video | Y15: https://scontent-ord5-1.cdninstagram.com/v/t51.82787-15/566519136_18538823026006681_439164417220232768_n.jpg?stp=dst-jpg_e35_s1080x1080_sh0.08_tt6&_nc_ht=scontent-ord5-1.cdninstagram.com&_nc_cat=101&_nc_oc=Q6cZ2QFUS5Iqj5Nyb6JRtCaIyI_RR05pGLdM3G5BIkpws8aq8MlgOGG_mfCKntaSpmdYr5Q&_nc_ohc=wZQ2_CVQSzEQ7kNvwEdrTDP&_nc_gid=9-H2rrphz3nAPU9fHWi-hw&edm=AOQ1c0wBAAAA&ccb=7-5&ig_cache_key=Mzc0NjQ3NjIxOTgwNjgyMjM4Mw%3D%3D.3-ccb7-5&oh=00_Afzwh-6pVR8_JYXX9iGbr2zd4FhiWUDhdx6IZx-n_qdv-Q&oe=69BDA84F&_nc_sid=8b3546, https://scontent-ord5-3.cdninstagram.com/v/t51.82787-15/620495262_17996161058886138_860335857072284453_n.jpg?stp=dst-jpg_e15_tt6&_nc_ht=scontent-ord5-3.cdninstagram.com&_nc_cat=106&_nc_oc=Q6cZ2QFUS5Iqj5Nyb6JRtCaIyI_RR05pGLdM3G5BIkpws8aq8MlgOGG_mfCKntaSpmdYr5Q&_nc_ohc=bulYQhxs7QMQ7kNvwFQNL9_&_nc_gid=9-H2rrphz3nAPU9fHWi-hw&edm=AOQ1c0wBAAAA&ccb=7-5&ig_cache_key=MzE2NzkzMTc0OTkwMzg5MjI0Ng%3D%3D.3-ccb7-5&oh=00_AfyQ_3mK-_DMILidKva6j98-eNOOZGNKRzSjMWxuZIH4FQ&oe=69BD97EA&_nc_sid=8b3546, https://scontent-ord5-3.cdninstagram.com/v/t51.82787-15/621662895_18093848359772529_4263249494575204670_n.jpg?stp=dst-jpg_e35_s1080x1080_sh0.08_tt6&_nc_ht=scontent-ord5-3.cdninstagram.com&_nc_cat=109&_nc_oc=Q6cZ2QFUS5Iqj5Nyb6JRtCaIyI_RR05pGLdM3G5BIkpws8aq8MlgOGG_mfCKntaSpmdYr5Q&_nc_ohc=DnMPumvsK18Q7kNvwF9evrZ&_nc_gid=9-H2rrphz3nAPU9fHWi-hw&edm=AOQ1c0wBAAAA&ccb=7-5&ig_cache_key=Mjk3NTc0Mjc2NzkyNjY1NjM2NQ%3D%3D.3-ccb7-5&oh=00_Afz8UhSXbVh9Fs0cBx9-Trq3Dg9tj8gP-sK3pvsdgzsB-g&oe=69BD9BC4&_nc_sid=8b3546, https://scontent-ord5-2.cdninstagram.com/v/t51.82787-15/627148472_18338721913213562_4977717356082719466_n.jpg?stp=dst-jpg_e35_p1080x1080_sh0.08_tt6&_nc_ht=scontent-ord5-2.cdninstagram.com&_nc_cat=102&_nc_oc=Q6cZ2QFUS5Iqj5Nyb6JRtCaIyI_RR05pGLdM3G5BIkpws8aq8MlgOGG_mfCKntaSpmdYr5Q&_nc_ohc=h73lq8XSuZ4Q7kNvwF49Ox7&_nc_gid=9-H2rrphz3nAPU9fHWi-hw&edm=AOQ1c0wBAAAA&ccb=7-5&ig_cache_key=MjQzMDcwODg1MTgwMTA3MjM2NA%3D%3D.3-ccb7-5&oh=00_Afx2BMuc1KXv8DYaPL2BATH6jsodRFQV_bghrKfQ4mDTCA&oe=69BD9376&_nc_sid=8b3546, https://scontent-ord5-2.cdninstagram.com/v/t51.82787-15/622305882_18069363005169298_2342666017377307055_n.jpg?stp=dst-jpg_e15_tt6&_nc_ht=scontent-ord5-2.cdninstagram.com&_nc_cat=110&_nc_oc=Q6cZ2QFUS5Iqj5Nyb6JRtCaIyI_RR05pGLdM3G5BIkpws8aq8MlgOGG_mfCKntaSpmdYr5Q&_nc_ohc=MAuxLj_m6TgQ7kNvwETLHa1&_nc_gid=9-H2rrphz3nAPU9fHWi-hw&edm=AOQ1c0wBAAAA&ccb=7-5&ig_cache_key=MjM2NTE1MTc1MzQ3OTEwNTc3Ng%3D%3D.3-ccb7-5&oh=00_AfxddiNqO7HINuKqSfRSBsxvcWc1mveRrobytrSev-OeEQ&oe=69BDB340&_nc_sid=8b3546, https://scontent-ord5-3.cdninstagram.com/v/t51.82787-15/639516763_18571790143042869_8993767024088833602_n.jpg?stp=dst-jpg_e15_fr_p1080x1080_tt6&_nc_ht=scontent-ord5-3.cdninstagram.com&_nc_cat=109&_nc_oc=Q6cZ2QFUS5Iqj5Nyb6JRtCaIyI_RR05pGLdM3G5BIkpws8aq8MlgOGG_mfCKntaSpmdYr5Q&_nc_ohc=h9dwIFfZVK0Q7kNvwHtFnl0&_nc_gid=9-H2rrphz3nAPU9fHWi-hw&edm=AOQ1c0wBAAAA&ccb=7-5&ig_cache_key=MTczMTIxODc0ODc3MzExODcyNQ%3D%3D.3-ccb7-5&oh=00_AfxUvT_aKasp3DRLMi-4nIa62W4xgPMNt6sQKHbKbHSpyA&oe=69BDAF45&_nc_sid=8b3546, https://scontent-ord5-3.cdninstagram.com/v/t51.82787-15/639576775_18565403089027048_1815067761325543576_n.jpg?stp=dst-jpg_e15_fr_s1080x1080_tt6&_nc_ht=scontent-ord5-3.cdninstagram.com&_nc_cat=104&_nc_oc=Q6cZ2QFUS5Iqj5Nyb6JRtCaIyI_RR05pGLdM3G5BIkpws8aq8MlgOGG_mfCKntaSpmdYr5Q&_nc_ohc=AoZJHz1EMEoQ7kNvwGtRsrw&_nc_gid=9-H2rrphz3nAPU9fHWi-hw&edm=AOQ1c0wBAAAA&ccb=7-5&ig_cache_key=MTczMDczNDU4MDg1OTQxOTQ2OQ%3D%3D.3-ccb7-5&oh=00_Afwn1IO_4ej8L2JSQc6GfrIz6gZsv0oD0WOVKIEZBVB5-g&oe=69BD90E6&_nc_sid=8b3546, https://scontent-ord5-3.cdninstagram.com/v/t51.82787-15/627926306_18526637998067887_4655012765328310238_n.jpg?stp=dst-jpg_e15_fr_s1080x1080_tt6&_nc_ht=scontent-ord5-3.cdninstagram.com&_nc_cat=107&_nc_oc=Q6cZ2QFUS5Iqj5Nyb6JRtCaIyI_RR05pGLdM3G5BIkpws8aq8MlgOGG_mfCKntaSpmdYr5Q&_nc_ohc=ai1Ia0vPX4cQ7kNvwFB_-RE&_nc_gid=9-H2rrphz3nAPU9fHWi-hw&edm=AOQ1c0wBAAAA&ccb=7-5&ig_cache_key=MTMzNzY1OTU5Nzc0NTQzMjc1Mg%3D%3D.3-ccb7-5&oh=00_AfzsJEoYpjsxr0TmMUJ-FsCa0pvUCZf5wBxfh83_03uq-A&oe=69BDAFCF&_nc_sid=8b3546, https://scontent-ord5-1.cdninstagram.com/v/t51.82787-15/625057839_18440123029109084_8587643786977149914_n.jpg?stp=dst-jpg_e15_fr_s1080x1080_tt6&_nc_ht=scontent-ord5-1.cdninstagram.com&_nc_cat=108&_nc_oc=Q6cZ2QFUS5Iqj5Nyb6JRtCaIyI_RR05pGLdM3G5BIkpws8aq8MlgOGG_mfCKntaSpmdYr5Q&_nc_ohc=U8FiFhIq_1sQ7kNvwH2leBp&_nc_gid=9-H2rrphz3nAPU9fHWi-hw&edm=AOQ1c0wBAAAA&ccb=7-5&ig_cache_key=MTI4ODI2NTgzNTEwMTYwMjM2Mw%3D%3D.3-ccb7-5&oh=00_Afzxu32cLSBuBwSByXMfKmeOtll-JOESkounfFWxfbB5Ig&oe=69BDB347&_nc_sid=8b3546 | Z15: https://scontent-ord5-3.cdninstagram.com/o1/v/t2/f2/m82/AQNuAJI8XtskhlQgUBk2p8n-LF6ewLH7YLrXAaZxvyl2y8sjE2lI414TlZuph_sgTugY3ImYlW9FCGCnjURemMe3caVLxfFbTdhvDxo.mp4?_nc_cat=100&_nc_sid=5e9851&_nc_ht=scontent-ord5-3.cdninstagram.com&_nc_ohc=lcHV2b4iaBwQ7kNvwGYgEo-&efg=eyJ2ZW5jb2RlX3RhZyI6Inhwdl9wcm9ncmVzc2l2ZS5JTlNUQUdSQU0uQ0xJUFMuQzMuNjcyLmRhc2hfYmFzZWxpbmVfMV92MSIsInhwdl9hc3NldF9pZCI6MzMxMDEzMjYxNTg2NjczNSwiYXNzZXRfYWdlX2RheXMiOjEyMTEsInZpX3VzZWNhc2VfaWQiOjEwMDk5LCJkdXJhdGlvbl9zIjo1OSwidXJsZ2VuX3NvdXJjZSI6Ind3dyJ9&ccb=17-1&_nc_gid=9-H2rrphz3nAPU9fHWi-hw&_nc_ss=1a&_nc_zt=28&vs=313ca257e910a9b7&_nc_vs=HBksFQIYT2lnX3hwdl9yZWVsc19wZXJtYW5lbnRfcHJvZC80MjQxRkY5QTFDMUUxQkZBQzYzQ0Y1NzVEQTk1REJCQV92aWRlb19kYXNoaW5pdC5tcDQVAALIARIAFQIYR2lnX3hwdl9yZWVsc19wZXJtYW5lbnRfc3JfcHJvZC8yMjk1MzM4MDczOTc2NDA0XzQ2NTU5NDc0ODYxMDQyOTgwMzYubXA0FQICyAESACgAGAAbAogHdXNlX29pbAExEnByb2dyZXNzaXZlX3JlY2lwZQExFQAAJt6l0-uJo-ELFQIoAkMzLBdATe7ZFocrAhgSZGFzaF9iYXNlbGluZV8xX3YxEQB1_gdl5p0BAA&oh=00_Afz__YpGISFwyEBXEJAQHis-iVt0Bpen8zv4LZSY1VgOTg&oe=69B99BBD, https://scontent-ord5-2.cdninstagram.com/o1/v/t2/f2/m82/AQPUJfLKVFQT9mVGR98ws9R2T4sBuHyMCZf-axOiUsRPR0xX0d02d-ZXQVOseeeLc45ieHKl662V2ggk_PdyhuG2_t0rrjyQnECGFog.mp4?_nc_cat=110&_nc_sid=5e9851&_nc_ht=scontent-ord5-2.cdninstagram.com&_nc_ohc=9AJqozIOEZcQ7kNvwFZiPFL&efg=eyJ2ZW5jb2RlX3RhZyI6Inhwdl9wcm9ncmVzc2l2ZS5JTlNUQUdSQU0uQ0xJUFMuQzMuNjcyLmRhc2hfYmFzZWxpbmVfMV92MSIsInhwdl9hc3NldF9pZCI6NTk0MTEzMzQyOTI4MDI3MSwiYXNzZXRfYWdlX2RheXMiOjEyMTEsInZpX3VzZWNhc2VfaWQiOjEwMDk5LCJkdXJhdGlvbl9zIjoyOSwidXJsZ2VuX3NvdXJjZSI6Ind3dyJ9&ccb=17-1&_nc_gid=9-H2rrphz3nAPU9fHWi-hw&_nc_ss=1a&_nc_zt=28&vs=563657932b580573&_nc_vs=HBksFQIYT2lnX3hwdl9yZWVsc19wZXJtYW5lbnRfcHJvZC82RjQzNDhFMjlGOEY5MTJBNDVDNTRFMzQxREIwMTBBM192aWRlb19kYXNoaW5pdC5tcDQVAALIARIAFQIYRmlnX3hwdl9yZWVsc19wZXJtYW5lbnRfc3JfcHJvZC84NjMzNTEzOTQ2NzA4MzRfNTg2NjMwODE2ODI1NTk1OTA3My5tcDQVAgLIARIAKAAYABsCiAd1c2Vfb2lsATEScHJvZ3Jlc3NpdmVfcmVjaXBlATEVAAAmnrjsub3bjRUVAigCQzMsF0A9XbItDlYEGBJkYXNoX2Jhc2VsaW5lXzFfdjERAHX-B2XmnQEA&oh=00_AfyMDNTiGgXbdYVPt2bOtoX53iADim9l0JrUVjV7KMTdZg&oe=69B9B16B, https://scontent-ord5-2.cdninstagram.com/o1/v/t16/f2/m84/AQNyOYItTijWjp8IkmGAkZa7vd1sRoDICATz4Zam5F6VJUpYj4U6rEnHLhhvhHsKP6D0bV8dZbMdIuYXEY8qhpT61cZdAxUJjXezcDg.mp4?_nc_cat=110&_nc_sid=5e9851&_nc_ht=scontent-ord5-2.cdninstagram.com&_nc_ohc=n6QdpHiD860Q7kNvwFNrWIC&efg=eyJ2ZW5jb2RlX3RhZyI6Inhwdl9wcm9ncmVzc2l2ZS5JTlNUQUdSQU0uRkVFRC5DMy42NDAuZGFzaF9iYXNlbGluZV8xX3YxIiwieHB2X2Fzc2V0X2lkIjoxNzk3NTY0MzUxNzY3MjEsImFzc2V0X2FnZV9kYXlzIjoyNjYwLCJ2aV91c2VjYXNlX2lkIjoxMDE0NiwiZHVyYXRpb25fcyI6MzQsInVybGdlbl9zb3VyY2UiOiJ3d3cifQ%3D%3D&ccb=17-1&_nc_gid=9-H2rrphz3nAPU9fHWi-hw&_nc_ss=1a&_nc_zt=28&vs=72cb21a7fc553b45&_nc_vs=HBksFQIYTGlnX2JhY2tmaWxsX3RpbWVsaW5lX3ZvZC80RjQwMDNGNTFERTk4QzhFREI5MTNDRURBNTg1NTM5QV92aWRlb19kYXNoaW5pdC5tcDQVAALIARIAFQIYOnBhc3N0aHJvdWdoX2V2ZXJzdG9yZS9HTjAxZGhkaFIzMDB6d3NCQUozZHY0UTlNUUJiYnBrd0FBQUYVAgLIARIAKAAYABsCiAd1c2Vfb2lsATEScHJvZ3Jlc3NpdmVfcmVjaXBlATEVAAAmovS355nfURUCKAJDMywXQEEqwIMSbpgYEmRhc2hfYmFzZWxpbmVfMV92MREAdeoHZcSeAQA&oh=00_Afy5fROuiceKthbZvuNtFm8mP4hWKqvJJVFiOAK3Jkta6g&oe=69B9A862 | AA15: 46 | AB15: 3 | AC15: 46097 | AD15: loupethis | AE15: collector_page | AF15: https://www.instagram.com/dam3h_333
A16: lisawaltn | B16: instagram | C16: Realtor Los Angeles | Lisa Walton | D16: 🌎 Дома,аренда,бизнес в Лос-Анджелесе 🏡 Luxury Homes • Leasing • 💲Investments•🌴Los Angeles 💼 20+Years in Real Estate 📩 DM for listings•consultations | E16: 186149 | F16: 3147 | G16: 709 | H16: TRUE | I16: FALSE | K16: https://www.themls.com/Share/YWFoYWRnZWJp | L16: https://scontent-phl2-1.cdninstagram.com/v/t51.2885-19/334382430_1322060535318951_4996135342304660630_n.jpg?stp=dst-jpg_e0_s150x150_tt6&efg=eyJ2ZW5jb2RlX3RhZyI6InByb2ZpbGVfcGljLmRqYW5nby45NTkuYzIifQ&_nc_ht=scontent-phl2-1.cdninstagram.com&_nc_cat=103&_nc_oc=Q6cZ2QHCwM09eTsEekyWhQDcfDQC5k6xdh7NOl-1G66CpciDu31ewK94D_UhnTU7l0NP7GE&_nc_ohc=_pzkK-7kHfEQ7kNvwFu1DDp&_nc_gid=w7EQHEcg-Hy90GA41WSgmg&edm=AOQ1c0wBAAAA&ccb=7-5&oh=00_AfzgoapfVe0DydKH8ZBZmPWRy7Ki0Xc9iOdocxsn5OHpHw&oe=69BD89FF&_nc_sid=8b3546 | O16: 0.0003 | P16: ➡️Licensed Collision Center For Sale in Van Nuys, CA! Great owner user property For Sale! Part 2. Turn-key facility with two licensed spray booths, office space, and a private balcony overlooking the entire lot. A rare, fully compliant opportunity in a prime Los Angeles location. DM for Showings | Turn-key Collision Center For Sale in Van Nuys! 🚗💨 • Multiple motorized garage doors • Two fully permitted spray booths • High-end vehicle lifts ($120K each) • Prep, paint & frame repair areas • Reception/office + ample parking Fully permitted, high-volume auto body & collision facility — ideal fo | ➡️For Sale In Topanga‼️Step into this bright and inviting 3-bed, 2-bath home with vaulted ceilings, upgraded floors, and a seamless open layout. Enjoy a spacious kitchen with a center island, outdoor living on the covered deck, and a fully gated yard with extra storage. Convenience, comfort, and cha | Hollywood has stars on the sidewalks… but in LA real estate, the real celebrities are the homes. 🏡 Running between showings, meetings, and inspections today in this Egyptian cotton Cairo Set from @qotn.club — soft, breathable, and perfect for a busy LA day. ✨ I love how it combines comfort, style, | I’m not just a Realtor. I’m a consultant, negotiator, problem solver and entrepreneur. 20+ years helping people navigate real estate — from apartments by the ocean to business opportunities and investment properties. Behind every deal there are negotiations, strategy, and protecting my client’s inte | America’s most powerful and luxurious symbol Waldorf Astoria New York Credit to @celebrityhome #manhattan #newyork #losangeles #fypシ #foryou | On March 6 we celebrated my mom’s 80th birthday at the beautiful Little Door in Los Angeles. Grateful for family, love, and moments like this. ❤️ #fyp #viralreels #love #birthdayvibes #familymoments | 80 years of love, laughter, and memories 💖 Surprise hugs, sweet moments, and the queen of my heart at The Little Door ✨ Part 1. #BirthdayMagic #MomGoals #BirthdayVibes #TheLittleDoorLA #love | Поверить не могу, что маме исполнилось 80!!! | Today I received a special package all the way from Kharkiv. 💛💙 I can’t share what’s inside… but it feels like a warm hug from home. Grateful for these little moments that touch the heart. 💌 ⸻ #FromKharkiv #UkraineStrong #PackageOfLove #HomeFeels #HeartfeltMoments | Package theft is NOT a small issue in LA. As a Realtor, I always tell my clients - security matters just as much as location and price. Smart cameras. Good lighting. A strong community. Buy smart. Live safe. Thinking about moving? Let’s choose a neighborhood where you feel protected — not worried. C | A little Hollywood secret 🎬✨ People always ask me… “How do you have so many clients in film & cinematography?” Here’s the truth 👇 While I was in college, I worked in the Cinema Department. I watched young directors create their first films… and many of them became my lifelong friends. Today, t | Q16: #manhattan, #newyork, #losangeles, #fyp, #foryou, #viralreels, #love, #birthdayvibes, #familymoments, #BirthdayMagic, #MomGoals, #BirthdayVibes, #TheLittleDoorLA, #FromKharkiv, #UkraineStrong, #PackageOfLove, #HomeFeels, #HeartfeltMoments | R16: @qotn.club, @celebrityhome, @d_j_roberson, @lisawaltn | S16: https://instagram.com/p/DUMgNvvjAtl, https://instagram.com/p/DTv7Iy7kpnE, https://instagram.com/p/DUBcmy-CXbY, https://instagram.com/p/DV4WNHRkiln, https://instagram.com/p/DVzQ0BOEngv, https://instagram.com/p/DVxXc1nD223, https://instagram.com/p/DVpqb4WoKM6, https://instagram.com/p/DVnbcDTkWZo, https://instagram.com/p/DVjY6N9j6S8, https://instagram.com/p/DVfaopclZ3r, https://instagram.com/p/DVdGLsCDuPB, https://instagram.com/p/DVZBOoCCUUZ | T16: 26, 14, 20, 41, 18, 5, 33, 45, 81, 48, 24, 39 | U16: 8, 4, 6, 46, 6, 2, 12, 22, 54, 18, 4, 8 | V16: 2026-02-01, 2026-01-20, 2026-01-27, 2026-03-14, 2026-03-12, 2026-03-12, 2026-03-09, 2026-03-08, 2026-03-06, 2026-03-05, 2026-03-04, 2026-03-02 | W16: Van Nuys, Los Angeles, Topanga, California, Walk Of Fame Hollywood California, Beverly Hills, California, Manhattan, New York, USA, The Little Door, 3rd Street, Beverly Hills, Los Angeles, California, Beverly Wilshire, Beverly Hills, A Four Seasons Hotel, Hollywood Walk of Fame- Los Angeles, California | X16: Video, Video, Video, Video, Video, Video, Video, Video, Video, Video, Video, Video | Z16: https://scontent-phl2-1.cdninstagram.com/o1/v/t2/f2/m86/AQNsPiRQ1dEDRv6hX658lbTVQ0OMrigOXACkErg9iu4Kcv9edwnSZVX6xhKjN8xzyplP8dfjfXJZr7ZBOKrbe9DlblgGiVtXvY_ygSQ.mp4?_nc_cat=100&_nc_sid=5e9851&_nc_ht=scontent-phl2-1.cdninstagram.com&_nc_ohc=W5P6Y4adhHAQ7kNvwFsbWeQ&efg=eyJ2ZW5jb2RlX3RhZyI6Inhwdl9wcm9ncmVzc2l2ZS5JTlNUQUdSQU0uQ0xJUFMuQzMuNzIwLmRhc2hfYmFzZWxpbmVfMV92MSIsInhwdl9hc3NldF9pZCI6MTc5MzgzMzQzOTcxNDk0MDMsImFzc2V0X2FnZV9kYXlzIjo0MywidmlfdXNlY2FzZV9pZCI6MTAwOTksImR1cmF0aW9uX3MiOjg0LCJ1cmxnZW5fc291cmNlIjoid3d3In0%3D&ccb=17-1&_nc_gid=w7EQHEcg-Hy90GA41WSgmg&_nc_ss=1a&_nc_zt=28&vs=b817048b731d4457&_nc_vs=HBksFQIYUmlnX3hwdl9yZWVsc19wZXJtYW5lbnRfc3JfcHJvZC9BQTQ5OTE1RjY5RTk2NDY5OEE4MjJFRTAzOUMzQzk5M192aWRlb19kYXNoaW5pdC5tcDQVAALIARIAFQIYUWlnX3hwdl9wbGFjZW1lbnRfcGVybWFuZW50X3YyL0FCNDYzQUM3Q0M0MDdCRjZFMzg4Qzk2OTEzQUE3NkI5X2F1ZGlvX2Rhc2hpbml0Lm1wNBUCAsgBEgAoABgAGwKIB3VzZV9vaWwBMRJwcm9ncmVzc2l2ZV9yZWNpcGUBMRUAACa2w9WZvrTdPxUCKAJDMywXQFUEOVgQYk4YEmRhc2hfYmFzZWxpbmVfMV92MREAdf4HZeadAQA&oh=00_AfwkdeQH-f_pHoTRoAq_4-haNU8EEZrhHPzhOIVIqPQkDA&oe=69B9AA09, https://scontent-phl2-1.cdninstagram.com/o1/v/t16/f2/m69/AQO3VNs-GXvsqd0DSvem09cHN0m4ADiHHo6D8PIZ4beIC6ouzQK50-lIENOTECaeaFfuwB7298IiY6-iDF3SX7QN.mp4?strext=1&_nc_cat=100&_nc_sid=5e9851&_nc_ht=scontent-phl2-1.cdninstagram.com&_nc_ohc=skjUO06RAlwQ7kNvwEk5dWx&efg=eyJ2ZW5jb2RlX3RhZyI6Inhwdl9wcm9ncmVzc2l2ZS5JTlNUQUdSQU0uQ0xJUFMuQzMuNzIwLmRhc2hfYmFzZWxpbmVfMV92MSIsInhwdl9hc3NldF9pZCI6MTc5MzY5ODM3OTcxNDk0MDMsImFzc2V0X2FnZV9kYXlzIjo1NCwidmlfdXNlY2FzZV9pZCI6MTAwOTksImR1cmF0aW9uX3MiOjgyLCJ3YXRjaF90aW1lX3MiOjk0NiwidXJsZ2VuX3NvdXJjZSI6Ind3dyJ9&ccb=17-1&vs=abbd0a150eb90f3d&_nc_vs=HBksFQIYOnBhc3N0aHJvdWdoX2V2ZXJzdG9yZS9HQ0xFc2lUd0JLeWljUkFEQUQ0YThaRlZYcEZ0YnNwVEFRQUYVAALIARIAFQIYUWlnX3hwdl9wbGFjZW1lbnRfcGVybWFuZW50X3YyLzRGNDhEQUI4NEU1OTJFMUFDQzI3NzdDMzkxRUQ1N0JCX2F1ZGlvX2Rhc2hpbml0Lm1wNBUCAsgBEgAoABgAGwKIB3VzZV9vaWwBMRJwcm9ncmVzc2l2ZV9yZWNpcGUBMRUAACa2u5G57-XcPxUCKAJDMywXQFS1T987ZFoYEmRhc2hfYmFzZWxpbmVfMV92MREAdf4HZeadAQA&_nc_gid=w7EQHEcg-Hy90GA41WSgmg&_nc_ss=1a&_nc_zt=28&oh=00_AfwtZhqfOWuwXCkEhPFxoq-wi1GfjTwQ14nm288XvhyJ3g&oe=69BDA8B8, https://scontent-phl2-1.cdninstagram.com/o1/v/t2/f2/m86/AQNqn9dDafjSzdu-6HGW4GsDiYSd7fO4wxmVtgnIItsueQ2oNX4NAU1KANnCnv9rHRbWMlza9Fx0LuzBhkxuglCOsSGtadwGxAQgIyQ.mp4?_nc_cat=101&_nc_sid=5e9851&_nc_ht=scontent-phl2-1.cdninstagram.com&_nc_ohc=AZQwnV6SVPMQ7kNvwErj1Gp&efg=eyJ2ZW5jb2RlX3RhZyI6Inhwdl9wcm9ncmVzc2l2ZS5JTlNUQUdSQU0uQ0xJUFMuQzMuNzIwLmRhc2hfYmFzZWxpbmVfMV92MSIsInhwdl9hc3NldF9pZCI6MTc5Mzc4MTY2MDMxNDk0MDMsImFzc2V0X2FnZV9kYXlzIjo0NywidmlfdXNlY2FzZV9pZCI6MTAwOTksImR1cmF0aW9uX3MiOjI2LCJ1cmxnZW5fc291cmNlIjoid3d3In0%3D&ccb=17-1&_nc_gid=w7EQHEcg-Hy90GA41WSgmg&_nc_ss=1a&_nc_zt=28&vs=38a874b5887e41ed&_nc_vs=HBksFQIYUmlnX3hwdl9yZWVsc19wZXJtYW5lbnRfc3JfcHJvZC83NjQ5ODM1RjA2QUU0OEQ5MjM1NDE0M0JFQUFGNDFBRF92aWRlb19kYXNoaW5pdC5tcDQVAALIARIAFQIYUWlnX3hwdl9wbGFjZW1lbnRfcGVybWFuZW50X3YyLzQxNDg0RDNCQjE0QTNGRDc3RjkyNjg0RjMwODRDRDk0X2F1ZGlvX2Rhc2hpbml0Lm1wNBUCAsgBEgAoABgAGwKIB3VzZV9vaWwBMRJwcm9ncmVzc2l2ZV9yZWNpcGUBMRUAACa2keqqrJbdPxUCKAJDMywXQDq1P3ztkWgYEmRhc2hfYmFzZWxpbmVfMV92MREAdf4HZeadAQA&oh=00_Afwm2oIirysKHjbagcW5IfjYPT0hvDtNYqeMs3uCzwcdHQ&oe=69B9A91A, https://scontent-phl2-1.cdninstagram.com/o1/v/t16/f2/m69/AQO-R41mnQ3Tw_CoVFcAM8i6K2uOcWmW_dw7n_56zZqV7Tjs1zZKW4QKFvZEqSIQ-LDT2OBmAe8jffM9HIBlkAWb.mp4?strext=1&_nc_cat=109&_nc_sid=5e9851&_nc_ht=scontent-phl2-1.cdninstagram.com&_nc_ohc=Vxk7OR9FLf0Q7kNvwFzfykK&efg=eyJ2ZW5jb2RlX3RhZyI6Inhwdl9wcm9ncmVzc2l2ZS5JTlNUQUdSQU0uQ0xJUFMuQzMuNzIwLmRhc2hfYmFzZWxpbmVfMV92MSIsInhwdl9hc3NldF9pZCI6MTc5NDM4MDUxMjgxNDk0MDMsImFzc2V0X2FnZV9kYXlzIjoxLCJ2aV91c2VjYXNlX2lkIjoxMDA5OSwiZHVyYXRpb25fcyI6MjQsInVybGdlbl9zb3VyY2UiOiJ3d3cifQ%3D%3D&ccb=17-1&_nc_gid=w7EQHEcg-Hy90GA41WSgmg&_nc_ss=1a&_nc_zt=28&vs=62548aad2410af61&_nc_vs=HBksFQIYOnBhc3N0aHJvdWdoX2V2ZXJzdG9yZS9HRVl6d3lieFp6TlhoVVFNQVA5VkFnUWE2SmhEYnNwVEFRQUYVAALIARIAFQIYUWlnX3hwdl9wbGFjZW1lbnRfcGVybWFuZW50X3YyLzk4NEZBOTU2RDJERjZFRTM2NjM0QjY5RDFFOUU5NEE5X2F1ZGlvX2Rhc2hpbml0Lm1wNBUCAsgBEgAoABgAGwKIB3VzZV9vaWwBMRJwcm9ncmVzc2l2ZV9yZWNpcGUBMRUAACa2pqip9vLfPxUCKAJDMywXQDgiDEm6XjUYEmRhc2hfYmFzZWxpbmVfMV92MREAdf4HZeadAQA&oh=00_AfzsLmgcJ_T9rln9A6cd4LyXSgrvZbWbCZbEaFPcZPzgHw&oe=69BDA49F, https://scontent-phl2-1.cdninstagram.com/o1/v/t16/f2/m69/AQPIer1q0hTC8vRSVMbRAhAZL03DY5vztIviIP5r9QOrZWdj-KRdMB5r51-0O6Xsm8JXhwxLTPwkcBm-39FOeJeb.mp4?strext=1&_nc_cat=105&_nc_sid=5e9851&_nc_ht=scontent-phl2-1.cdninstagram.com&_nc_ohc=ctqISATZsbEQ7kNvwGlwBnG&efg=eyJ2ZW5jb2RlX3RhZyI6Inhwdl9wcm9ncmVzc2l2ZS5JTlNUQUdSQU0uQ0xJUFMuQzMuNzIwLmRhc2hfYmFzZWxpbmVfMV92MSIsInhwdl9hc3NldF9pZCI6MTc5NDM1MjU2MzMxNDk0MDMsImFzc2V0X2FnZV9kYXlzIjozLCJ2aV91c2VjYXNlX2lkIjoxMDA5OSwiZHVyYXRpb25fcyI6MjEsInVybGdlbl9zb3VyY2UiOiJ3d3cifQ%3D%3D&ccb=17-1&_nc_gid=w7EQHEcg-Hy90GA41WSgmg&_nc_ss=1a&_nc_zt=28&vs=418e3e2903c2e305&_nc_vs=HBksFQIYOnBhc3N0aHJvdWdoX2V2ZXJzdG9yZS9HSnhVdGlaV0pGaEktcHNHQVBQc1FaLTZ6eEp6YnNwVEFRQUYVAALIARIAFQIYUWlnX3hwdl9wbGFjZW1lbnRfcGVybWFuZW50X3YyL0M4NDJCN0E2Rjg5NjUyMjU2NkVBOUJGOEQyNThGRDlBX2F1ZGlvX2Rhc2hpbml0Lm1wNBUCAsgBEgAoABgA | AA16: 33 | AB16: 16 | AC16: 46097 | AD16: loupethis | AE16: collector_page | AF16: https://www.instagram.com/lisawaltn
A17: rhinococktails | B17: instagram | C17: Rhino Williams | D17: Welshman in Hollywood, CA making and creating cocktails. 🏴󠁧󠁢󠁷󠁬󠁳󠁿🦏🥃🇺🇸Hogyn o Gymru yn Hollywood, CA genud a creu coctails. 🏴󠁧󠁢󠁷󠁬󠁳󠁿🦏🥃🇺🇸 | E17: 1061 | F17: 4344 | G17: 116 | H17: FALSE | I17: FALSE | J17: People | K17: http://lostpropertybar.com/ | L17: https://scontent-lga3-1.cdninstagram.com/v/t51.2885-19/314701310_3543144005903266_702641318959271513_n.jpg?stp=dst-jpg_e0_s150x150_tt6&efg=eyJ2ZW5jb2RlX3RhZyI6InByb2ZpbGVfcGljLmRqYW5nby41NTcuYzIifQ&_nc_ht=scontent-lga3-1.cdninstagram.com&_nc_cat=110&_nc_oc=Q6cZ2QEp9vICBLef8aFcSQLnxDSE07PweegjQWVxAEjsF3viOaoR1HoyRuzyowk9lUvd6xE&_nc_ohc=Rl_5nUTSJMYQ7kNvwFl8Cap&_nc_gid=DoBPfmDs1aApTXm89VRysQ&edm=AOQ1c0wBAAAA&ccb=7-5&oh=00_Afwgenuy7smWSoM1Eo5eaQMmTG_gCQcI6bWRryE-Vk3EbA&oe=69BD93A0&_nc_sid=8b3546 | O17: 0.0549 | P17: Tomorrow night! SATURDAY MARCH 14th Get it!! LP Vinyl Bar 1704 Vine at Hollywood 8 til Late NO COVER #hollywood #funk #housemusic #disco #vinyl | The schedule is out, the turntables are warm and the drinks are cold. Slide through, grab a cocktail, and let the vinyl do the talking. No algorithms. Just grooves! | This week’s schedule at LP Vinyl Bar! The records are stacked. The bartenders are dangerous. The dance floor is calling your name. If you’re not here, you’re somewhere boring. | TONIGHT!!! We welcome back @AndyCaldwell to spin some vinyl gems at @LPVinylBar!! It’s gonna be a fun one along with @SenorDiscos in the mix. Doors open at 8p | No playlists. No distractions. Just great drinks, good company, and a full album spinning on vinyl. Come vibe with us for an album listening party of @loneshipmusic newest album, Nightsun, you’ll feel long after the last track fades. | TONITE! We’ve got a big one for you! @xraythebaby an @mtritter will be behind the booth, playing the hits, deep cuts, and everything in between. You don’t want to miss this one! | RESCHEDULE: Professor Ben will be switching nights, we will give updates on new dates shortly. In light of today’s protests, we will have @djdoublebird, @djraulcampos and @finnlankan playing the biggest and best protest songs, all nite long, all on vinyl. Stay safe, stay vocal. | This week at the bar 💿 Fresh wax. Heavy grooves. Zero skips. We’ve got selectors behind the decks every night, spinning everything from deep cuts to dancefloor essentials. Pull up, grab a drink, and let the records do the talking. | TONIGHT! Just back from the east coast and ready to boogie! Bringing some fresh treats from @hrrecords so prepare to get down! | This week’s schedule is spinning hot. We’ve lined up a crew of selectors bringing everything from deep cuts to dancefloor classics—all on wax. Come hang, sip something strong, and let the music handle the rest. | LA Deadheads, we’ve dug through the crates and found some incredible Bobby moments from the last 60 years, all on vinyl. Join us from 8p onwards on Wednesday for a celebration of the great man, the musicians he played with, and the fans he played too. 🐺🎸🌹 | This week’s schedule! We have a big, fun week full of awesome DJs playing the best music ever recorded to vinyl! Whether it’s House, Disco, or something from Australia, we’ve got it all, and everything in between! | Q17: #hollywood, #funk, #housemusic, #disco, #vinyl | R17: @AndyCaldwell, @LPVinylBar, @SenorDiscos, @loneshipmusic, @xraythebaby, @mtritter, @djdoublebird, @djraulcampos, @finnlankan, @hrrecords | S17: https://instagram.com/p/DV0yG-MDpxQ, https://instagram.com/p/DVudzdaiVpI, https://instagram.com/p/DVcMoGigeVX, https://instagram.com/p/DVRd7xJElW9, https://instagram.com/p/DUkaQI2Eo0W, https://instagram.com/p/DUbd23wkvK9, https://instagram.com/p/DUJWLjlARhV, https://instagram.com/p/DUE9TvaERdG, https://instagram.com/p/DT0785WE_Jl, https://instagram.com/p/DT0uvDzkm-N, https://instagram.com/p/DTwD_hIktQ-, https://instagram.com/p/DTikC6qgamB | T17: 33, 61, 46, 308, 19, 23, 23, 30, 29, 17, 42, 35 | U17: 1, 0, 1, 21, 1, 1, 0, 0, 2, 2, 0, 4 | V17: 2026-03-13, 2026-03-11, 2026-03-03, 2026-02-27, 2026-02-10, 2026-02-06, 2026-01-30, 2026-01-29, 2026-01-22, 2026-01-22, 2026-01-20, 2026-01-15 | W17: Lost Property Bar, Hollywood & Vine | X17: Video, Image, Image, Sidecar, Image, Image, Image, Image, Image, Image, Image, Image | Y17: https://scontent-lga3-3.cdninstagram.com/v/t51.82787-15/649338414_18571125181017944_738467017091063916_n.jpg?stp=dst-jpg_e35_p1080x1080_sh0.08_tt6&_nc_ht=scontent-lga3-3.cdninstagram.com&_nc_cat=108&_nc_oc=Q6cZ2QEp9vICBLef8aFcSQLnxDSE07PweegjQWVxAEjsF3viOaoR1HoyRuzyowk9lUvd6xE&_nc_ohc=cYImxkeSSVIQ7kNvwHkm10L&_nc_gid=DoBPfmDs1aApTXm89VRysQ&edm=AOQ1c0wBAAAA&ccb=7-5&ig_cache_key=Mzg1MDE0NTgxMTA3NDIxMDM3Ng%3D%3D.3-ccb7-5&oh=00_AfwYopbK5Ue66aTvTvmhlR20lc8J-obrnLaWhzXjGrh20Q&oe=69BDA8F4&_nc_sid=8b3546, https://scontent-lga3-3.cdninstagram.com/v/t51.82787-15/642842485_18569511844017944_6465768084336649309_n.jpg?stp=dst-jpg_e35_p1080x1080_sh0.08_tt6&_nc_ht=scontent-lga3-3.cdninstagram.com&_nc_cat=108&_nc_oc=Q6cZ2QEp9vICBLef8aFcSQLnxDSE07PweegjQWVxAEjsF3viOaoR1HoyRuzyowk9lUvd6xE&_nc_ohc=6Db1xSxFW4sQ7kNvwGweOPh&_nc_gid=DoBPfmDs1aApTXm89VRysQ&edm=AOQ1c0wBAAAA&ccb=7-5&ig_cache_key=Mzg0NTAwMzcxNDIyNjE1Mjc5MQ%3D%3D.3-ccb7-5&oh=00_AfzhWfVeuwHhw31ICZZp51jdpgVm75pXvNHQn7z5Cbd_Rg&oe=69BDAF7A&_nc_sid=8b3546, https://scontent-lga3-2.cdninstagram.com/v/t51.82787-15/641250665_18574995046044336_6574914997723656873_n.jpg?stp=dst-jpg_e35_p1080x1080_sh0.08_tt6&_nc_ht=scontent-lga3-2.cdninstagram.com&_nc_cat=100&_nc_oc=Q6cZ2QEp9vICBLef8aFcSQLnxDSE07PweegjQWVxAEjsF3viOaoR1HoyRuzyowk9lUvd6xE&_nc_ohc=qS80mCzZkfUQ7kNvwGfqasF&_nc_gid=DoBPfmDs1aApTXm89VRysQ&edm=AOQ1c0wBAAAA&ccb=7-5&ig_cache_key=Mzg0MTk3OTg2MzMzOTc3NjkzMQ%3D%3D.3-ccb7-5&oh=00_Afzn8R-PbiJ_518PRqeenKgrYmKgq5oYOfpprzAY2cZ1CA&oe=69BDABFC&_nc_sid=8b3546, https://scontent-lga3-2.cdninstagram.com/v/t51.82787-15/641250665_18574995046044336_6574914997723656873_n.jpg?stp=dst-jpg_e35_p1080x1080_sh0.08_tt6&_nc_ht=scontent-lga3-2.cdninstagram.com&_nc_cat=100&_nc_oc=Q6cZ2QEp9vICBLef8aFcSQLnxDSE07PweegjQWVxAEjsF3viOaoR1HoyRuzyowk9lUvd6xE&_nc_ohc=qS80mCzZkfUQ7kNvwGfqasF&_nc_gid=DoBPfmDs1aApTXm89VRysQ&edm=AOQ1c0wBAAAA&ccb=7-5&ig_cache_key=Mzg0MTk3OTg2MzMzOTc3NjkzMQ%3D%3D.3-ccb7-5&oh=00_Afzn8R-PbiJ_518PRqeenKgrYmKgq5oYOfpprzAY2cZ1CA&oe=69BDABFC&_nc_sid=8b3546, https://scontent-lga3-2.cdninstagram.com/v/t51.82787-15/641052917_18574995055044336_2738304229356002191_n.jpg?stp=dst-jpg_e35_p1080x1080_sh0.08_tt6&_nc_ht=scontent-lga3-2.cdninstagram.com&_nc_cat=100&_nc_oc=Q6cZ2QEp9vICBLef8aFcSQLnxDSE07PweegjQWVxAEjsF3viOaoR1HoyRuzyowk9lUvd6xE&_nc_ohc=ZL-qO4Uqo54Q7kNvwESYz8R&_nc_gid=DoBPfmDs1aApTXm89VRysQ&edm=AOQ1c0wBAAAA&ccb=7-5&ig_cache_key=Mzg0MTk3OTg2NDU2NDU1Nzc5OQ%3D%3D.3-ccb7-5&oh=00_AfzCrfOoeAEFHripwwUJkHqHbH32OSBD0GNNXKMK-m-CFg&oe=69BD8C70&_nc_sid=8b3546, https://scontent-lga3-3.cdninstagram.com/v/t51.82787-15/629351483_18561513325017944_6372308094986551617_n.jpg?stp=dst-jpg_e15_tt6&_nc_ht=scontent-lga3-3.cdninstagram.com&_nc_cat=108&_nc_oc=Q6cZ2QEp9vICBLef8aFcSQLnxDSE07PweegjQWVxAEjsF3viOaoR1HoyRuzyowk9lUvd6xE&_nc_ohc=b7JZqY-ZgDUQ7kNvwFyPiNb&_nc_gid=DoBPfmDs1aApTXm89VRysQ&edm=AOQ1c0wBAAAA&ccb=7-5&ig_cache_key=MzgyOTMwMTA0MTM4OTgwMDcyNg%3D%3D.3-ccb7-5&oh=00_AfxdZQ39vaG4hkMzwqsmbatObCHXm1s1uCq9k_aK7It50Q&oe=69BD8239&_nc_sid=8b3546, https://scontent-lga3-3.cdninstagram.com/v/t51.82787-15/626931469_18559850701017944_2361394075343340201_n.jpg?stp=dst-jpg_e35_p1080x1080_sh0.08_tt6&_nc_ht=scontent-lga3-3.cdninstagram.com&_nc_cat=108&_nc_oc=Q6cZ2QEp9vICBLef8aFcSQLnxDSE07PweegjQWVxAEjsF3viOaoR1HoyRuzyowk9lUvd6xE&_nc_ohc=_BspcQrQ4BEQ7kNvwFoZaNb&_nc_gid=DoBPfmDs1aApTXm89VRysQ&edm=AOQ1c0wBAAAA&ccb=7-5&ig_cache_key=MzgyNjc4MzYyMjQ1MjY3MTE2NQ%3D%3D.3-ccb7-5&oh=00_AfyxJ04z8fI9fuDEq_PQeFxvEhUFh7FRYN4_SA688Z5qFg&oe=69BDB550&_nc_sid=8b3546, https://scontent-lga3-3.cdninstagram.com/v/t51.82787-15/625979074_18556621546017944_8138284173725496594_n.jpg?stp=dst-jpg_e35_p1080x1080_sh0.08_tt6&_nc_ht=scontent-lga3-3.cdninstagram.com&_nc_cat=108&_nc_oc=Q6cZ2QEp9vICBLef8aFcSQLnxDSE07PweegjQWVxAEjsF3viOaoR1HoyRuzyowk9lUvd6xE&_nc_ohc=TdN6rG4xg9YQ7kNvwFKOdOl&_nc_gid=DoBPfmDs1aApTXm89VRysQ&edm=AOQ1c0wBAAAA&ccb=7-5&ig_cache_key=MzgyMTY4MzMwOTkzOTg1NzQ5Mw%3D%3D.3-ccb7-5&oh=00_AfyKlok5U_hfIzUMbBZtYTecCCjFRqHTGqYjevlhm4HuTQ&oe=69BDA1E2&_nc_sid=8b3546, https://scontent-lga3-3.cdninstagram.com/v/t51.82787-15/623395686_18556224298017944_8626668082536722929_n.jpg?stp=dst-jpg_e35_p1080x1080_sh0.08_tt6&_nc_ht=scontent-lga3-3.cdninstagram.com&_nc_cat=108&_nc_oc=Q6cZ2QEp9vICBLef8aFcSQLnxDSE07PweegjQWVxAEjsF3viOaoR1HoyRuzyowk9lUvd6xE&_nc_ohc=A9Vnn6BD9gEQ7kNvwGnu6Jj&_nc_gid=DoBPfmDs1aApTXm89VRysQ&edm=AOQ1c0wBAAAA&ccb=7-5&ig_cache_key=MzgyMDQ0ODAyMTMyNzQ1MTk3NA%3D%3D.3-ccb7-5&oh=00_AfwUVJoY3Yd2_SqXa6aRRaHckwDbH3UdA7mKFTK4GtLpvA&oe=69BD87A1&_nc_sid=8b3546, https://scontent-lga3-1.cdninstagram.com/v/t51.82787-15/621140438_18549981844038718_7563757944981249614_n.jpg?stp=dst-jpg_e35_p1080x1080_sh0.08_tt6&_nc_ht=scontent-lga3-1.cdninstagram.com&_nc_cat=110&_nc_oc=Q6cZ2QEp9vICBLef8aFcSQLnxDSE07PweegjQWVxAEjsF3viOaoR1HoyRuzyowk9lUvd6xE&_nc_ohc=OjhupMj_GMgQ7kNvwHI3Dn6&_nc_gid=DoBPfmDs1aApTXm89VRysQ&edm=AOQ1c0wBAAAA&ccb=7-5&ig_cache_key=MzgxNTkzODQ1Mzc3NjEwMTk4OQ%3D%3D.3-ccb7-5&oh=00_Afz8EbtHIjnVGhJX7h5lrH5gKu6xthjvRJ1zVDsxLgzYmQ&oe=69BD913C&_nc_s | Z17: https://scontent-lga3-2.cdninstagram.com/o1/v/t16/f2/m69/AQOqiwPGEyxXOlzpCZJZf76aCX1laVtmm5767vlcIUnXAV4COi4rj59sFske8KcBRnnRDUD3jDZC3x1bb9biEUDs.mp4?strext=1&_nc_cat=107&_nc_sid=5e9851&_nc_ht=scontent-lga3-2.cdninstagram.com&_nc_ohc=k0bw0_oPCGoQ7kNvwEanhDX&efg=eyJ2ZW5jb2RlX3RhZyI6Inhwdl9wcm9ncmVzc2l2ZS5JTlNUQUdSQU0uQ0xJUFMuQzMuNzIwLmRhc2hfYmFzZWxpbmVfMV92MSIsInhwdl9hc3NldF9pZCI6MTc5NDg5ODgxNTMxMTk3MzQsImFzc2V0X2FnZV9kYXlzIjoyLCJ2aV91c2VjYXNlX2lkIjoxMDA5OSwiZHVyYXRpb25fcyI6MjYsInVybGdlbl9zb3VyY2UiOiJ3d3cifQ%3D%3D&ccb=17-1&_nc_gid=DoBPfmDs1aApTXm89VRysQ&_nc_ss=1a&_nc_zt=28&vs=9c56233f6625e2e7&_nc_vs=HBksFQIYOnBhc3N0aHJvdWdoX2V2ZXJzdG9yZS9HRFEza1NhTEVhb0hEdzhRQUljblV3akprQ2tjYnNwVEFRQUYVAALIARIAFQIYUWlnX3hwdl9wbGFjZW1lbnRfcGVybWFuZW50X3YyLzEwNEFGM0ZCRTAzNzVBOTY3OURDQTAxQTUzMUM2NkE3X2F1ZGlvX2Rhc2hpbml0Lm1wNBUCAsgBEgAoABgAGwKIB3VzZV9vaWwBMRJwcm9ncmVzc2l2ZV9yZWNpcGUBMRUAACbsj47vzqDiPxUCKAJDMywXQDru2RaHKwIYEmRhc2hfYmFzZWxpbmVfMV92MREAdf4HZeadAQA&oh=00_Afx5DH5eaz9DEzz_qjdsGgHskwVDHuDgcT1UjkP_b_Y3fw&oe=69BD8E21, https://scontent-lga3-2.cdninstagram.com/o1/v/t16/f2/m69/AQMT0QxMFGm9dP7QY7wRIzjWITAzui9PzdiAK7GKAdr_Mf9_y5dz-B5pE5Tq74fn3dAN5FDmjCTZySt-TcqbjU7c.mp4?strext=1&_nc_cat=105&_nc_sid=5e9851&_nc_ht=scontent-lga3-2.cdninstagram.com&_nc_ohc=e9073KoYXfEQ7kNvwHmEoT0&efg=eyJ2ZW5jb2RlX3RhZyI6Inhwdl9wcm9ncmVzc2l2ZS5JTlNUQUdSQU0uQ0FST1VTRUxfSVRFTS5DMy43MjAuZGFzaF9iYXNlbGluZV8xX3YxIiwieHB2X2Fzc2V0X2lkIjoxNzk0NjEzNjkzODExNDAwNiwiYXNzZXRfYWdlX2RheXMiOjE2LCJ2aV91c2VjYXNlX2lkIjoxMDE0NiwiZHVyYXRpb25fcyI6OCwidXJsZ2VuX3NvdXJjZSI6Ind3dyJ9&ccb=17-1&_nc_gid=DoBPfmDs1aApTXm89VRysQ&_nc_ss=1a&_nc_zt=28&vs=a82f255f90d069dc&_nc_vs=HBkcFQIYOnBhc3N0aHJvdWdoX2V2ZXJzdG9yZS9HR0FWUFNacks0bWhCd1FEQVAxNGZmUVNubXd2YnNwVEFRQUYVAALIARIAKAAYABsCiAd1c2Vfb2lsATEScHJvZ3Jlc3NpdmVfcmVjaXBlATEVAAAmrK_L1NP64D8VAigCQzMsF0AgmZmZmZmaGBJkYXNoX2Jhc2VsaW5lXzFfdjERAHXuB2XEngEA&oh=00_AfzG2pF-R6n0Ic1oYgP_k10DjxOZerohCGrGrnhOfu_8yg&oe=69BD8AA3, https://scontent-lga3-3.cdninstagram.com/o1/v/t16/f2/m69/AQNcQFdUAPZgaDyB40K33x37UNXOPe7WCB6wL_VMbqa02ecK7zl6zLr6qwFU7LE98iTxwhQDiZVeKWTYtkL01SxA.mp4?strext=1&_nc_cat=108&_nc_sid=5e9851&_nc_ht=scontent-lga3-3.cdninstagram.com&_nc_ohc=NhoeljohfNUQ7kNvwGXeYc9&efg=eyJ2ZW5jb2RlX3RhZyI6Inhwdl9wcm9ncmVzc2l2ZS5JTlNUQUdSQU0uQ0FST1VTRUxfSVRFTS5DMy43MjAuZGFzaF9iYXNlbGluZV8xX3YxIiwieHB2X2Fzc2V0X2lkIjoxNzk0NjEzNjk1OTExNDAwNiwiYXNzZXRfYWdlX2RheXMiOjE2LCJ2aV91c2VjYXNlX2lkIjoxMDE0NiwiZHVyYXRpb25fcyI6MTAsInVybGdlbl9zb3VyY2UiOiJ3d3cifQ%3D%3D&ccb=17-1&_nc_gid=DoBPfmDs1aApTXm89VRysQ&_nc_ss=1a&_nc_zt=28&vs=623e8e7387475e5b&_nc_vs=HBkcFQIYOnBhc3N0aHJvdWdoX2V2ZXJzdG9yZS9HRnZ2V2laMk9YYi1pVHdGQU5iLUExWHMxdzkxYnNwVEFRQUYVAALIARIAKAAYABsCiAd1c2Vfb2lsATEScHJvZ3Jlc3NpdmVfcmVjaXBlATEVAAAmrOzO6NP64D8VAigCQzMsF0Ak3bItDlYEGBJkYXNoX2Jhc2VsaW5lXzFfdjERAHXuB2XEngEA&oh=00_AfyED6QFfjtp8YgzUYJYjtQdc80Fg0Eu8m46dOsp2sic7g&oe=69BDA434, https://scontent-lga3-3.cdninstagram.com/o1/v/t16/f2/m69/AQOz3Sda5XmRnDybDXluvVIHefYuOX-UyQDdYg3z6x20I66iBKKguYmx1KqWDvIQZtbePyq3IRI5L03fHrXBGnu0.mp4?strext=1&_nc_cat=108&_nc_sid=5e9851&_nc_ht=scontent-lga3-3.cdninstagram.com&_nc_ohc=0HeidD7PbMMQ7kNvwG63Cm6&efg=eyJ2ZW5jb2RlX3RhZyI6Inhwdl9wcm9ncmVzc2l2ZS5JTlNUQUdSQU0uQ0FST1VTRUxfSVRFTS5DMy43MjAuZGFzaF9iYXNlbGluZV8xX3YxIiwieHB2X2Fzc2V0X2lkIjoxNzk0NjEzNjk3NzExNDAwNiwiYXNzZXRfYWdlX2RheXMiOjE2LCJ2aV91c2VjYXNlX2lkIjoxMDE0NiwiZHVyYXRpb25fcyI6MjAsInVybGdlbl9zb3VyY2UiOiJ3d3cifQ%3D%3D&ccb=17-1&_nc_gid=DoBPfmDs1aApTXm89VRysQ&_nc_ss=1a&_nc_zt=28&vs=48db25b055160cf1&_nc_vs=HBkcFQIYOnBhc3N0aHJvdWdoX2V2ZXJzdG9yZS9HQ3p3WGlhaG9uT0pwblFPQUJFTFZfbmxuUWN3YnNwVEFRQUYVAALIARIAKAAYABsCiAd1c2Vfb2lsATEScHJvZ3Jlc3NpdmVfcmVjaXBlATEVAAAmrI7k-dP64D8VAigCQzMsF0A0szMzMzMzGBJkYXNoX2Jhc2VsaW5lXzFfdjERAHXuB2XEngEA&oh=00_AfwtQ1zDpUx0fAResuYMNQ2W-H1NQfq0AgqWVKqGDxhVoA&oe=69BDAAC4 | AA17: 56 | AB17: 3 | AC17: 46097 | AD17: loupethis | AE17: collector_page | AF17: https://www.instagram.com/rhinococktails
A18: mr.antik71 | B18: instagram | C18: Ramazan Kahraman | D18: Tarihi geleceğe taşı mutlu ol 🥰 | E18: 1632 | F18: 3544 | G18: 32 | H18: FALSE | I18: FALSE | L18: https://scontent-sjc3-1.cdninstagram.com/v/t51.82787-19/649232063_18035445476600933_211024051870618031_n.jpg?stp=dst-jpg_e0_s150x150_tt6&efg=eyJ2ZW5jb2RlX3RhZyI6InByb2ZpbGVfcGljLmRqYW5nby4xMDgwLmMyIn0&_nc_ht=scontent-sjc3-1.cdninstagram.com&_nc_cat=105&_nc_oc=Q6cZ2QFT9Arb8QFyyYmN0gP59YGckqX_BIfhDlqt0dsW3sBvKMj6eQZzJRE8Do-SFG36DtY&_nc_ohc=x2jy5I-sQTsQ7kNvwEnZ2um&_nc_gid=hKcJC6OWIKdq3M2hUaMJjQ&edm=AOQ1c0wBAAAA&ccb=7-5&oh=00_Afxdw_AHcrJiKYaP7yacuvWGtLhhN2vjvZ5md4Z8jNmLJg&oe=69BD9A01&_nc_sid=8b3546 | O18: 0.0163 | P18: 🔥🔥🔥 1950 Japon Denon GS Vintage çakmak. Gümüş kaplama ağır ve el oyması kasa ile tarihini yansıtan bir eser. Fiyatı 5000 TL 🔥🔥🔥 | 🔥🔥🔥 1970 Almanya 🇩🇪 İbelo İbelight benzinli Vintage çakmak. Zarif yapısı estetik görüntüsüyle Tarihe ışık tutmaya devam ediyor. Komple aleminyum blok. Özel bir ürün mükemmel kondisyon koleksiyonluk bir eser. Fiyatı 5500 TL 🔥🔥🔥 | 🔥🔥🔥 1970 İsviçre OMAX Otomatik Vintage Çakmak. Nadide bir eser tıkır tıkır zamanın içinden gelen güzellik. Kahve tonunda 17 kristal mükemmel kondisyon. Fiyatı 5000 TL 🔥🔥🔥 | ⌚️ 1970 Orijinal Seiko 5. Otomatik dakik tıkır tıkır zamanın içinden bir ürün. Kalitesi zerafeti sağlamlığı erkeğin yakışıklısı. Mükemmel kondisyon Fiyat 5500 TL ⌚️ | 🔥🔥🔥 1930 Fransa 🇫🇷 Paris Benzinli MD. Mükemmel kondisyonu yılan derisi giydirme koleksiyon defterinde sergilenen bu şaheser el değiştirmeye hazır. Peki siz hazırmısınız ? Fiyat 7500 TL 🔥🔥🔥 | 🔥🔥🔥 O bir 1970 Japon Rolstar benzinli krom çakmak. Fiyatı 2500 TL 🔥🔥🔥 | 🔥🔥🔥O bir Fransız Benzinli MD. Tarihin tozlu sayfalarından günümüze kadar ulaşan bir eser. 1930’lar timsah 🐊 derisi giydirme özel bir çakmak. Koleksiyonunuza değer katacak Fiyat 5500 TL 🔥🔥🔥 | 🔥🔥🔥1970 Almanya yapımı Rowenta Magirus çakmak. Harika kondisyon çalışır vaziyette kaya gibi sağlam minibüs gibi hizmetkar. Nadir bulunan bir eser. Fiyatı 5000 TL 🔥🔥🔥 | ⌚️ 1960 İsviçre Hislon kurmalı kol saati. Zamanın ötesinde bir çılgınlık. Mükemmel kondisyon. Fiyat 8000 TL ⌚️ | ⌚️ İsviçre 1960 Nacar kol saati. Tarihin akışını durduramazsın!!! Kurmalı Nadide bir eser. Emsallerinin en yakışıklısı. Deri kordon mükemmel kondisyon. Fiyat 10.000 TL ⌚️ | ⌚️1960 İsviçre Hislon marka kol saati. Orijinal otomatik ve çil durumda mükemmel kurmalı bir dönem eseri. Daha temizi yok. Evladiyelik dededen toruna zamanın nasıl aktığını yaşamak isteyenlere. Fiyat 15.000 TL ⌚️ | 🔥🔥🔥 Vintage Deri Masa çakmağı sigaralık küllük üçü bir arada. Dönemini yansıtan dekor. Koleksiyonluk. Fiyat 3500 TL 🔥🔥🔥 | S18: https://instagram.com/p/DV3OsX0CM1b, https://instagram.com/p/DV27iCdCM-p, https://instagram.com/p/DV26KCbiMAc, https://instagram.com/p/DV5v2y4iD8e, https://instagram.com/p/DV5tfGEiAb9, https://instagram.com/p/DV5sux_iJ2b, https://instagram.com/p/DV5rMa8iLw9, https://instagram.com/p/DV2zJpOCHGV, https://instagram.com/p/DVt2fM7iMwW, https://instagram.com/p/DVt1RkSiN7a, https://instagram.com/p/DVtzmeKiMC5, https://instagram.com/p/DVoLnGmCF0Y | T18: 36, 36, 36, 18, 12, 15, 14, 39, 36, 28, 25, 22 | U18: 0, 0, 0, 0, 0, 0, 0, 0, 2, 0, 0, 0 | V18: 2026-03-14, 2026-03-14, 2026-03-14, 2026-03-15, 2026-03-15, 2026-03-15, 2026-03-15, 2026-03-14, 2026-03-10, 2026-03-10, 2026-03-10, 2026-03-08 | X18: Video, Video, Video, Video, Video, Video, Video, Video, Video, Video, Video, Video | Z18: https://scontent-sjc3-1.cdninstagram.com/o1/v/t16/f2/m69/AQOJK5ZQJ6KTW-xuxaAC5lKWZGen-fF6fIx3hZLWDo-o3durGGYkOKzjQ1yDUVHuXkia9R1cfpHLtFxbSDNrn_pL.mp4?strext=1&_nc_cat=100&_nc_sid=5e9851&_nc_ht=scontent-sjc3-1.cdninstagram.com&_nc_ohc=gcmN3kfmVogQ7kNvwFd3q4r&efg=eyJ2ZW5jb2RlX3RhZyI6Inhwdl9wcm9ncmVzc2l2ZS5JTlNUQUdSQU0uQ0xJUFMuQzMuNzIwLmRhc2hfYmFzZWxpbmVfMV92MSIsInhwdl9hc3NldF9pZCI6MTgwMzU5MzMwODQ2MDA5MzMsImFzc2V0X2FnZV9kYXlzIjoxLCJ2aV91c2VjYXNlX2lkIjoxMDA5OSwiZHVyYXRpb25fcyI6MTgsInVybGdlbl9zb3VyY2UiOiJ3d3cifQ%3D%3D&ccb=17-1&_nc_gid=hKcJC6OWIKdq3M2hUaMJjQ&_nc_ss=1a&_nc_zt=28&vs=5399069fdd3d49d4&_nc_vs=HBksFQIYOnBhc3N0aHJvdWdoX2V2ZXJzdG9yZS9HRUc0dlNaWW1yUFo1ZWdIQUd6ajZrSFdpWk1mYnNwVEFRQUYVAALIARIAFQIYUWlnX3hwdl9wbGFjZW1lbnRfcGVybWFuZW50X3YyLzQyNDFCNEE0QUZCRjdENUFEQzk1QkIzQjM1OTkwMThBX2F1ZGlvX2Rhc2hpbml0Lm1wNBUCAsgBEgAoABgAGwKIB3VzZV9vaWwBMRJwcm9ncmVzc2l2ZV9yZWNpcGUBMRUAACbKqZqLveWJQBUCKAJDMywXQDL3S8an754YEmRhc2hfYmFzZWxpbmVfMV92MREAdf4HZeadAQA&oh=00_AfwqyehjcQhSXIXwEZJ2jznwIR_u-XfggYc2xSLxH2TXXQ&oe=69BD95B4, https://scontent-sjc3-1.cdninstagram.com/o1/v/t16/f2/m69/AQMhKRYX215MIgUO7-vZJAf8XVCZfKlb559kN65Ijlmq8fCfqxHZLTvnFirmALigWBw2EoWCIHnlKr6gBoz-xd-j.mp4?strext=1&_nc_cat=110&_nc_sid=5e9851&_nc_ht=scontent-sjc3-1.cdninstagram.com&_nc_ohc=sfDfzf8n5wUQ7kNvwHZRT5z&efg=eyJ2ZW5jb2RlX3RhZyI6Inhwdl9wcm9ncmVzc2l2ZS5JTlNUQUdSQU0uQ0xJUFMuQzMuNzIwLmRhc2hfYmFzZWxpbmVfMV92MSIsInhwdl9hc3NldF9pZCI6MTgwMzU5MTEyMzU2MDA5MzMsImFzc2V0X2FnZV9kYXlzIjoyLCJ2aV91c2VjYXNlX2lkIjoxMDA5OSwiZHVyYXRpb25fcyI6MjksInVybGdlbl9zb3VyY2UiOiJ3d3cifQ%3D%3D&ccb=17-1&_nc_gid=hKcJC6OWIKdq3M2hUaMJjQ&_nc_ss=1a&_nc_zt=28&vs=99d2f69413be0d84&_nc_vs=HBksFQIYOnBhc3N0aHJvdWdoX2V2ZXJzdG9yZS9HSjJLdHlheDJWMU9XT1lLQUJBVHVEWlRtQUZoYnNwVEFRQUYVAALIARIAFQIYUWlnX3hwdl9wbGFjZW1lbnRfcGVybWFuZW50X3YyLzc4NDZBMTM3ODYyNzMxRDBDRkRBNjFBRTVGNzcxQzhBX2F1ZGlvX2Rhc2hpbml0Lm1wNBUCAsgBEgAoABgAGwKIB3VzZV9vaWwBMRJwcm9ncmVzc2l2ZV9yZWNpcGUBMRUAACbKiLCmmuSJQBUCKAJDMywXQD2ZmZmZmZoYEmRhc2hfYmFzZWxpbmVfMV92MREAdf4HZeadAQA&oh=00_AfzJ_7aFYjXcgNvnxos9JHTLodnyi_1ZiRRaugFFfGm_hg&oe=69BDA46A, https://scontent-sjc6-1.cdninstagram.com/o1/v/t16/f2/m69/AQO0_adISSuf7clfeFtD9vOXStViCZKKJJIr3ReDQpxy0m5jdeDHC-iZlhTo4pY28vyqwZv7rwpnLMOc6BP2Re5s.mp4?strext=1&_nc_cat=107&_nc_sid=5e9851&_nc_ht=scontent-sjc6-1.cdninstagram.com&_nc_ohc=QbPxo9Y5v-IQ7kNvwHGIW4F&efg=eyJ2ZW5jb2RlX3RhZyI6Inhwdl9wcm9ncmVzc2l2ZS5JTlNUQUdSQU0uQ0xJUFMuQzMuNzIwLmRhc2hfYmFzZWxpbmVfMV92MSIsInhwdl9hc3NldF9pZCI6MTgwMzU5MDk3ODA2MDA5MzMsImFzc2V0X2FnZV9kYXlzIjoyLCJ2aV91c2VjYXNlX2lkIjoxMDA5OSwiZHVyYXRpb25fcyI6MTksInVybGdlbl9zb3VyY2UiOiJ3d3cifQ%3D%3D&ccb=17-1&_nc_gid=hKcJC6OWIKdq3M2hUaMJjQ&_nc_ss=1a&_nc_zt=28&vs=5cd40a7fe15d40ac&_nc_vs=HBksFQIYOnBhc3N0aHJvdWdoX2V2ZXJzdG9yZS9HRmJ4dnlaN2JmdUN1MWtEQUR1a0V3clJYYUYwYnNwVEFRQUYVAALIARIAFQIYUWlnX3hwdl9wbGFjZW1lbnRfcGVybWFuZW50X3YyL0MzNDQwNzAwNjhEQjE5NDk4NDRERkVGQ0QwMTQyNkIzX2F1ZGlvX2Rhc2hpbml0Lm1wNBUCAsgBEgAoABgAGwKIB3VzZV9vaWwBMRJwcm9ncmVzc2l2ZV9yZWNpcGUBMRUAACbK4eO6j-SJQBUCKAJDMywXQDOIcrAgxJwYEmRhc2hfYmFzZWxpbmVfMV92MREAdf4HZeadAQA&oh=00_Afz6X3xde8tbHgVORmOxMJYesTNdN1kskaGeWxQZ1T7x2g&oe=69BD8F11, https://scontent-sjc3-1.cdninstagram.com/o1/v/t16/f2/m69/AQPIG-EM-_7N5CGI5RUEk-GyPA3c4FlctdP4BEJOsuG26x0dSWlTYOXSAGRSkazBQ4lQ9hbJ0Uc0zPFQrb42JdQ1.mp4?strext=1&_nc_cat=110&_nc_sid=5e9851&_nc_ht=scontent-sjc3-1.cdninstagram.com&_nc_ohc=Q-ewcSkUfUMQ7kNvwFJBa3X&efg=eyJ2ZW5jb2RlX3RhZyI6Inhwdl9wcm9ncmVzc2l2ZS5JTlNUQUdSQU0uQ0xJUFMuQzMuNzIwLmRhc2hfYmFzZWxpbmVfMV92MSIsInhwdl9hc3NldF9pZCI6MTgwMzYxMjIwMTg2MDA5MzMsImFzc2V0X2FnZV9kYXlzIjowLCJ2aV91c2VjYXNlX2lkIjoxMDA5OSwiZHVyYXRpb25fcyI6MjAsInVybGdlbl9zb3VyY2UiOiJ3d3cifQ%3D%3D&ccb=17-1&_nc_gid=hKcJC6OWIKdq3M2hUaMJjQ&_nc_ss=1a&_nc_zt=28&vs=d2ff98f67f561afc&_nc_vs=HBksFQIYOnBhc3N0aHJvdWdoX2V2ZXJzdG9yZS9HTm5RMnliV1JKcmZmQk1GQUNGeE16aHlmakJJYnNwVEFRQUYVAALIARIAFQIYUWlnX3hwdl9wbGFjZW1lbnRfcGVybWFuZW50X3YyLzM2NDY2N0NGMjkwNjBDNzUxQjRDOTYzOEE2MTZGRkExX2F1ZGlvX2Rhc2hpbml0Lm1wNBUCAsgBEgAoABgAGwKIB3VzZV9vaWwBMRJwcm9ncmVzc2l2ZV9yZWNpcGUBMRUAACbK39rgvPCJQBUCKAJDMywXQDQAAAAAAAAYEmRhc2hfYmFzZWxpbmVfMV92MREAdf4HZeadAQA&oh=00_AfxT7Z9q94rSJDkiyj5REuiRqwPIbYhiWNC2beYfpROgPg&oe=69BDA66E, https://scontent-sjc3-1.cdninstagram.com/o1/v/t16/f2/m69/AQOxYmKfaXIH3q4860zd2ITNqSTF6rmLt0EIiEeVdJyyIQAExFkwpt1jLvch47mgA1McwWR1EKTToee1JGo0trrB.mp4?strext=1&_nc_cat=106&_nc_sid=5e9851&_nc_ht=scontent-sjc3-1.cdninstagram.com&_nc_ohc=bfCH8rBNP08Q7kNvwFYzYKP&efg=eyJ2ZW5jb2RlX3RhZyI6Inhwdl9wcm9ncmVzc2l2ZS5JTlNUQUdSQU0uQ0xJUFMuQzMuNzIwLmRhc2hfYmFzZWxpbmVfMV92MSIsInhwdl9hc3NldF9pZCI6MTgwMzYxMTk0NDc2MDA5MzMsImFzc2V0X2FnZV9kYXlzIjowLCJ2aV91c2VjYXNlX2lkIjoxMDA5OSwiZHVyYXRpb25fcyI6MjgsInVybGdlbl9zb3VyY2UiOiJ3d3cifQ%3D%3D&ccb=17-1&_nc_gid=hKcJC6OWIKdq3M2hUaMJjQ&_nc_ss=1a&_nc_zt=28&vs=429ae775d245db83&_nc_vs=HBksFQIYOnBhc3N0aHJvdWdoX2V2ZXJzdG9yZS9HUFNpRUNadFRSSnNqTVpjQVBCUGNGZGNrN0lOYnNwVEFRQUYVAALIARIAFQIYUWlnX3hwdl9wbGFjZW1lbnRfcGVybWFuZW50X3YyL0MzNDFENjFEOTJFRkZBRDRCRkMzRjk3MDc2RTM4Mzg3X2F1ZGlvX2Rhc2hpbml0Lm1wNBUCAsgBEgAoABgAGwKIB3VzZV9vaWwBMRJwcm9ncmVzc2l2ZV9yZWNpcGUBMRUAACbK_OfMqfCJQBUCKAJDMywXQDwAAAAAAAAYEmRhc2 | AA18: 26 | AB18: 0 | AC18: 46097 | AD18: loupethis | AE18: collector_page | AF18: https://www.instagram.com/mr.antik71
A19: chronohawk.watch | B19: instagram | D19: Army Aviation meets Horology Blackhawks + wrist checks + Flightline Stories ⌚️Watches as Gear, 🚁Hawks as Heritage UH60M Instructor Pilot | E19: 1248 | F19: 944 | G19: 52 | H19: FALSE | I19: FALSE | J19: Personal blog | L19: https://scontent-lax3-2.cdninstagram.com/v/t51.82787-19/540709338_17847780360555591_8701181556634594324_n.jpg?stp=dst-jpg_e0_s150x150_tt6&efg=eyJ2ZW5jb2RlX3RhZyI6InByb2ZpbGVfcGljLmRqYW5nby4xMDI0LmMyIn0&_nc_ht=scontent-lax3-2.cdninstagram.com&_nc_cat=103&_nc_oc=Q6cZ2QHYq3YPkhjBOs_UXhJP1MwHme6f5xjiGj4EgSkQeIyX9defgKM5E2iCh7yhBnR_WeU&_nc_ohc=-4Rhsr14f2MQ7kNvwET-Q26&_nc_gid=SmOsQQvgdkp0X11DBMTqug&edm=AOQ1c0wBAAAA&ccb=7-5&oh=00_AfwuifNxf9NC6pm3AW-XCvwiHFVDvN4yhcsNi2EIb4jBJw&oe=69BDABDC&_nc_sid=8b3546 | O19: 0.089 | P19: Some watches tell time. Some watches tell a story. Sangin Instruments Kinetic II Titanium on the wrist while the Black Hawk sits on the ramp, waiting to spin up for tonight’s mission. A watch built by veterans for people who still operate in the environments tool watches were originally made for. | A Man and His Watch. The stories in this book belong to explorers, soldiers, pilots, musicians, and celebrities. Different watches. Same idea. A watch becomes meaningful because of what you do while wearing it. While my story is far from over, my watches keep doing what they’re supposed to do. | Another night in the Hawk. Black dial @chriswardlondon Sealander GMT 39mm on a @watchesofespionage NATO strap. @rayban sunglasses, arcpro edc flashlight, and @spartanblades1 knife. Simple. Functional. Exactly how a cockpit tool watch should be. #pilotwatch #blackhawkpilot #aviationstyle #army #w | Swipe for that Lume Shot 👀 ➡️➡️➡️ Been a little quiet on here lately. Does not mean the flying stopped. Most days ended well after shutdown. Hours in the seat, rotors turning, missions getting done. Some days it doesn’t stop. On the wrist today is the Rolex Titanium Yacht-Master. RLX titanium | Valentine’s Day done right. Matching moments, matching mindsets. His and hers @henryarcherwatches on the wrist, built for everyday wear and the memories that matter most. His: øhav meteroite lunaris 40mm Hers: vesterhav ultraviolet 38mm #pilotwatch #HenryArcher #valentinesday #WatchFam #hisandher | (SWIPE->) After a long week in the cockpit, the checklists, and the noise, you earn the quiet moments. Rolex Submariner. Vintage Cartier. Christian Louboutin red bottoms. Sunset, cocktails, and a Valentine’s weekend done right. #redbottoms #PilotLife #Rolex #pilotwatch #cartier @christianloubou | First EDC post. Figured it was time. This is what I actually carry everyday. Not optimized. Just the gear that earns a spot every day. Usually my watch changes based on my mood, and what I have going on but today it’s the @tudorwatch Pelagos FXD GMT. It’s light, and its lume legibility is second t | In a game where ounces equal pounds, titanium matters. Built rugged. Built to take a beating. Gunnery day as an instructor pilot with the Omega “No Time To Die” on the wrist. Tools you trust when it counts. Patch courtesy of @watcheswinwars #pilotwatch #omegaseamaster #instructorpilot #titaniumwa | Gunnery live fire. Real consequences. I trust the Explorer II for the same reason I trust good crews and good systems. It just works. There’s a reason why watches win wars. Office flag by @watcheswinwars #pilotwatch #WatchesWinWars #RolexExplorerII #MilitaryAviation #ToolWatch | The mission starts on the map, not in the air. Planning is work. Flying is execution. Omega No Time To Die keeping time between both. #omega #army #AviationLife #pilotwatch #toolwatch | No date. No excuses. Just a dive watch built to work when it matters. And enjoying my @watcheswinwars patches that just came in #pilotwatch #army #omega #helicopterpilot #lowlevel | Evenings like this are worth slowing down for. #rolex #watchlife #quietmoments #toolwatch #pilotwatch | Q19: #pilotwatch, #blackhawkpilot, #aviationstyle, #army, #w, #HenryArcher, #valentinesday, #WatchFam, #hisandher, #redbottoms, #PilotLife, #Rolex, #cartier, #omegaseamaster, #instructorpilot, #titaniumwa, #WatchesWinWars, #RolexExplorerII, #MilitaryAviation, #ToolWatch, #omega, #AviationLife, #toolwatch, #helicopterpilot, #lowlevel, #rolex, #watchlife, #quietmoments | R19: @watchesofespionage, @chriswardlondon, @rayban, @spartanblades1, @henryarcherwatches, @christianlouboutin, @rolex, @cartier, @omnihotels, @tudorwatch, @reformcarry, @watcheswinwars | S19: https://instagram.com/p/DVt8bovgRyZ, https://instagram.com/p/DVqbdmuABoY, https://instagram.com/p/DVhDtv0gZEP, https://instagram.com/p/DVdjA3_gGnt, https://instagram.com/p/DUwf7CGAQRn, https://instagram.com/p/DUt7ZozDPgx, https://instagram.com/p/DUTQjOlgNYu, https://instagram.com/p/DUGaxCykdBR, https://instagram.com/p/DUEbqc9AXO3, https://instagram.com/p/DT0RmYzgFiL, https://instagram.com/p/DTvJuuYgLjr, https://instagram.com/p/DTtIBACAdQB | T19: 160, 114, 141, 150, 89, 137, 104, 67, 101, 68, 81, 100 | U19: 3, 1, 0, 1, 1, 3, 1, 2, 1, 3, 4, 1 | V19: 2026-03-10, 2026-03-09, 2026-03-05, 2026-03-04, 2026-02-15, 2026-02-14, 2026-02-03, 2026-01-29, 2026-01-28, 2026-01-22, 2026-01-20, 2026-01-19 | X19: Image, Image, Image, Sidecar, Image, Sidecar, Image, Sidecar, Image, Image, Image, Image | Y19: https://scontent-lax3-2.cdninstagram.com/v/t51.82787-15/649465884_17872757478555591_7588256338906703599_n.jpg?stp=dst-jpg_e35_p1080x1080_sh0.08_tt6&_nc_ht=scontent-lax3-2.cdninstagram.com&_nc_cat=103&_nc_oc=Q6cZ2QHYq3YPkhjBOs_UXhJP1MwHme6f5xjiGj4EgSkQeIyX9defgKM5E2iCh7yhBnR_WeU&_nc_ohc=9WrcHmU6sAQQ7kNvwH7stUl&_nc_gid=SmOsQQvgdkp0X11DBMTqug&edm=AOQ1c0wBAAAA&ccb=7-5&ig_cache_key=Mzg0OTk5OTAzODQzNDg0MzgwMQ%3D%3D.3-ccb7-5&oh=00_Afxa9jPxKtku9Xjtl3rSbMFspMccdlP1oJIp0MadpX3x9g&oe=69BD8503&_nc_sid=8b3546, https://scontent-lax3-2.cdninstagram.com/v/t51.82787-15/642784085_17872527021555591_94730415683475430_n.jpg?stp=dst-jpg_e35_p1080x1080_sh0.08_tt6&_nc_ht=scontent-lax3-2.cdninstagram.com&_nc_cat=103&_nc_oc=Q6cZ2QHYq3YPkhjBOs_UXhJP1MwHme6f5xjiGj4EgSkQeIyX9defgKM5E2iCh7yhBnR_WeU&_nc_ohc=c3eYxGzXxTMQ7kNvwGUiUiG&_nc_gid=SmOsQQvgdkp0X11DBMTqug&edm=AOQ1c0wBAAAA&ccb=7-5&ig_cache_key=Mzg0OTAwOTYxMzIzNjA4MzIyNA%3D%3D.3-ccb7-5&oh=00_Afyyi6DWbZhKntmvHwqIhzsybGOfjpRnknElNsYbA6-5xg&oe=69BD901C&_nc_sid=8b3546, https://scontent-lax3-2.cdninstagram.com/v/t51.82787-15/641313684_17871868542555591_567261576565998011_n.jpg?stp=dst-jpg_e35_p1080x1080_sh0.08_tt6&_nc_ht=scontent-lax3-2.cdninstagram.com&_nc_cat=103&_nc_oc=Q6cZ2QHYq3YPkhjBOs_UXhJP1MwHme6f5xjiGj4EgSkQeIyX9defgKM5E2iCh7yhBnR_WeU&_nc_ohc=PO-Uu25ocPwQ7kNvwGedT3b&_nc_gid=SmOsQQvgdkp0X11DBMTqug&edm=AOQ1c0wBAAAA&ccb=7-5&ig_cache_key=Mzg0NjM3MTg5NDYxMzg3MjkxMQ%3D%3D.3-ccb7-5&oh=00_AfyBhzAUS8cWgdfD1vAwo507wFIkx0APOQ1GxrU6eB1FYA&oe=69BD8373&_nc_sid=8b3546, https://scontent-lax3-2.cdninstagram.com/v/t51.82787-15/641778934_17871627453555591_4137911794880138989_n.jpg?stp=dst-jpg_e35_p1080x1080_sh0.08_tt6&_nc_ht=scontent-lax3-2.cdninstagram.com&_nc_cat=103&_nc_oc=Q6cZ2QHYq3YPkhjBOs_UXhJP1MwHme6f5xjiGj4EgSkQeIyX9defgKM5E2iCh7yhBnR_WeU&_nc_ohc=mRtGUeoHDJcQ7kNvwF2NgHn&_nc_gid=SmOsQQvgdkp0X11DBMTqug&edm=AOQ1c0wBAAAA&ccb=7-5&ig_cache_key=Mzg0NTM4MTUyNjgzNzU4ODQxMQ%3D%3D.3-ccb7-5&oh=00_Afz87v98QfasYHvQ8NzfyU8LTNLrJQ3efgdiOEpvIR6dgA&oe=69BD90A8&_nc_sid=8b3546, https://scontent-lax3-2.cdninstagram.com/v/t51.82787-15/641778934_17871627453555591_4137911794880138989_n.jpg?stp=dst-jpg_e35_p1080x1080_sh0.08_tt6&_nc_ht=scontent-lax3-2.cdninstagram.com&_nc_cat=103&_nc_oc=Q6cZ2QHYq3YPkhjBOs_UXhJP1MwHme6f5xjiGj4EgSkQeIyX9defgKM5E2iCh7yhBnR_WeU&_nc_ohc=mRtGUeoHDJcQ7kNvwF2NgHn&_nc_gid=SmOsQQvgdkp0X11DBMTqug&edm=AOQ1c0wBAAAA&ccb=7-5&ig_cache_key=Mzg0NTM4MTUyNjgzNzU4ODQxMQ%3D%3D.3-ccb7-5&oh=00_Afz87v98QfasYHvQ8NzfyU8LTNLrJQ3efgdiOEpvIR6dgA&oe=69BD90A8&_nc_sid=8b3546, https://scontent-lax3-2.cdninstagram.com/v/t51.82787-15/641788733_17871627438555591_8359179565522793499_n.jpg?stp=dst-jpg_e35_p1080x1080_sh0.08_tt6&_nc_ht=scontent-lax3-2.cdninstagram.com&_nc_cat=103&_nc_oc=Q6cZ2QHYq3YPkhjBOs_UXhJP1MwHme6f5xjiGj4EgSkQeIyX9defgKM5E2iCh7yhBnR_WeU&_nc_ohc=SMFqIskQhnkQ7kNvwFfy8vE&_nc_gid=SmOsQQvgdkp0X11DBMTqug&edm=AOQ1c0wBAAAA&ccb=7-5&ig_cache_key=Mzg0NTM4MTUyNTQ3ODU3Mzg0OA%3D%3D.3-ccb7-5&oh=00_AfyGLQnJtWn9wHPDbix9LFfVD2_xdM6tfo2ZHJxK6DmBZQ&oe=69BD88F8&_nc_sid=8b3546, https://scontent-lax3-2.cdninstagram.com/v/t51.82787-15/632287320_17868946662555591_4460469820445504858_n.jpg?stp=dst-jpg_e35_p1080x1080_sh0.08_tt6&_nc_ht=scontent-lax3-2.cdninstagram.com&_nc_cat=103&_nc_oc=Q6cZ2QHYq3YPkhjBOs_UXhJP1MwHme6f5xjiGj4EgSkQeIyX9defgKM5E2iCh7yhBnR_WeU&_nc_ohc=mcwJDTGpjEIQ7kNvwGYnkf0&_nc_gid=SmOsQQvgdkp0X11DBMTqug&edm=AOQ1c0wBAAAA&ccb=7-5&ig_cache_key=MzgzMjcwMzY3OTAzMTQ3NzM1MQ%3D%3D.3-ccb7-5&oh=00_AfyrA21SiKe76X8iHFn-GKo97SeAN2uJbqfg99RegP04Cg&oe=69BD8C27&_nc_sid=8b3546, https://scontent-lax3-2.cdninstagram.com/v/t51.82787-15/632279080_17868779349555591_2953936846649156647_n.jpg?stp=dst-jpg_e35_p1080x1080_sh0.08_tt6&_nc_ht=scontent-lax3-2.cdninstagram.com&_nc_cat=103&_nc_oc=Q6cZ2QHYq3YPkhjBOs_UXhJP1MwHme6f5xjiGj4EgSkQeIyX9defgKM5E2iCh7yhBnR_WeU&_nc_ohc=Wij85vQisNUQ7kNvwEe4AME&_nc_gid=SmOsQQvgdkp0X11DBMTqug&edm=AOQ1c0wBAAAA&ccb=7-5&ig_cache_key=MzgzMTk3NzQyMjk4NzgxODI4OA%3D%3D.3-ccb7-5&oh=00_AfzsUFAIjynnIUUtYqwlQsVi6YIgYDOU79WM7bcGPjby9Q&oe=69BD9DF1&_nc_sid=8b3546, https://scontent-lax3-2.cdninstagram.com/v/t51.82787-15/632279080_17868779349555591_2953936846649156647_n.jpg?stp=dst-jpg_e35_p1080x1080_sh0.08_tt6&_nc_ht=scontent-lax3-2.cdninstagram.com&_nc_cat=103&_nc_oc=Q6cZ2QHYq3YPkhjBOs_UXhJP1MwHme6f5xjiGj4EgSkQeIyX9defgKM5E2iCh7yhBnR_WeU&_nc_ohc=Wij85vQisNUQ7kNvwEe4AME&_nc_gid=SmOsQQvgdkp0X11DBMTqug&edm=AOQ1c0wBAAAA&ccb=7-5&ig_cache_key=MzgzMTk3NzQyMjk4NzgxODI4OA%3D%3D.3-ccb7-5&oh=00_AfzsUFAIjynnIUUtYqwlQsVi6YIgYDOU79WM7bcGPjby9Q&oe=69BD9DF1&_nc_sid=8b3546, https://scontent-lax3-2.cdninstagram.com/v/t51.82787-15/630198638_17868779358555591_8364483952597121690_n.jpg?stp=dst-jpg_e35_p1080x1080_sh0.08_tt6&_nc_ht=scontent-lax3-2.cdninstagram.com&_nc_cat=103&_nc_oc=Q6cZ2QHYq3YPkhjBOs_UXhJP1MwHme6f5xjiGj4EgSkQeIyX9defgKM5E2iCh7yhBnR_WeU&_nc_ohc=XgMKatHOUeYQ7kNvwE0sR_u&_nc_gid=SmOsQQvgdkp0X11DBMTqug&edm=AOQ1c0wBAAAA&ccb=7-5&ig_cache_key=MzgzMTk3NzQyNDQ0NzQxNjUyOQ%3D%3D.3-ccb7-5&oh=00_AfwvKHp0kURx6o01ba1iQe_IGP95LMdHlK_AALH8y_bA-Q&o | AA19: 109 | AB19: 2 | AC19: 46097 | AD19: loupethis | AE19: collector_page | AF19: https://www.instagram.com/chronohawk.watch
A20: anbeanwatch | B20: instagram | C20: AnBeAnwatch | D20: Watch Lover ⌚️⌛️🕰️ Saat Sever - Hobi - Paylaşım Detaylar için Dm ✍️ Dolap Link ⬇️ | E20: 328 | F20: 638 | G20: 52 | H20: FALSE | I20: FALSE | J20: Personal blog | K20: https://link.dolap.com/1fwe8c | L20: https://scontent-iad3-1.cdninstagram.com/v/t51.82787-19/650644466_18038851670587845_2678982524041205972_n.jpg?stp=dst-jpg_e0_s150x150_tt6&efg=eyJ2ZW5jb2RlX3RhZyI6InByb2ZpbGVfcGljLmRqYW5nby4xMDgwLmMyIn0&_nc_ht=scontent-iad3-1.cdninstagram.com&_nc_cat=109&_nc_oc=Q6cZ2QEIz-E0Ih9sLOV7KGa83NmqJf7-90tn_Z2qmERv0e_qwIHJuFjP_cN3kdSpDbObOBo&_nc_ohc=-4TEi_ZWnOkQ7kNvwEUBE0A&_nc_gid=Cmq0dIyiMgU1ta5CTdbUTA&edm=AOQ1c0wBAAAA&ccb=7-5&oh=00_Afz2-ILHn55qgSFiL8t-e4AR7EIcY_RAAA46YVw3ZEZKsA&oe=69BD84CD&_nc_sid=8b3546 | O20: 0.0193 | P20: #watch #horology @anbeanwatch | Quantum Qmaster Otomatik ⌚️ Detaylı bilgi için Bio 👍 Dm ulaşın ✍️ @anbeanwatch #watch #saat #quantum Ürün Özellikleri Cinsiyet : Erkek Renk : Lacivert Kasa Malzemesi : Çelik Kordon Malzemesi : Silikon Marka : Quantum Tip : Kol Saati Su Geçirmezlik : 5 ATM Yaş Grubu : Yetişkin Takvim | Spinnaker Hull Kronograf ⌚️ Detaylı bilgi için Bio 👍 Dm ulaşın ✍️ @anbeanwatch #saat #watch #spinnaker Kasa Çapı: 42 mm Kasa Şekli: Kare Kasa Materyali: Çelik Kasa Rengi: Metalik Gri Kordon Materyali: Deri Kordon Rengi: Yeşil Kadran Rengi: Yeşil Kadran Işığı: Yok Çalışma Şekli: Analog | Momentus Turkuaz Otomatik⌚️ Detaylı bilgi için Bio 👍 Dm ✍️ @anbeanwatch #saat #watch #momentus Erkek MechaMaster Collection TM264T-10SS Otomatik Japon TMI NH34 Paslanmaz Çelik Yuvarlak 43 mm Çelik GMT Seramik Bezel Safir cam Suya Dayanıklılık : 10 ATM Çift Zaman Dilimi : Var K | G shock Solar / Bluetooth ⌚️ Detaylı bilgi için bio 👍 Dm ✍️ @anbeanwatch #watch #saat #casio #gshock 20 Bar Su Geçirmezlik Akıllı Telefon Bağlantısı Alarm Aydınlatma Bluetooth Darbelere Dayanıklılık Dünya Saatleri Güneş Enerjisi Günlük Kullanıma Uygun İnce Tasarım Kronometre Pil S | Calvine Klien Dress 44 mm ⌚️ Detaylı bilgi için Bio 👍 Dm ulaşın ✍️ @anbeanwatch #saat #saatler #ck #calvinklein Minimal çizgili gri kadran Swiss made kalitesi Pilli mekanizma Deri kordonlu Çelik kasa ve tokalı 43 mm kasa çapı 100 metre su geçirmezlik Tek saat | Buler De Luxe ⌚️ Automagnetic Small secont Nos kondisyon 36 mm Kasa Çapı Tepe , Kordon ve Toka After Sorunsuz zaman tutması var Deri kordonlu Orjinal kutusu ile verilecek Detaylı bilgi için Bio 👍 Dm ulaşın✍️ @anbeanwatch #saat #saatler #buler #automatic #vintage | Momentus Pembe -Siyah Panda kadran ⌚️ Detaylı bilgi için Bio👍 Dm ulaşın ✍️ @anbeanwatch #saat #saatler #momentus #panda Cinsiyet : ERKEK Kasa Çapı :41 MM Makine Tipi :PİLLİ Kayış Rengi : GÜMÜŞ Makine : ANALOG Kayış Tipi : ÇELİK Kadran Şekli :YUVARLAK Kadran Rengi : PEMBE Kasa Materyali : ÇE | Momentus Turuncu -Siyah renk uyumu Panda kadran ⌚️ Detaylı bilgi için Bio👍 Dm ulaşın ✍️ @anbeanwatch #saat #saatler #momentus #panda Cinsiyet : ERKEK Kasa Çapı :41 MM Makine Tipi :PİLLİ Kayış Rengi : GÜMÜŞ Makine : ANALOG Kayış Tipi : ÇELİK Kadran Şekli :YUVARLAK Kadran Rengi : TURUNCU Kasa | Momentus Panda Mat Cronograf ⌚️ Detaylı bilgi için Bio 👍 Dm ULAŞIN ✍️ @anbeanwatch #saat #momentus Kasa Çapı: : 46 mm Kasa Renk: : Metalik Kasa Materyali: : Çelik Kordon Renk: : Gun Çelik Kordon Materyali: Çelik Su Geçirmezlik: 3 ATM Cam Tipi: Mineral Cam Mekanizma: : Quartz Cam Şekl | Momentus Drives Otomatik Lacivert ⌚️ Detaylar için Bio 👍 Dm ULAŞIN ✍️ @anbeanwatch #saat #saatler #momentus #drives Kasa Çapı: : 43 mm Kasa Renk: : Siyah Kasa Materyali: : Çelik Kordon Renk: Siyah Kordon Materyali: Çelik Su Geçirmezlik: 10 ATM Takvim Cam Tipi: Kristal Mekanizma: Otomatik | Bulova Otomatik Open Heart ⌚️ Detaylı bilgi için Bio 👍 Dm ULAŞIN ✍️ @anbeanwatch #saat #bulova Görüntüleme Türü : Analog Özellikler : Işıklı Su Geçirmezlik Derinliği : 30 Metre Spor Türü : Yürüş Toka Türü Toka İlikleme Türü Toka Tasarım Adı Modern Ürünün Biçimi : Yuvarlak Kayış Rengi : Siyah | Q20: #watch, #horology, #saat, #quantum, #spinnaker, #momentus, #casio, #gshock, #saatler, #ck, #calvinklein, #buler, #automatic, #vintage, #panda, #drives, #bulova | R20: @anbeanwatch | S20: https://instagram.com/p/DVpBbInjEmX, https://instagram.com/p/DV1924ajAiZ, https://instagram.com/p/DV18gFmjDm7, https://instagram.com/p/DV17erXDCku, https://instagram.com/p/DV16Fh6jCTa, https://instagram.com/p/DVbOAeWjLiA, https://instagram.com/p/DVbNeY1jKvV, https://instagram.com/p/DVbM_R8jJbK, https://instagram.com/p/DVbMdHyjN1c, https://instagram.com/p/DVW0DoFDI-M, https://instagram.com/p/DVWzxFxjKFg, https://instagram.com/p/DVWzd9vDEzD | T20: 6, 4, 3, 4, 4, 12, 14, 9, 5, 8, 5, 2 | U20: 0, 0, 0, 0, 0, 0, 0, 0, 0, 0, 0, 0 | V20: 2026-03-08, 2026-03-13, 2026-03-13, 2026-03-13, 2026-03-13, 2026-03-03, 2026-03-03, 2026-03-03, 2026-03-03, 2026-03-01, 2026-03-01, 2026-03-01 | X20: Video, Sidecar, Sidecar, Sidecar, Sidecar, Sidecar, Sidecar, Sidecar, Sidecar, Sidecar, Sidecar, Sidecar | Y20: https://scontent-iad3-1.cdninstagram.com/v/t51.82787-15/650834480_18038868173587845_3954419809362465568_n.jpg?stp=dst-jpg_e35_s1080x1080_sh0.08_tt6&_nc_ht=scontent-iad3-1.cdninstagram.com&_nc_cat=109&_nc_oc=Q6cZ2QEIz-E0Ih9sLOV7KGa83NmqJf7-90tn_Z2qmERv0e_qwIHJuFjP_cN3kdSpDbObOBo&_nc_ohc=H0RjJ-6VJ3kQ7kNvwGvihOf&_nc_gid=Cmq0dIyiMgU1ta5CTdbUTA&edm=AOQ1c0wBAAAA&ccb=7-5&ig_cache_key=Mzg1MjI1Njk3NTM4ODQ0NDExNg%3D%3D.3-ccb7-5&oh=00_Afwh1CYCauyvzFD90r5VwAx2ZNN1jgbknAivQ-R51aAung&oe=69BD91A0&_nc_sid=8b3546, https://scontent-iad3-1.cdninstagram.com/v/t51.82787-15/650834480_18038868173587845_3954419809362465568_n.jpg?stp=dst-jpg_e35_s1080x1080_sh0.08_tt6&_nc_ht=scontent-iad3-1.cdninstagram.com&_nc_cat=109&_nc_oc=Q6cZ2QEIz-E0Ih9sLOV7KGa83NmqJf7-90tn_Z2qmERv0e_qwIHJuFjP_cN3kdSpDbObOBo&_nc_ohc=H0RjJ-6VJ3kQ7kNvwGvihOf&_nc_gid=Cmq0dIyiMgU1ta5CTdbUTA&edm=AOQ1c0wBAAAA&ccb=7-5&ig_cache_key=Mzg1MjI1Njk3NTM4ODQ0NDExNg%3D%3D.3-ccb7-5&oh=00_Afwh1CYCauyvzFD90r5VwAx2ZNN1jgbknAivQ-R51aAung&oe=69BD91A0&_nc_sid=8b3546, https://scontent-iad3-1.cdninstagram.com/v/t51.82787-15/650818308_18038868164587845_3154095423224750124_n.jpg?stp=dst-jpg_e35_s1080x1080_sh0.08_tt6&_nc_ht=scontent-iad3-1.cdninstagram.com&_nc_cat=109&_nc_oc=Q6cZ2QEIz-E0Ih9sLOV7KGa83NmqJf7-90tn_Z2qmERv0e_qwIHJuFjP_cN3kdSpDbObOBo&_nc_ohc=vPe5ekXW3WAQ7kNvwFZipJ9&_nc_gid=Cmq0dIyiMgU1ta5CTdbUTA&edm=AOQ1c0wBAAAA&ccb=7-5&ig_cache_key=Mzg1MjI1Njk3ODEzMTUyODY4MQ%3D%3D.3-ccb7-5&oh=00_Afzcg7cuM7WCZ92-AQ8hhmT7emD29O3bG4mIZUQMFGhzkg&oe=69BD85EA&_nc_sid=8b3546, https://scontent-iad3-1.cdninstagram.com/v/t51.82787-15/649917669_18038867111587845_6460961138924917536_n.jpg?stp=dst-jpg_e35_s1080x1080_sh0.08_tt6&_nc_ht=scontent-iad3-1.cdninstagram.com&_nc_cat=109&_nc_oc=Q6cZ2QEIz-E0Ih9sLOV7KGa83NmqJf7-90tn_Z2qmERv0e_qwIHJuFjP_cN3kdSpDbObOBo&_nc_ohc=NmLk4sG25SMQ7kNvwGR-avO&_nc_gid=Cmq0dIyiMgU1ta5CTdbUTA&edm=AOQ1c0wBAAAA&ccb=7-5&ig_cache_key=Mzg1MjI1MDkwNzAzNTgyOTc5NA%3D%3D.3-ccb7-5&oh=00_AfwfU3BoQml5iThM6Teew_xH5CAuvqcwvZsX9AenjnPeig&oe=69BDA6E2&_nc_sid=8b3546, https://scontent-iad3-1.cdninstagram.com/v/t51.82787-15/649917669_18038867111587845_6460961138924917536_n.jpg?stp=dst-jpg_e35_s1080x1080_sh0.08_tt6&_nc_ht=scontent-iad3-1.cdninstagram.com&_nc_cat=109&_nc_oc=Q6cZ2QEIz-E0Ih9sLOV7KGa83NmqJf7-90tn_Z2qmERv0e_qwIHJuFjP_cN3kdSpDbObOBo&_nc_ohc=NmLk4sG25SMQ7kNvwGR-avO&_nc_gid=Cmq0dIyiMgU1ta5CTdbUTA&edm=AOQ1c0wBAAAA&ccb=7-5&ig_cache_key=Mzg1MjI1MDkwNzAzNTgyOTc5NA%3D%3D.3-ccb7-5&oh=00_AfwfU3BoQml5iThM6Teew_xH5CAuvqcwvZsX9AenjnPeig&oe=69BDA6E2&_nc_sid=8b3546, https://scontent-iad3-1.cdninstagram.com/v/t51.82787-15/651665227_18038867126587845_8398402757417879133_n.jpg?stp=dst-jpg_e35_s1080x1080_sh0.08_tt6&_nc_ht=scontent-iad3-1.cdninstagram.com&_nc_cat=109&_nc_oc=Q6cZ2QEIz-E0Ih9sLOV7KGa83NmqJf7-90tn_Z2qmERv0e_qwIHJuFjP_cN3kdSpDbObOBo&_nc_ohc=gTGVoNkpPGgQ7kNvwGQliYK&_nc_gid=Cmq0dIyiMgU1ta5CTdbUTA&edm=AOQ1c0wBAAAA&ccb=7-5&ig_cache_key=Mzg1MjI1MDkxMTM1NTk4ODI1MQ%3D%3D.3-ccb7-5&oh=00_AfyI-ac527ZuP4BH_bWYcUmHjDggFdLme-vv0Y7db3CWAQ&oe=69BDA9E5&_nc_sid=8b3546, https://scontent-iad3-1.cdninstagram.com/v/t51.82787-15/651502027_18038866544587845_7627823882221643897_n.jpg?stp=dst-jpg_e35_s1080x1080_sh0.08_tt6&_nc_ht=scontent-iad3-1.cdninstagram.com&_nc_cat=109&_nc_oc=Q6cZ2QEIz-E0Ih9sLOV7KGa83NmqJf7-90tn_Z2qmERv0e_qwIHJuFjP_cN3kdSpDbObOBo&_nc_ohc=EpDbKyL6aFEQ7kNvwFjTCrJ&_nc_gid=Cmq0dIyiMgU1ta5CTdbUTA&edm=AOQ1c0wBAAAA&ccb=7-5&ig_cache_key=Mzg1MjI0NjM3MjY5MTI0MDY1OA%3D%3D.3-ccb7-5&oh=00_AfxKeZ3-zfYYZQ_AZhGy1eUM5zP9pefANr4e2fTaG9kW4A&oe=69BDA9CF&_nc_sid=8b3546, https://scontent-iad3-1.cdninstagram.com/v/t51.82787-15/651502027_18038866544587845_7627823882221643897_n.jpg?stp=dst-jpg_e35_s1080x1080_sh0.08_tt6&_nc_ht=scontent-iad3-1.cdninstagram.com&_nc_cat=109&_nc_oc=Q6cZ2QEIz-E0Ih9sLOV7KGa83NmqJf7-90tn_Z2qmERv0e_qwIHJuFjP_cN3kdSpDbObOBo&_nc_ohc=EpDbKyL6aFEQ7kNvwFjTCrJ&_nc_gid=Cmq0dIyiMgU1ta5CTdbUTA&edm=AOQ1c0wBAAAA&ccb=7-5&ig_cache_key=Mzg1MjI0NjM3MjY5MTI0MDY1OA%3D%3D.3-ccb7-5&oh=00_AfxKeZ3-zfYYZQ_AZhGy1eUM5zP9pefANr4e2fTaG9kW4A&oe=69BDA9CF&_nc_sid=8b3546, https://scontent-iad3-1.cdninstagram.com/v/t51.82787-15/650393874_18038866559587845_1651816982374130304_n.jpg?stp=dst-jpg_e35_s1080x1080_sh0.08_tt6&_nc_ht=scontent-iad3-1.cdninstagram.com&_nc_cat=109&_nc_oc=Q6cZ2QEIz-E0Ih9sLOV7KGa83NmqJf7-90tn_Z2qmERv0e_qwIHJuFjP_cN3kdSpDbObOBo&_nc_ohc=iE-nV_TRnlsQ7kNvwGmptol&_nc_gid=Cmq0dIyiMgU1ta5CTdbUTA&edm=AOQ1c0wBAAAA&ccb=7-5&ig_cache_key=Mzg1MjI0NjM3MjkyNjE1NDI1NQ%3D%3D.3-ccb7-5&oh=00_AfyJfpvTxzhnvWPlvyYHdsqiA_Br51oyj_85B9oYfFw_RQ&oe=69BD9A33&_nc_sid=8b3546, https://scontent-iad3-1.cdninstagram.com/v/t51.82787-15/651444382_18038865701587845_1794996339760690535_n.jpg?stp=dst-jpg_e35_s1080x1080_sh0.08_tt6&_nc_ht=scontent-iad3-1.cdninstagram.com&_nc_cat=109&_nc_oc=Q6cZ2QEIz-E0Ih9sLOV7KGa83NmqJf7-90tn_Z2qmERv0e_qwIHJuFjP_cN3kdSpDbObOBo&_nc_ohc=yVJWbDecDQYQ7kNvwGFTM-V&_nc_gid=Cmq0dIyiMgU1ta5CTdbUTA&edm=AOQ1c0wBAAAA&ccb=7-5&ig_cache_key=Mzg1MjI0MDE5MTAzMzc1NTUwNg%3D%3D.3-ccb7-5&oh=00_AfzB6bWmzcoTQczaelJqEsYo0BNdX8OTfof4DRrMEkaKb | Z20: https://scontent-iad3-1.cdninstagram.com/o1/v/t16/f2/m69/AQPn6AGMa_YX4yt8h03jPdJarfFKG9jeD5IabEtUIfJ8rDmE8SWp0N5zvvz5PWaLZSBZs1yXcl3snd4jcz0mTv16.mp4?strext=1&_nc_cat=102&_nc_sid=5e9851&_nc_ht=scontent-iad3-1.cdninstagram.com&_nc_ohc=1q6pYzz_L3wQ7kNvwHQCjAG&efg=eyJ2ZW5jb2RlX3RhZyI6Inhwdl9wcm9ncmVzc2l2ZS5JTlNUQUdSQU0uQ0xJUFMuQzMuNzIwLmRhc2hfYmFzZWxpbmVfMV92MSIsInhwdl9hc3NldF9pZCI6MTgwMzc4ODY4NzA1ODc4NDUsImFzc2V0X2FnZV9kYXlzIjo3LCJ2aV91c2VjYXNlX2lkIjoxMDA5OSwiZHVyYXRpb25fcyI6NCwidXJsZ2VuX3NvdXJjZSI6Ind3dyJ9&ccb=17-1&_nc_gid=Cmq0dIyiMgU1ta5CTdbUTA&_nc_ss=1a&_nc_zt=28&vs=f189ec3eeaae3b0b&_nc_vs=HBkcFQIYOnBhc3N0aHJvdWdoX2V2ZXJzdG9yZS9HTDU5cHlhc2tjV3VEV0lGQUVYQWFQR2EtME5vYnNwVEFRQUYVAALIARIAKAAYABsCiAd1c2Vfb2lsATEScHJvZ3Jlc3NpdmVfcmVjaXBlATEVAAAmiqfc9pnXikAVAigCQzMsF0AQAAAAAAAAGBJkYXNoX2Jhc2VsaW5lXzFfdjERAHX-B2XmnQEA&oh=00_AfyHKp4BgbrVJXQRjIHaTspl7tRfXibRU4cuqpUsThzJtg&oe=69BD841E | AA20: 6 | AB20: 0 | AC20: 46097 | AD20: loupethis | AE20: collector_page | AF20: https://www.instagram.com/anbeanwatch
